Workbook

Sheet 00 START HERE
A1: SAKSHI FORGE | ELECTROPOLISHED PIPE CITY-PAGE PROGRAMME
A2: 2,159 pages · 18 countries · one URL per city · built for uniqueness, not volume
A4: THE OBJECTIVE: GOOGLE TRUSTS THIS SITE
A5: What earns trust | B5: Not page count. A site earns trust when each page tells a reader something they could not get from the other 1,831 pages. Every mechanism in this workbook exists to force that outcome and to let you measure whether you achieved it.
A6: Structure decision | B6: ONE URL per city. Manufacturer, supplier and wholesaler are covered as three distinct H2 sections on that page, with their own body copy and their own FAQ. Sheet 03 shows all 21 keyword variants mapped to the section that targets them. Three URLs per city would have been the same buyer, same need, same answer - which is how Google defines a doorway page regardless of how differently the text is worded.
A8: THE UNIQUENESS ENGINE - WHAT CHANGED IN THIS VERSION
A9: The problem it solves | B9: A city page programme fails when the only variable is the city name. This build attacks that from four directions at once, so no two pages share a structure OR a data set.
A10: Mechanism | B10: How it works
A11: 8 unique data fields | B11: Every page carries 8 researched, city-only facts - estates, lead estate, industry mix, tag, gateway, transit note, local regulator, local proof point. These are the sentences that break when you swap the city name. | G11: 1,832 x 8 = 14,656 facts | H11: Informational uniqueness
A12: Pattern rotation | B12: Title suffix, meta template and H2 phrasing are assigned by position using coprime moduli, so structurally adjacent pages never share a template. | G12: 8 titles x 7 metas x 5 H2 sets | H12: Structural uniqueness
A13: Content angle | B13: The page shape changes with the dominant local industry. A Baddi page leads on formulations and packaging; a Kulim page leads on wafer fab and SEMI F19. Different sections, standards, grades, images. | G13: 8 angles | H13: Editorial uniqueness
A14: FAQ set assignment | B14: Each city is pre-assigned a named set from the 48-template bank, rotated so neighbouring cities overlap by less than half. | G14: 6 sets per tier | H14: Q&A uniqueness
A15: Measured, not claimed | B15: Column U of the CITY MASTER writes a pattern fingerprint for every page and column V counts how many other pages share it. Sheet 17 UNIQUENESS AUDIT turns that into a scorecard. If the number is wrong you will see it before Google does.
A17: THE HONEST COST
A18: Research load | B18: 484 rows arrive with real desk-researched data. 1,348 rows are seeded with placeholders and need local research. At roughly 20 minutes per city that is about 449 hours. You have said you will do it - sheet 13 is the worklist and it names the exact source to use for every state and country.
A19: The rule that protects you | B19: A row whose Data Status still reads VERIFY must not be published. Not as a thin page, not as a placeholder. Cut the city instead. One doorway page in a batch can pull the whole batch down with it.
A20: Pace | B20: 60 pages per week, 31 waves. This is not a launch, it is a build-out. The pace is itself a trust signal - and it gives you a feedback loop at wave 3 instead of a nasty surprise at page 1,800.
A22: SHEET INDEX
A23: 01 PAGE INVENTORY | B23: Counts by country and tier, live from the CITY MASTER.
A24: 02 CITY MASTER | B24: 1,832 rows. 8 research fields + rotation assignment + every generated SEO field.
A25: 03 KEYWORD MAP | B25: 21 keyword variants per city, each mapped to the page section that targets it.
A26: 04 PAGE BLUEPRINT | B26: Section-by-section wireframe with word budgets by tier.
A27: 05 CONTENT RULES | B27: The find-and-replace test and the five fields that carry uniqueness.
A28: 06 FAQ BANK | B28: 48 templates plus the FAQ SET assignment table.
A29: 07 SCHEMA LIBRARY | B29: Six JSON-LD blocks, copy-paste ready.
A30: 08 CALCULATORS | B30: Competitor tool audit plus build spec for 12 tools.
A31: 09 IMAGE & ALT | B31: Image slots, alt patterns, filename rules.
A32: 10 INTERNAL LINKING | B32: Silo depth, link counts, anchor diversity.
A33: 11 TECH SEO + HREFLANG | B33: Staged checklist. Stage 0 blocks everything.
A34: 12 SUPPORTING PAGES | B34: 327 non-city URLs.
... A39: 17 UNIQUENESS AUDIT | B39: Live scorecard proving the pages are not clones.

Sheet 01 PAGE INVENTORY
A1: PAGE INVENTORY BY MARKET
A2: Counts are COUNTIFS against the CITY MASTER - they move as you work
A4: Country | B4: Tier A | C4: Tier B | D4: Tier C | E4: Total city pages | F4: Data complete | G4: Research outstanding | H4: Waves | I4: Compliance anchor for this market
A5: India | B5: =COUNTIFS('02 CITY MASTER'!$B:$B,$A5,'02 CITY MASTER'!$F:$F,"A") -> 139 | C5: =COUNTIFS('02 CITY MASTER'!$B:$B,$A5,'02 CITY MASTER'!$F:$F,"B") -> 397 | D5: =COUNTIFS('02 CITY MASTER'!$B:$B,$A5,'02 CITY MASTER'!$F:$F,"C") -> 440 | E5: =SUM(B5:D5) -> 976 | F5: =COUNTIFS('02 CITY MASTER'!$B:$B,$A5,'02 CITY MASTER'!$G:$G,"VERIFIED") -> 139 | G5: =E5-F5 -> 837 | H5: =ROUNDUP(E5/60,0) -> 17 | I5: BIS; CDSCO/state FDA for pharma; FSSAI for food and dairy; buyer-specified ASTM A270 and ASME BPE
A6: UAE | B6: =COUNTIFS('02 CITY MASTER'!$B:$B,$A6,'02 CITY MASTER'!$F:$F,"A") -> 6 | C6: =COUNTIFS('02 CITY MASTER'!$B:$B,$A6,'02 CITY MASTER'!$F:$F,"B") -> 6 | D6: =COUNTIFS('02 CITY MASTER'!$B:$B,$A6,'02 CITY MASTER'!$F:$F,"C") -> 10 | E6: =SUM(B6:D6) -> 22 | F6: =COUNTIFS('02 CITY MASTER'!$B:$B,$A6,'02 CITY MASTER'!$G:$G,"VERIFIED") -> 12 | G6: =E6-F6 -> 10 | H6: =ROUNDUP(E6/60,0) -> 1 | I6: ASME BPE, ASTM A270, EN 10204 3.1, ESMA conformity, Halal-plant hygiene norms
A7: Saudi Arabia | B7: =COUNTIFS('02 CITY MASTER'!$B:$B,$A7,'02 CITY MASTER'!$F:$F,"A") -> 8 | C7: =COUNTIFS('02 CITY MASTER'!$B:$B,$A7,'02 CITY MASTER'!$F:$F,"B") -> 12 | D7: =COUNTIFS('02 CITY MASTER'!$B:$B,$A7,'02 CITY MASTER'!$F:$F,"C") -> 20 | E7: =SUM(B7:D7) -> 40 | F7: =COUNTIFS('02 CITY MASTER'!$B:$B,$A7,'02 CITY MASTER'!$G:$G,"VERIFIED") -> 20 | G7: =E7-F7 -> 20 | H7: =ROUNDUP(E7/60,0) -> 1 | I7: ASME BPE, ASTM A270, EN 10204 3.1, SASO / SABER certificate of conformity mandatory
A8: Qatar | B8: =COUNTIFS('02 CITY MASTER'!$B:$B,$A8,'02 CITY MASTER'!$F:$F,"A") -> 4 | C8: =COUNTIFS('02 CITY MASTER'!$B:$B,$A8,'02 CITY MASTER'!$F:$F,"B") -> 4 | D8: =COUNTIFS('02 CITY MASTER'!$B:$B,$A8,'02 CITY MASTER'!$F:$F,"C") -> 4 | E8: =SUM(B8:D8) -> 12 | F8: =COUNTIFS('02 CITY MASTER'!$B:$B,$A8,'02 CITY MASTER'!$G:$G,"VERIFIED") -> 8 | G8: =E8-F8 -> 4 | H8: =ROUNDUP(E8/60,0) -> 1 | I8: ASME BPE, ASTM A270, EN 10204 3.1, QS conformity
A9: Oman | B9: =COUNTIFS('02 CITY MASTER'!$B:$B,$A9,'02 CITY MASTER'!$F:$F,"A") -> 5 | C9: =COUNTIFS('02 CITY MASTER'!$B:$B,$A9,'02 CITY MASTER'!$F:$F,"B") -> 6 | D9: =COUNTIFS('02 CITY MASTER'!$B:$B,$A9,'02 CITY MASTER'!$F:$F,"C") -> 10 | E9: =SUM(B9:D9) -> 21 | F9: =COUNTIFS('02 CITY MASTER'!$B:$B,$A9,'02 CITY MASTER'!$G:$G,"VERIFIED") -> 11 | G9: =E9-F9 -> 10 | H9: =ROUNDUP(E9/60,0) -> 1 | I9: ASME BPE, ASTM A270, EN 10204 3.1, DGSM conformity
A10: Kuwait | B10: =COUNTIFS('02 CITY MASTER'!$B:$B,$A10,'02 CITY MASTER'!$F:$F,"A") -> 4 | C10: =COUNTIFS('02 CITY MASTER'!$B:$B,$A10,'02 CITY MASTER'!$F:$F,"B") -> 4 | D10: =COUNTIFS('02 CITY MASTER'!$B:$B,$A10,'02 CITY MASTER'!$F:$F,"C") -> 4 | E10: =SUM(B10:D10) -> 12 | F10: =COUNTIFS('02 CITY MASTER'!$B:$B,$A10,'02 CITY MASTER'!$G:$G,"VERIFIED") -> 8 | G10: =E10-F10 -> 4 | H10: =ROUNDUP(E10/60,0) -> 1 | I10: ASME BPE, ASTM A270, EN 10204 3.1, KUCAS conformity scheme
A11: Bahrain | B11: =COUNTIFS('02 CITY MASTER'!$B:$B,$A11,'02 CITY MASTER'!$F:$F,"A") -> 3 | C11: =COUNTIFS('02 CITY MASTER'!$B:$B,$A11,'02 CITY MASTER'!$F:$F,"B") -> 3 | D11: =COUNTIFS('02 CITY MASTER'!$B:$B,$A11,'02 CITY MASTER'!$F:$F,"C") -> 4 | E11: =SUM(B11:D11) -> 10 | F11: =COUNTIFS('02 CITY MASTER'!$B:$B,$A11,'02 CITY MASTER'!$G:$G,"VERIFIED") -> 6 | G11: =E11-F11 -> 4 | H11: =ROUNDUP(E11/60,0) -> 1 | I11: ASME BPE, ASTM A270, EN 10204 3.1, BSMD conformity
A12: USA | B12: =COUNTIFS('02 CITY MASTER'!$B:$B,$A12,'02 CITY MASTER'!$F:$F,"A") -> 16 | C12: =COUNTIFS('02 CITY MASTER'!$B:$B,$A12,'02 CITY MASTER'!$F:$F,"B") -> 30 | D12: =COUNTIFS('02 CITY MASTER'!$B:$B,$A12,'02 CITY MASTER'!$F:$F,"C") -> 60 | E12: =SUM(B12:D12) -> 106 | F12: =COUNTIFS('02 CITY MASTER'!$B:$B,$A12,'02 CITY MASTER'!$G:$G,"VERIFIED") -> 46 | G12: =E12-F12 -> 60 | H12: =ROUNDUP(E12/60,0) -> 2 | I12: ASME BPE SF1-SF6, ASTM A270 S2 pharma grade, 3-A Sanitary Standards, FDA 21 CFR 177, SEMI F19/F17 for semiconductor
A13: UK | B13: =COUNTIFS('02 CITY MASTER'!$B:$B,$A13,'02 CITY MASTER'!$F:$F,"A") -> 12 | C13: =COUNTIFS('02 CITY MASTER'!$B:$B,$A13,'02 CITY MASTER'!$F:$F,"B") -> 20 | D13: =COUNTIFS('02 CITY MASTER'!$B:$B,$A13,'02 CITY MASTER'!$F:$F,"C") -> 60 | E13: =SUM(B13:D13) -> 92 | F13: =COUNTIFS('02 CITY MASTER'!$B:$B,$A13,'02 CITY MASTER'!$G:$G,"VERIFIED") -> 32 | G13: =E13-F13 -> 60 | H13: =ROUNDUP(E13/60,0) -> 2 | I13: ASME BPE, ASTM A270, EN 10217-7, EN 10204 3.1, UKCA marking, PED/UK PER for pressure equipment
A14: Germany | B14: =COUNTIFS('02 CITY MASTER'!$B:$B,$A14,'02 CITY MASTER'!$F:$F,"A") -> 12 | C14: =COUNTIFS('02 CITY MASTER'!$B:$B,$A14,'02 CITY MASTER'!$F:$F,"B") -> 20 | D14: =COUNTIFS('02 CITY MASTER'!$B:$B,$A14,'02 CITY MASTER'!$F:$F,"C") -> 60 | E14: =SUM(B14:D14) -> 92 | F14: =COUNTIFS('02 CITY MASTER'!$B:$B,$A14,'02 CITY MASTER'!$G:$G,"VERIFIED") -> 32 | G14: =E14-F14 -> 60 | H14: =ROUNDUP(E14/60,0) -> 2 | I14: EN 10217-7, EN 10357, DIN 11850, ASME BPE, EN 10204 3.1/3.2, PED 2014/68/EU, EHEDG hygienic design
A15: Netherlands | B15: =COUNTIFS('02 CITY MASTER'!$B:$B,$A15,'02 CITY MASTER'!$F:$F,"A") -> 7 | C15: =COUNTIFS('02 CITY MASTER'!$B:$B,$A15,'02 CITY MASTER'!$F:$F,"B") -> 12 | D15: =COUNTIFS('02 CITY MASTER'!$B:$B,$A15,'02 CITY MASTER'!$F:$F,"C") -> 26 | E15: =SUM(B15:D15) -> 45 | F15: =COUNTIFS('02 CITY MASTER'!$B:$B,$A15,'02 CITY MASTER'!$G:$G,"VERIFIED") -> 19 | G15: =E15-F15 -> 26 | H15: =ROUNDUP(E15/60,0) -> 1 | I15: EN 10217-7, EN 10357, ASME BPE, EN 10204 3.1, PED 2014/68/EU, EHEDG
A16: Italy | B16: =COUNTIFS('02 CITY MASTER'!$B:$B,$A16,'02 CITY MASTER'!$F:$F,"A") -> 10 | C16: =COUNTIFS('02 CITY MASTER'!$B:$B,$A16,'02 CITY MASTER'!$F:$F,"B") -> 20 | D16: =COUNTIFS('02 CITY MASTER'!$B:$B,$A16,'02 CITY MASTER'!$F:$F,"C") -> 60 | E16: =SUM(B16:D16) -> 90 | F16: =COUNTIFS('02 CITY MASTER'!$B:$B,$A16,'02 CITY MASTER'!$G:$G,"VERIFIED") -> 30 | G16: =E16-F16 -> 60 | H16: =ROUNDUP(E16/60,0) -> 2 | I16: EN 10217-7, EN 10357, ASME BPE, EN 10204 3.1, PED 2014/68/EU, UNI hygienic norms
... A22: Vietnam | B22: =COUNTIFS('02 CITY MASTER'!$B:$B,$A22,'02 CITY MASTER'!$F:$F,"A") -> 8 | C22: =COUNTIFS('02 CITY MASTER'!$B:$B,$A22,'02 CITY MASTER'!$F:$F,"B") -> 14 | D22: =COUNTIFS('02 CITY MASTER'!$B:$B,$A22,'02 CITY MASTER'!$F:$F,"C") -> 36 | E22: =SUM(B22:D22) -> 58 | F22: =COUNTIFS('02 CITY MASTER'!$B:$B,$A22,'02 CITY MASTER'!$G:$G,"VERIFIED") -> 22 | G22: =E22-F22 -> 36 | H22: =ROUNDUP(E22/60,0) -> 1 | I22: ASME BPE, ASTM A270, TCVN conformity, SEMI F19/F17 for electronics fabs, EN 10204 3.1
A23: TOTAL | B23: =SUM(B5:B22) -> 270 | C23: =SUM(C5:C22) -> 611 | D23: =SUM(D5:D22) -> 951 | E23: =SUM(E5:E22) -> 1832 | F23: =SUM(F5:F22) -> 484 | G23: =SUM(G5:G22) -> 1348
A25: EXPORT CONTEXT PER MARKET - use these on the country hub and in FAQ answers
A26: Country | B26: Gateway port | C26: Sea transit from Nhava Sheva | D26: Incoterm | E26: Regulator | F26: Duty / customs note
A27: UAE | B27: Jebel Ali Port | C27: 10-14 days sea from Nhava Sheva to Jebel Ali | D27: CIF Jebel Ali | E27: MOIAT / ESMA (Emirates Authority for Standardization) | F27: 0-5% GCC common external tariff; India-UAE CEPA preferential rates apply
A28: Saudi Arabia | B28: King Abdulaziz Port Dammam / Jeddah Islamic Port | C28: 12-16 days sea from Nhava Sheva to Dammam | D28: CIF Dammam / Jeddah | E28: SASO with SABER platform registration | F28: 5-15% depending on HS code; SABER CoC required at customs
A29: Qatar | B29: Hamad Port Doha | C29: 12-15 days sea from Nhava Sheva to Hamad Port | D29: CIF Hamad Port | E29: Qatar General Organization for Standards and Metrology | F29: 5% GCC common external tariff
A30: Oman | B30: Port of Sohar / Port of Salalah | C30: 7-10 days sea from Nhava Sheva to Sohar | D30: CIF Sohar / Salalah | E30: Directorate General for Standards and Metrology | F30: 5% GCC common external tariff
A31: Kuwait | B31: Shuwaikh Port / Shuaiba Port | C31: 14-18 days sea from Nhava Sheva to Shuwaikh | D31: CIF Shuwaikh | E31: Public Authority for Industry (PAI) under KUCAS | F31: 5% GCC common external tariff; KUCAS TIR required
A32: Bahrain | B32: Khalifa Bin Salman Port | C32: 13-17 days sea from Nhava Sheva to Khalifa Bin Salman Port | D32: CIF Khalifa Bin Salman | E32: Bahrain Standards and Metrology Directorate | F32: 5% GCC common external tariff
A33: USA | B33: Port of New York/Newark, Port of Houston, Port of LA-Long Beach | C33: 28-35 days sea from Nhava Sheva to US East Coast | D33: CIF / DDP US port | E33: FDA (food/pharma contact), ASME BPE, 3-A SSI | F33: Section 232 steel tariff plus MFN rate; verify current HTS 7306.40 treatment before quoting
A34: UK | B34: Port of Felixstowe / Southampton | C34: 22-28 days sea from Nhava Sheva to Felixstowe | D34: CIF Felixstowe / Southampton | E34: UKCA regime post-Brexit; UK Pressure Equipment (Safety) Regulations | F34: UK Global Tariff; check TRQ on steel
A35: Germany | B35: Port of Hamburg / Bremerhaven | C35: 24-30 days sea from Nhava Sheva to Hamburg | D35: CIF Hamburg / Rotterdam | E35: CE marking under PED 2014/68/EU; AD 2000-Merkblatt for pressure parts | F35: EU CBAM reporting applies to steel from Oct 2023; verify current phase
A36: Netherlands | B36: Port of Rotterdam | C36: 23-29 days sea from Nhava Sheva to Rotterdam | D36: CIF Rotterdam | E36: CE marking under PED 2014/68/EU | F36: EU CBAM reporting applies to steel imports
A37: Italy | B37: Port of Genoa / Port of Trieste | C37: 18-24 days sea from Nhava Sheva to Genoa | D37: CIF Genoa / Trieste | E37: CE marking under PED 2014/68/EU | F37: EU CBAM reporting applies to steel imports
... A43: Vietnam | B43: Hai Phong Port / Cat Lai Ho Chi Minh City | C43: 12-16 days sea from Nhava Sheva to Hai Phong | D43: CIF Hai Phong / Cat Lai | E43: STAMEQ / Ministry of Science and Technology | F43: AIFTA preferential tariff applies

Sheet 02 CITY MASTER
A1: CITY MASTER
A2: AMBER = research and edit by hand. WHITE = formula, never type over. Columns H-O are what make each page unique.
A3: Page ID | B3: Country | C3: State / Region | D3: City | E3: Display Name | F3: Tier | G3: Data Status | H3: 1. Industrial Estates (all real names) | I3: 2. Lead Estate (short) | J3: 3. Dominant Industry Mix | K3: 4. Short Industry Tag | L3: 5. Logistics Gateway | M3: 6. Transit Note | N3: 7. Local Standard / Regulator | O3: 8. Local Proof Point (one true sentence) | P3: Content Angle | Q3: Title Pattern | R3: Meta Pattern | S3: H2 Set | T3: FAQ Set | U3: Pattern Fingerprint | V3: Pages sharing this fingerprint | W3: Slug Override | X3: URL Slug | Y3: Full URL | Z3: Title Tag | AA3: Title QC | AB3: Meta Description | AC3: Meta QC | AD3: H1 | AE3: H2 - Manufacturer | AF3: H2 - Supplier | AG3: H2 - Wholesaler | AH3: Meta Keywords | AI3: OG / Twitter Title | AJ3: OG / Twitter Description | AK3: Hero Image ALT | AL3: Hero Image Title | AM3: Breadcrumb Trail | AN3: Word Target | AO3: Min FAQs | AP3: Min Internal Links | AQ3: Rollout Wave | AR3: Title Override | AS3: Meta Description Override | AT3: Build Status | AU3: Indexed in GSC
A4: CTY-0001 | B4: India | C4: Uttar Pradesh | D4: Agra | E4: Agra | F4: A | G4: VERIFIED | H4: Sikandra Industrial Area, Runakta UPSIDA | I4: Sikandra Industrial Area | J4: Leather, food processing, engineering | K4: food processing | L4: ICD Dadri (180 km) | M4: 1-2 day road transit from our Mumbai works | N4: FSSAI licensing; 3-A Sanitary Standards on product-contact lines | O4: VERIFY | P4: =IF($K4="VERIFY","VERIFY",IF(ISNUMBER(SEARCH("semicon",$K4)),"SEMI",IF(ISNUMBER(SEARCH("electronic",$K4)),"SEMI",IF(ISNUMBER(SEARCH("biotech",$K4)),"BIOTECH",IF(ISNUMBER(SEARCH("pharma",$K4)),"PHARMA",IF(ISNUMBER(SEARCH("medical",$K4)),"PHARMA",IF(ISNUMBER(SEARCH("dairy",$K4)),"DAIRY",IF(ISNUMBER(SEARCH("brewery",$K4)),"BREWERY",IF(ISNUMBER(SEARCH("food",$K4)),"FOOD",IF(ISNUMBER(SEARCH("personal care",$K4)),"FOOD",IF(ISNUMBER(SEARCH("chemical",$K4)),"CHEM",IF(ISNUMBER(SEARCH("refining",$K4)),"CHEM",IF(ISNUMBER(SEARCH("petrochem",$K4)),"CHEM",IF(ISNUMBER(SEARCH("fertilis",$K4)),"CHEM",IF(ISNUMBER(SEARCH("water",$K4)),"CHEM","GENERAL"))))))))))))))) -> FOOD | Q4: =MOD(ROW()-4,8)+1 -> 1 | R4: =MOD(ROW()-4,7)+1 -> 1 | S4: =MOD(ROW()-4,5)+1 -> 1 | T4: =$F4&"-"&(MOD(ROW()-4,6)+1) -> A-1 | U4: ="T"&$Q4&"-M"&$R4&"-H"&$S4&"-F"&$T4&"-"&$P4 -> T1-M1-H1-FA-1-FOOD | V4: =COUNTIF($U$4:$U$1835,$U4)-1 -> 0 | X4: =IF($W4<>"",$W4,IF($B4="India",LOWER(SUBSTITUTE(SUBSTITUTE($D4," ","-"),".","")),LOWER(SUBSTITUTE(SUBSTITUTE($D4," ","-"),".",""))&"-"&LOWER(SUBSTITUTE($B4," ","-")))) -> agra | Y4: ="https://steelmanufacturer.in/market-area/electropolished-pipes-manufacturer-in-"&$X4&"/" -> https://steelmanufacturer.in/market-area/electropolished-pipes-manufacturer-in-agra/ | Z4: =IF($AR4<>"",$AR4,IF(LEN("Electropolished Pipes Manufacturer in "&$E4&CHOOSE($Q4," | Sakshi Forge"," - ASTM A270 & ASME BPE"," | EP Tube Supplier"," - SS 304/316L EP Tube"," | Sanitary Tube Supply"," - Mill Certified Supply"," | ASME BPE SF1-SF4"," - EP Tube Stockist"))<=65,"Electropolished Pipes Manufacturer in "&$E4&CHOOSE($Q4," | Sakshi Forge"," - ASTM A270 & ASME BPE"," | EP Tube Supplier"," - SS 304/316L EP Tube"," | Sanitary Tube Supply"," - Mill Certified Supply"," | ASME BPE SF1-SF4"," - EP Tube Stockist"),"Electropolished Pipes Manufacturer in "&$E4)) -> Electropolished Pipes Manufacturer in Agra | Sakshi Forge | AA4: =IF(LEN($Z4)>65,"TRIM ("&LEN($Z4)&")",IF(LEN($Z4)<35,"SHORT ("&LEN($Z4)&")","OK ("&LEN($Z4)&")")) -> OK (57) | AB4: =IF($AS4<>"",$AS4,CHOOSE($R4,"EP-finished SS 304/316L pipes & tubes for "&$K4&" plants in "&$E4&". ASTM A270, ASME BPE SF1-SF4, EN 10204 3.1 MTC. PMI tested.","Electropolished tube supply to "&$I4&", "&$E4&". Ra from 0.25 um, SF4 finish, mill test certificate with every lot.","EP stainless tube for "&$K4&" lines in "&$E4&". "&$M4&". ASTM A270 S2, PMI tested, EN 10204 3.1.","Sanitary electropolished pipes in "&$E4&" for "&$K4&" plants. ASME BPE SF1-SF4, orbital-weld ready, 3.1 MTC. Mumbai-made.","Manufacturer of electropolished SS 316L tube serving "&$E4&". "&$M4&". Ra 0.25-0.5 um, EN 10204 3.1 MTC.",IF(LEN("EP tube and pipe for "&$K4&" plants around "&$I4&", "&$E4&". Made at our Mumbai works to ASTM A270 and ASME BPE SF1-SF4, with 3.1 MTC.")<=160,"EP tube and pipe for "&$K4&" plants around "&$I4&", "&$E4&". Made at our Mumbai works to ASTM A270 and ASME BPE SF1-SF4, with 3.1 MTC.","EP tube and pipe for "&$K4&" plants around "&$I4&", "&$E4&". ASTM A270, ASME BPE SF1-SF4, EN 10204 3.1 MTC."),"Electropolished pipes in "&$E4&": 304, 304L, 316 and 316L in SF1-SF4. "&$M4&". Mill certified.")) -> EP-finished SS 304/316L pipes & tubes for food processing plants in Agra. ASTM A270, ASME BPE SF1-SF4, EN 10204 3.1 MTC. PMI tested. | AC4: =IF($G4="VERIFY","PENDING RESEARCH",IF(LEN($AB4)>160,"TRIM ("&LEN($AB4)&")",IF(LEN($AB4)<110,"SHORT ("&LEN($AB4)&")","OK ("&LEN($AB4)&")"))) -> OK (132) | AD4: ="Electropolished Pipes Manufacturer in "&$E4 -> Electropolished Pipes Manufacturer in Agra | AE4: =CHOOSE($S4,"Electropolished Pipe & Tube Manufacturing for "&$E4&" - Grades, Finishes & Certification","How We Manufacture Electropolished Tube for "&$E4&" Plants","Electropolished Pipes Manufacturer in "&$E4&" - Our Process & Capability","Manufacturing Electropolished SS Tube for "&$E4&": The Standards We Build To","Electropolished Tube Manufacturing Capability Serving "&$E4) -> Electropolished Pipe & Tube Manufacturing for Agra - Grades, Finishes & Certification | AF4: =CHOOSE($S4,"Electropolished Pipes Supplier in "&$E4&" - Stock Sizes, Lead Time & Delivery","Supplying Electropolished Pipes in "&$E4&": Availability, Sizes & Dispatch","Electropolished Pipes Supplier in "&$E4&" - What We Hold in Stock","Electropolished Pipe Supply Into "&$E4&" - Certification & Transit","Electropolished Pipes Supplier in "&$E4&" - From Order to Delivery") -> Electropolished Pipes Supplier in Agra - Stock Sizes, Lead Time & Delivery | AG4: =CHOOSE($S4,"Electropolished Pipes Wholesaler & Stockist in "&$E4&" - Bulk & Project Pricing","Wholesale Electropolished Pipe Supply for "&$E4&" Projects","Bulk & Wholesale Electropolished Pipe Rates for "&$E4&" Buyers","Electropolished Pipes Wholesaler in "&$E4&" - Project Quantities & Terms","Stockist & Wholesale Supply of Electropolished Pipes in "&$E4) -> Electropolished Pipes Wholesaler & Stockist in Agra - Bulk & Project Pricing | AH4: ="electropolished pipes manufacturer in "&$D4&", electropolished pipes supplier in "&$D4&", electropolished pipes wholesaler in "&$D4&", electropolished tube manufacturer "&$D4&", EP pipe supplier "&$D4&", sanitary tube supplier "&$D4&", ASME BPE tubing "&$D4&", ASTM A270 tube "&$D4&", SS 316L electropolished pipe "&$D4 -> electropolished pipes manufacturer in Agra, electropolished pipes supplier in Agra, electropolished pipes wholesaler in Agra, electropolished tube manufacturer Agra, EP pipe supplier Agra, sanitary tube supplier Agra, ASME BPE tubing Agra, ASTM A270 tube Agra, SS 316L electropolished pipe Agra | AI4: ="Electropolished Pipes Manufacturer & Supplier in "&$E4 -> Electropolished Pipes Manufacturer & Supplier in Agra | AJ4: ="EP-finished SS 304/316L pipes and tubes for "&$K4&" plants in "&$E4&". ASME BPE SF1-SF4, Ra from 0.25 um, EN 10204 3.1 certificate with every lot." -> EP-finished SS 304/316L pipes and tubes for food processing plants in Agra. ASME BPE SF1-SF4, Ra from 0.25 um, EN 10204 3.1 certificate with every lot. | AK4: ="Electropolished stainless steel pipes supplied by Sakshi Forge to "&$K4&" plants at "&$I4&", "&$E4 -> Electropolished stainless steel pipes supplied by Sakshi Forge to food processing plants at Sikandra Industrial Area, Agra | AL4: ="Electropolished SS 316L tube stock for "&$E4&" - Sakshi Forge" -> Electropolished SS 316L tube stock for Agra - Sakshi Forge | AM4: ="Home > Market Area > "&$B4&" > "&$C4&" > "&$D4 -> Home > Market Area > India > Uttar Pradesh > Agra | AN4: =IF($F4="A",1400,IF($F4="B",1000,750)) -> 1400 | AO4: =IF($F4="A",10,IF($F4="B",8,6)) -> 10 | AP4: =IF($F4="A",12,IF($F4="B",8,6)) -> 12 | AQ4: =ROUNDUP((ROW()-3)/60,0) -> 1 | AT4: Not started
A5: CTY-0002 | B5: India | C5: Gujarat | D5: Ahmedabad | E5: Ahmedabad | F5: A | G5: VERIFIED | H5: Odhav GIDC, Vatva GIDC, Naroda GIDC, Changodar | I5: Odhav GIDC | J5: Pharmaceutical formulations, dyes and intermediates, food processing | K5: pharma | L5: Mundra Port (350 km) | M5: 2-3 day road transit from our Mumbai works | N5: CDSCO + state FDA licensed plants; WHO-GMP and USFDA documentation common | O5: VERIFY | P5: =IF($K5="VERIFY","VERIFY",IF(ISNUMBER(SEARCH("semicon",$K5)),"SEMI",IF(ISNUMBER(SEARCH("electronic",$K5)),"SEMI",IF(ISNUMBER(SEARCH("biotech",$K5)),"BIOTECH",IF(ISNUMBER(SEARCH("pharma",$K5)),"PHARMA",IF(ISNUMBER(SEARCH("medical",$K5)),"PHARMA",IF(ISNUMBER(SEARCH("dairy",$K5)),"DAIRY",IF(ISNUMBER(SEARCH("brewery",$K5)),"BREWERY",IF(ISNUMBER(SEARCH("food",$K5)),"FOOD",IF(ISNUMBER(SEARCH("personal care",$K5)),"FOOD",IF(ISNUMBER(SEARCH("chemical",$K5)),"CHEM",IF(ISNUMBER(SEARCH("refining",$K5)),"CHEM",IF(ISNUMBER(SEARCH("petrochem",$K5)),"CHEM",IF(ISNUMBER(SEARCH("fertilis",$K5)),"CHEM",IF(ISNUMBER(SEARCH("water",$K5)),"CHEM","GENERAL"))))))))))))))) -> PHARMA | Q5: =MOD(ROW()-4,8)+1 -> 2 | R5: =MOD(ROW()-4,7)+1 -> 2 | S5: =MOD(ROW()-4,5)+1 -> 2 | T5: =$F5&"-"&(MOD(ROW()-4,6)+1) -> A-2 | U5: ="T"&$Q5&"-M"&$R5&"-H"&$S5&"-F"&$T5&"-"&$P5 -> T2-M2-H2-FA-2-PHARMA | V5: =COUNTIF($U$4:$U$1835,$U5)-1 -> 0 | X5: =IF($W5<>"",$W5,IF($B5="India",LOWER(SUBSTITUTE(SUBSTITUTE($D5," ","-"),".","")),LOWER(SUBSTITUTE(SUBSTITUTE($D5," ","-"),".",""))&"-"&LOWER(SUBSTITUTE($B5," ","-")))) -> ahmedabad | Y5: ="https://steelmanufacturer.in/market-area/electropolished-pipes-manufacturer-in-"&$X5&"/" -> https://steelmanufacturer.in/market-area/electropolished-pipes-manufacturer-in-ahmedabad/ | Z5: =IF($AR5<>"",$AR5,IF(LEN("Electropolished Pipes Manufacturer in "&$E5&CHOOSE($Q5," | Sakshi Forge"," - ASTM A270 & ASME BPE"," | EP Tube Supplier"," - SS 304/316L EP Tube"," | Sanitary Tube Supply"," - Mill Certified Supply"," | ASME BPE SF1-SF4"," - EP Tube Stockist"))<=65,"Electropolished Pipes Manufacturer in "&$E5&CHOOSE($Q5," | Sakshi Forge"," - ASTM A270 & ASME BPE"," | EP Tube Supplier"," - SS 304/316L EP Tube"," | Sanitary Tube Supply"," - Mill Certified Supply"," | ASME BPE SF1-SF4"," - EP Tube Stockist"),"Electropolished Pipes Manufacturer in "&$E5)) -> Electropolished Pipes Manufacturer in Ahmedabad | AA5: =IF(LEN($Z5)>65,"TRIM ("&LEN($Z5)&")",IF(LEN($Z5)<35,"SHORT ("&LEN($Z5)&")","OK ("&LEN($Z5)&")")) -> OK (47) | AB5: =IF($AS5<>"",$AS5,CHOOSE($R5,"EP-finished SS 304/316L pipes & tubes for "&$K5&" plants in "&$E5&". ASTM A270, ASME BPE SF1-SF4, EN 10204 3.1 MTC. PMI tested.","Electropolished tube supply to "&$I5&", "&$E5&". Ra from 0.25 um, SF4 finish, mill test certificate with every lot.","EP stainless tube for "&$K5&" lines in "&$E5&". "&$M5&". ASTM A270 S2, PMI tested, EN 10204 3.1.","Sanitary electropolished pipes in "&$E5&" for "&$K5&" plants. ASME BPE SF1-SF4, orbital-weld ready, 3.1 MTC. Mumbai-made.","Manufacturer of electropolished SS 316L tube serving "&$E5&". "&$M5&". Ra 0.25-0.5 um, EN 10204 3.1 MTC.",IF(LEN("EP tube and pipe for "&$K5&" plants around "&$I5&", "&$E5&". Made at our Mumbai works to ASTM A270 and ASME BPE SF1-SF4, with 3.1 MTC.")<=160,"EP tube and pipe for "&$K5&" plants around "&$I5&", "&$E5&". Made at our Mumbai works to ASTM A270 and ASME BPE SF1-SF4, with 3.1 MTC.","EP tube and pipe for "&$K5&" plants around "&$I5&", "&$E5&". ASTM A270, ASME BPE SF1-SF4, EN 10204 3.1 MTC."),"Electropolished pipes in "&$E5&": 304, 304L, 316 and 316L in SF1-SF4. "&$M5&". Mill certified.")) -> Electropolished tube supply to Odhav GIDC, Ahmedabad. Ra from 0.25 um, SF4 finish, mill test certificate with every lot. | AC5: =IF($G5="VERIFY","PENDING RESEARCH",IF(LEN($AB5)>160,"TRIM ("&LEN($AB5)&")",IF(LEN($AB5)<110,"SHORT ("&LEN($AB5)&")","OK ("&LEN($AB5)&")"))) -> OK (120) | AD5: ="Electropolished Pipes Manufacturer in "&$E5 -> Electropolished Pipes Manufacturer in Ahmedabad | AE5: =CHOOSE($S5,"Electropolished Pipe & Tube Manufacturing for "&$E5&" - Grades, Finishes & Certification","How We Manufacture Electropolished Tube for "&$E5&" Plants","Electropolished Pipes Manufacturer in "&$E5&" - Our Process & Capability","Manufacturing Electropolished SS Tube for "&$E5&": The Standards We Build To","Electropolished Tube Manufacturing Capability Serving "&$E5) -> How We Manufacture Electropolished Tube for Ahmedabad Plants | AF5: =CHOOSE($S5,"Electropolished Pipes Supplier in "&$E5&" - Stock Sizes, Lead Time & Delivery","Supplying Electropolished Pipes in "&$E5&": Availability, Sizes & Dispatch","Electropolished Pipes Supplier in "&$E5&" - What We Hold in Stock","Electropolished Pipe Supply Into "&$E5&" - Certification & Transit","Electropolished Pipes Supplier in "&$E5&" - From Order to Delivery") -> Supplying Electropolished Pipes in Ahmedabad: Availability, Sizes & Dispatch | AG5: =CHOOSE($S5,"Electropolished Pipes Wholesaler & Stockist in "&$E5&" - Bulk & Project Pricing","Wholesale Electropolished Pipe Supply for "&$E5&" Projects","Bulk & Wholesale Electropolished Pipe Rates for "&$E5&" Buyers","Electropolished Pipes Wholesaler in "&$E5&" - Project Quantities & Terms","Stockist & Wholesale Supply of Electropolished Pipes in "&$E5) -> Wholesale Electropolished Pipe Supply for Ahmedabad Projects | AH5: ="electropolished pipes manufacturer in "&$D5&", electropolished pipes supplier in "&$D5&", electropolished pipes wholesaler in "&$D5&", electropolished tube manufacturer "&$D5&", EP pipe supplier "&$D5&", sanitary tube supplier "&$D5&", ASME BPE tubing "&$D5&", ASTM A270 tube "&$D5&", SS 316L electropolished pipe "&$D5 -> electropolished pipes manufacturer in Ahmedabad, electropolished pipes supplier in Ahmedabad, electropolished pipes wholesaler in Ahmedabad, electropolished tube manufacturer Ahmedabad, EP pipe supplier Ahmedabad, sanitary tube supplier Ahmedabad, ASME BPE tubing Ahmedabad, ASTM A270 tube Ahmedabad, SS 316L electropolished pipe Ahmedabad | AI5: ="Electropolished Pipes Manufacturer & Supplier in "&$E5 -> Electropolished Pipes Manufacturer & Supplier in Ahmedabad | AJ5: ="EP-finished SS 304/316L pipes and tubes for "&$K5&" plants in "&$E5&". ASME BPE SF1-SF4, Ra from 0.25 um, EN 10204 3.1 certificate with every lot." -> EP-finished SS 304/316L pipes and tubes for pharma plants in Ahmedabad. ASME BPE SF1-SF4, Ra from 0.25 um, EN 10204 3.1 certificate with every lot. | AK5: ="Electropolished stainless steel pipes supplied by Sakshi Forge to "&$K5&" plants at "&$I5&", "&$E5 -> Electropolished stainless steel pipes supplied by Sakshi Forge to pharma plants at Odhav GIDC, Ahmedabad | AL5: ="Electropolished SS 316L tube stock for "&$E5&" - Sakshi Forge" -> Electropolished SS 316L tube stock for Ahmedabad - Sakshi Forge | AM5: ="Home > Market Area > "&$B5&" > "&$C5&" > "&$D5 -> Home > Market Area > India > Gujarat > Ahmedabad | AN5: =IF($F5="A",1400,IF($F5="B",1000,750)) -> 1400 | AO5: =IF($F5="A",10,IF($F5="B",8,6)) -> 10 | AP5: =IF($F5="A",12,IF($F5="B",8,6)) -> 12 | AQ5: =ROUNDUP((ROW()-3)/60,0) -> 1 | AT5: Not started
A6: CTY-0003 | B6: India | C6: Rajasthan | D6: Alwar | E6: Alwar | F6: A | G6: VERIFIED | H6: Alwar RIICO, MIA Alwar, Neemrana Japanese Zone | I6: Alwar RIICO | J6: Automotive, engineering, food processing | K6: food processing | L6: ICD Tughlakabad (150 km) | M6: 1-2 day road transit from our Mumbai works | N6: FSSAI licensing; 3-A Sanitary Standards on product-contact lines | O6: VERIFY | P6: =IF($K6="VERIFY","VERIFY",IF(ISNUMBER(SEARCH("semicon",$K6)),"SEMI",IF(ISNUMBER(SEARCH("electronic",$K6)),"SEMI",IF(ISNUMBER(SEARCH("biotech",$K6)),"BIOTECH",IF(ISNUMBER(SEARCH("pharma",$K6)),"PHARMA",IF(ISNUMBER(SEARCH("medical",$K6)),"PHARMA",IF(ISNUMBER(SEARCH("dairy",$K6)),"DAIRY",IF(ISNUMBER(SEARCH("brewery",$K6)),"BREWERY",IF(ISNUMBER(SEARCH("food",$K6)),"FOOD",IF(ISNUMBER(SEARCH("personal care",$K6)),"FOOD",IF(ISNUMBER(SEARCH("chemical",$K6)),"CHEM",IF(ISNUMBER(SEARCH("refining",$K6)),"CHEM",IF(ISNUMBER(SEARCH("petrochem",$K6)),"CHEM",IF(ISNUMBER(SEARCH("fertilis",$K6)),"CHEM",IF(ISNUMBER(SEARCH("water",$K6)),"CHEM","GENERAL"))))))))))))))) -> FOOD | Q6: =MOD(ROW()-4,8)+1 -> 3 | R6: =MOD(ROW()-4,7)+1 -> 3 | S6: =MOD(ROW()-4,5)+1 -> 3 | T6: =$F6&"-"&(MOD(ROW()-4,6)+1) -> A-3 | U6: ="T"&$Q6&"-M"&$R6&"-H"&$S6&"-F"&$T6&"-"&$P6 -> T3-M3-H3-FA-3-FOOD | V6: =COUNTIF($U$4:$U$1835,$U6)-1 -> 0 | X6: =IF($W6<>"",$W6,IF($B6="India",LOWER(SUBSTITUTE(SUBSTITUTE($D6," ","-"),".","")),LOWER(SUBSTITUTE(SUBSTITUTE($D6," ","-"),".",""))&"-"&LOWER(SUBSTITUTE($B6," ","-")))) -> alwar | Y6: ="https://steelmanufacturer.in/market-area/electropolished-pipes-manufacturer-in-"&$X6&"/" -> https://steelmanufacturer.in/market-area/electropolished-pipes-manufacturer-in-alwar/ | Z6: =IF($AR6<>"",$AR6,IF(LEN("Electropolished Pipes Manufacturer in "&$E6&CHOOSE($Q6," | Sakshi Forge"," - ASTM A270 & ASME BPE"," | EP Tube Supplier"," - SS 304/316L EP Tube"," | Sanitary Tube Supply"," - Mill Certified Supply"," | ASME BPE SF1-SF4"," - EP Tube Stockist"))<=65,"Electropolished Pipes Manufacturer in "&$E6&CHOOSE($Q6," | Sakshi Forge"," - ASTM A270 & ASME BPE"," | EP Tube Supplier"," - SS 304/316L EP Tube"," | Sanitary Tube Supply"," - Mill Certified Supply"," | ASME BPE SF1-SF4"," - EP Tube Stockist"),"Electropolished Pipes Manufacturer in "&$E6)) -> Electropolished Pipes Manufacturer in Alwar | EP Tube Supplier | AA6: =IF(LEN($Z6)>65,"TRIM ("&LEN($Z6)&")",IF(LEN($Z6)<35,"SHORT ("&LEN($Z6)&")","OK ("&LEN($Z6)&")")) -> OK (62) | AB6: =IF($AS6<>"",$AS6,CHOOSE($R6,"EP-finished SS 304/316L pipes & tubes for "&$K6&" plants in "&$E6&". ASTM A270, ASME BPE SF1-SF4, EN 10204 3.1 MTC. PMI tested.","Electropolished tube supply to "&$I6&", "&$E6&". Ra from 0.25 um, SF4 finish, mill test certificate with every lot.","EP stainless tube for "&$K6&" lines in "&$E6&". "&$M6&". ASTM A270 S2, PMI tested, EN 10204 3.1.","Sanitary electropolished pipes in "&$E6&" for "&$K6&" plants. ASME BPE SF1-SF4, orbital-weld ready, 3.1 MTC. Mumbai-made.","Manufacturer of electropolished SS 316L tube serving "&$E6&". "&$M6&". Ra 0.25-0.5 um, EN 10204 3.1 MTC.",IF(LEN("EP tube and pipe for "&$K6&" plants around "&$I6&", "&$E6&". Made at our Mumbai works to ASTM A270 and ASME BPE SF1-SF4, with 3.1 MTC.")<=160,"EP tube and pipe for "&$K6&" plants around "&$I6&", "&$E6&". Made at our Mumbai works to ASTM A270 and ASME BPE SF1-SF4, with 3.1 MTC.","EP tube and pipe for "&$K6&" plants around "&$I6&", "&$E6&". ASTM A270, ASME BPE SF1-SF4, EN 10204 3.1 MTC."),"Electropolished pipes in "&$E6&": 304, 304L, 316 and 316L in SF1-SF4. "&$M6&". Mill certified.")) -> EP stainless tube for food processing lines in Alwar. 1-2 day road transit from our Mumbai works. ASTM A270 S2, PMI tested, EN 10204 3.1. | AC6: =IF($G6="VERIFY","PENDING RESEARCH",IF(LEN($AB6)>160,"TRIM ("&LEN($AB6)&")",IF(LEN($AB6)<110,"SHORT ("&LEN($AB6)&")","OK ("&LEN($AB6)&")"))) -> OK (137) | AD6: ="Electropolished Pipes Manufacturer in "&$E6 -> Electropolished Pipes Manufacturer in Alwar | AE6: =CHOOSE($S6,"Electropolished Pipe & Tube Manufacturing for "&$E6&" - Grades, Finishes & Certification","How We Manufacture Electropolished Tube for "&$E6&" Plants","Electropolished Pipes Manufacturer in "&$E6&" - Our Process & Capability","Manufacturing Electropolished SS Tube for "&$E6&": The Standards We Build To","Electropolished Tube Manufacturing Capability Serving "&$E6) -> Electropolished Pipes Manufacturer in Alwar - Our Process & Capability | AF6: =CHOOSE($S6,"Electropolished Pipes Supplier in "&$E6&" - Stock Sizes, Lead Time & Delivery","Supplying Electropolished Pipes in "&$E6&": Availability, Sizes & Dispatch","Electropolished Pipes Supplier in "&$E6&" - What We Hold in Stock","Electropolished Pipe Supply Into "&$E6&" - Certification & Transit","Electropolished Pipes Supplier in "&$E6&" - From Order to Delivery") -> Electropolished Pipes Supplier in Alwar - What We Hold in Stock | AG6: =CHOOSE($S6,"Electropolished Pipes Wholesaler & Stockist in "&$E6&" - Bulk & Project Pricing","Wholesale Electropolished Pipe Supply for "&$E6&" Projects","Bulk & Wholesale Electropolished Pipe Rates for "&$E6&" Buyers","Electropolished Pipes Wholesaler in "&$E6&" - Project Quantities & Terms","Stockist & Wholesale Supply of Electropolished Pipes in "&$E6) -> Bulk & Wholesale Electropolished Pipe Rates for Alwar Buyers | AH6: ="electropolished pipes manufacturer in "&$D6&", electropolished pipes supplier in "&$D6&", electropolished pipes wholesaler in "&$D6&", electropolished tube manufacturer "&$D6&", EP pipe supplier "&$D6&", sanitary tube supplier "&$D6&", ASME BPE tubing "&$D6&", ASTM A270 tube "&$D6&", SS 316L electropolished pipe "&$D6 -> electropolished pipes manufacturer in Alwar, electropolished pipes supplier in Alwar, electropolished pipes wholesaler in Alwar, electropolished tube manufacturer Alwar, EP pipe supplier Alwar, sanitary tube supplier Alwar, ASME BPE tubing Alwar, ASTM A270 tube Alwar, SS 316L electropolished pipe Alwar | AI6: ="Electropolished Pipes Manufacturer & Supplier in "&$E6 -> Electropolished Pipes Manufacturer & Supplier in Alwar | AJ6: ="EP-finished SS 304/316L pipes and tubes for "&$K6&" plants in "&$E6&". ASME BPE SF1-SF4, Ra from 0.25 um, EN 10204 3.1 certificate with every lot." -> EP-finished SS 304/316L pipes and tubes for food processing plants in Alwar. ASME BPE SF1-SF4, Ra from 0.25 um, EN 10204 3.1 certificate with every lot. | AK6: ="Electropolished stainless steel pipes supplied by Sakshi Forge to "&$K6&" plants at "&$I6&", "&$E6 -> Electropolished stainless steel pipes supplied by Sakshi Forge to food processing plants at Alwar RIICO, Alwar | AL6: ="Electropolished SS 316L tube stock for "&$E6&" - Sakshi Forge" -> Electropolished SS 316L tube stock for Alwar - Sakshi Forge | AM6: ="Home > Market Area > "&$B6&" > "&$C6&" > "&$D6 -> Home > Market Area > India > Rajasthan > Alwar | AN6: =IF($F6="A",1400,IF($F6="B",1000,750)) -> 1400 | AO6: =IF($F6="A",10,IF($F6="B",8,6)) -> 10 | AP6: =IF($F6="A",12,IF($F6="B",8,6)) -> 12 | AQ6: =ROUNDUP((ROW()-3)/60,0) -> 1 | AT6: Not started
A7: CTY-0004 | B7: India | C7: Haryana | D7: Ambala | E7: Ambala | F7: A | G7: VERIFIED | H7: Ambala Industrial Area, Ambala Cantt Estate | I7: Ambala Industrial Area | J7: Scientific instruments, engineering, mixers | K7: engineering & process | L7: ICD Ludhiana (170 km) | M7: 1-2 day road transit from our Mumbai works | N7: BIS and buyer-specified ASTM A270 / ASME BPE; EN 10204 3.1 MTC standard | O7: VERIFY | P7: =IF($K7="VERIFY","VERIFY",IF(ISNUMBER(SEARCH("semicon",$K7)),"SEMI",IF(ISNUMBER(SEARCH("electronic",$K7)),"SEMI",IF(ISNUMBER(SEARCH("biotech",$K7)),"BIOTECH",IF(ISNUMBER(SEARCH("pharma",$K7)),"PHARMA",IF(ISNUMBER(SEARCH("medical",$K7)),"PHARMA",IF(ISNUMBER(SEARCH("dairy",$K7)),"DAIRY",IF(ISNUMBER(SEARCH("brewery",$K7)),"BREWERY",IF(ISNUMBER(SEARCH("food",$K7)),"FOOD",IF(ISNUMBER(SEARCH("personal care",$K7)),"FOOD",IF(ISNUMBER(SEARCH("chemical",$K7)),"CHEM",IF(ISNUMBER(SEARCH("refining",$K7)),"CHEM",IF(ISNUMBER(SEARCH("petrochem",$K7)),"CHEM",IF(ISNUMBER(SEARCH("fertilis",$K7)),"CHEM",IF(ISNUMBER(SEARCH("water",$K7)),"CHEM","GENERAL"))))))))))))))) -> GENERAL | Q7: =MOD(ROW()-4,8)+1 -> 4 | R7: =MOD(ROW()-4,7)+1 -> 4 | S7: =MOD(ROW()-4,5)+1 -> 4 | T7: =$F7&"-"&(MOD(ROW()-4,6)+1) -> A-4 | U7: ="T"&$Q7&"-M"&$R7&"-H"&$S7&"-F"&$T7&"-"&$P7 -> T4-M4-H4-FA-4-GENERAL | V7: =COUNTIF($U$4:$U$1835,$U7)-1 -> 0 | X7: =IF($W7<>"",$W7,IF($B7="India",LOWER(SUBSTITUTE(SUBSTITUTE($D7," ","-"),".","")),LOWER(SUBSTITUTE(SUBSTITUTE($D7," ","-"),".",""))&"-"&LOWER(SUBSTITUTE($B7," ","-")))) -> ambala | Y7: ="https://steelmanufacturer.in/market-area/electropolished-pipes-manufacturer-in-"&$X7&"/" -> https://steelmanufacturer.in/market-area/electropolished-pipes-manufacturer-in-ambala/ | Z7: =IF($AR7<>"",$AR7,IF(LEN("Electropolished Pipes Manufacturer in "&$E7&CHOOSE($Q7," | Sakshi Forge"," - ASTM A270 & ASME BPE"," | EP Tube Supplier"," - SS 304/316L EP Tube"," | Sanitary Tube Supply"," - Mill Certified Supply"," | ASME BPE SF1-SF4"," - EP Tube Stockist"))<=65,"Electropolished Pipes Manufacturer in "&$E7&CHOOSE($Q7," | Sakshi Forge"," - ASTM A270 & ASME BPE"," | EP Tube Supplier"," - SS 304/316L EP Tube"," | Sanitary Tube Supply"," - Mill Certified Supply"," | ASME BPE SF1-SF4"," - EP Tube Stockist"),"Electropolished Pipes Manufacturer in "&$E7)) -> Electropolished Pipes Manufacturer in Ambala | AA7: =IF(LEN($Z7)>65,"TRIM ("&LEN($Z7)&")",IF(LEN($Z7)<35,"SHORT ("&LEN($Z7)&")","OK ("&LEN($Z7)&")")) -> OK (44) | AB7: =IF($AS7<>"",$AS7,CHOOSE($R7,"EP-finished SS 304/316L pipes & tubes for "&$K7&" plants in "&$E7&". ASTM A270, ASME BPE SF1-SF4, EN 10204 3.1 MTC. PMI tested.","Electropolished tube supply to "&$I7&", "&$E7&". Ra from 0.25 um, SF4 finish, mill test certificate with every lot.","EP stainless tube for "&$K7&" lines in "&$E7&". "&$M7&". ASTM A270 S2, PMI tested, EN 10204 3.1.","Sanitary electropolished pipes in "&$E7&" for "&$K7&" plants. ASME BPE SF1-SF4, orbital-weld ready, 3.1 MTC. Mumbai-made.","Manufacturer of electropolished SS 316L tube serving "&$E7&". "&$M7&". Ra 0.25-0.5 um, EN 10204 3.1 MTC.",IF(LEN("EP tube and pipe for "&$K7&" plants around "&$I7&", "&$E7&". Made at our Mumbai works to ASTM A270 and ASME BPE SF1-SF4, with 3.1 MTC.")<=160,"EP tube and pipe for "&$K7&" plants around "&$I7&", "&$E7&". Made at our Mumbai works to ASTM A270 and ASME BPE SF1-SF4, with 3.1 MTC.","EP tube and pipe for "&$K7&" plants around "&$I7&", "&$E7&". ASTM A270, ASME BPE SF1-SF4, EN 10204 3.1 MTC."),"Electropolished pipes in "&$E7&": 304, 304L, 316 and 316L in SF1-SF4. "&$M7&". Mill certified.")) -> Sanitary electropolished pipes in Ambala for engineering & process plants. ASME BPE SF1-SF4, orbital-weld ready, 3.1 MTC. Mumbai-made. | AC7: =IF($G7="VERIFY","PENDING RESEARCH",IF(LEN($AB7)>160,"TRIM ("&LEN($AB7)&")",IF(LEN($AB7)<110,"SHORT ("&LEN($AB7)&")","OK ("&LEN($AB7)&")"))) -> OK (134) | AD7: ="Electropolished Pipes Manufacturer in "&$E7 -> Electropolished Pipes Manufacturer in Ambala | AE7: =CHOOSE($S7,"Electropolished Pipe & Tube Manufacturing for "&$E7&" - Grades, Finishes & Certification","How We Manufacture Electropolished Tube for "&$E7&" Plants","Electropolished Pipes Manufacturer in "&$E7&" - Our Process & Capability","Manufacturing Electropolished SS Tube for "&$E7&": The Standards We Build To","Electropolished Tube Manufacturing Capability Serving "&$E7) -> Manufacturing Electropolished SS Tube for Ambala: The Standards We Build To | AF7: =CHOOSE($S7,"Electropolished Pipes Supplier in "&$E7&" - Stock Sizes, Lead Time & Delivery","Supplying Electropolished Pipes in "&$E7&": Availability, Sizes & Dispatch","Electropolished Pipes Supplier in "&$E7&" - What We Hold in Stock","Electropolished Pipe Supply Into "&$E7&" - Certification & Transit","Electropolished Pipes Supplier in "&$E7&" - From Order to Delivery") -> Electropolished Pipe Supply Into Ambala - Certification & Transit | AG7: =CHOOSE($S7,"Electropolished Pipes Wholesaler & Stockist in "&$E7&" - Bulk & Project Pricing","Wholesale Electropolished Pipe Supply for "&$E7&" Projects","Bulk & Wholesale Electropolished Pipe Rates for "&$E7&" Buyers","Electropolished Pipes Wholesaler in "&$E7&" - Project Quantities & Terms","Stockist & Wholesale Supply of Electropolished Pipes in "&$E7) -> Electropolished Pipes Wholesaler in Ambala - Project Quantities & Terms | AH7: ="electropolished pipes manufacturer in "&$D7&", electropolished pipes supplier in "&$D7&", electropolished pipes wholesaler in "&$D7&", electropolished tube manufacturer "&$D7&", EP pipe supplier "&$D7&", sanitary tube supplier "&$D7&", ASME BPE tubing "&$D7&", ASTM A270 tube "&$D7&", SS 316L electropolished pipe "&$D7 -> electropolished pipes manufacturer in Ambala, electropolished pipes supplier in Ambala, electropolished pipes wholesaler in Ambala, electropolished tube manufacturer Ambala, EP pipe supplier Ambala, sanitary tube supplier Ambala, ASME BPE tubing Ambala, ASTM A270 tube Ambala, SS 316L electropolished pipe Ambala | AI7: ="Electropolished Pipes Manufacturer & Supplier in "&$E7 -> Electropolished Pipes Manufacturer & Supplier in Ambala | AJ7: ="EP-finished SS 304/316L pipes and tubes for "&$K7&" plants in "&$E7&". ASME BPE SF1-SF4, Ra from 0.25 um, EN 10204 3.1 certificate with every lot." -> EP-finished SS 304/316L pipes and tubes for engineering & process plants in Ambala. ASME BPE SF1-SF4, Ra from 0.25 um, EN 10204 3.1 certificate with every lot. | AK7: ="Electropolished stainless steel pipes supplied by Sakshi Forge to "&$K7&" plants at "&$I7&", "&$E7 -> Electropolished stainless steel pipes supplied by Sakshi Forge to engineering & process plants at Ambala Industrial Area, Ambala | AL7: ="Electropolished SS 316L tube stock for "&$E7&" - Sakshi Forge" -> Electropolished SS 316L tube stock for Ambala - Sakshi Forge | AM7: ="Home > Market Area > "&$B7&" > "&$C7&" > "&$D7 -> Home > Market Area > India > Haryana > Ambala | AN7: =IF($F7="A",1400,IF($F7="B",1000,750)) -> 1400 | AO7: =IF($F7="A",10,IF($F7="B",8,6)) -> 10 | AP7: =IF($F7="A",12,IF($F7="B",8,6)) -> 12 | AQ7: =ROUNDUP((ROW()-3)/60,0) -> 1 | AT7: Not started
A8: CTY-0005 | B8: India | C8: Maharashtra | D8: Ambernath | E8: Ambernath | F8: A | G8: VERIFIED | H8: Ambernath MIDC (Anand Nagar), Additional Ambernath | I8: Ambernath MIDC (Anand Nagar) | J8: Chemicals, pharma intermediates, engineering | K8: chemical | L8: JNPT Nhava Sheva (60 km) | M8: same-day to next-day road from our Mumbai works | N8: PESO / OISD for hazardous service; IBR where applicable | O8: VERIFY | P8: =IF($K8="VERIFY","VERIFY",IF(ISNUMBER(SEARCH("semicon",$K8)),"SEMI",IF(ISNUMBER(SEARCH("electronic",$K8)),"SEMI",IF(ISNUMBER(SEARCH("biotech",$K8)),"BIOTECH",IF(ISNUMBER(SEARCH("pharma",$K8)),"PHARMA",IF(ISNUMBER(SEARCH("medical",$K8)),"PHARMA",IF(ISNUMBER(SEARCH("dairy",$K8)),"DAIRY",IF(ISNUMBER(SEARCH("brewery",$K8)),"BREWERY",IF(ISNUMBER(SEARCH("food",$K8)),"FOOD",IF(ISNUMBER(SEARCH("personal care",$K8)),"FOOD",IF(ISNUMBER(SEARCH("chemical",$K8)),"CHEM",IF(ISNUMBER(SEARCH("refining",$K8)),"CHEM",IF(ISNUMBER(SEARCH("petrochem",$K8)),"CHEM",IF(ISNUMBER(SEARCH("fertilis",$K8)),"CHEM",IF(ISNUMBER(SEARCH("water",$K8)),"CHEM","GENERAL"))))))))))))))) -> CHEM | Q8: =MOD(ROW()-4,8)+1 -> 5 | R8: =MOD(ROW()-4,7)+1 -> 5 | S8: =MOD(ROW()-4,5)+1 -> 5 | T8: =$F8&"-"&(MOD(ROW()-4,6)+1) -> A-5 | U8: ="T"&$Q8&"-M"&$R8&"-H"&$S8&"-F"&$T8&"-"&$P8 -> T5-M5-H5-FA-5-CHEM | V8: =COUNTIF($U$4:$U$1835,$U8)-1 -> 0 | X8: =IF($W8<>"",$W8,IF($B8="India",LOWER(SUBSTITUTE(SUBSTITUTE($D8," ","-"),".","")),LOWER(SUBSTITUTE(SUBSTITUTE($D8," ","-"),".",""))&"-"&LOWER(SUBSTITUTE($B8," ","-")))) -> ambernath | Y8: ="https://steelmanufacturer.in/market-area/electropolished-pipes-manufacturer-in-"&$X8&"/" -> https://steelmanufacturer.in/market-area/electropolished-pipes-manufacturer-in-ambernath/ | Z8: =IF($AR8<>"",$AR8,IF(LEN("Electropolished Pipes Manufacturer in "&$E8&CHOOSE($Q8," | Sakshi Forge"," - ASTM A270 & ASME BPE"," | EP Tube Supplier"," - SS 304/316L EP Tube"," | Sanitary Tube Supply"," - Mill Certified Supply"," | ASME BPE SF1-SF4"," - EP Tube Stockist"))<=65,"Electropolished Pipes Manufacturer in "&$E8&CHOOSE($Q8," | Sakshi Forge"," - ASTM A270 & ASME BPE"," | EP Tube Supplier"," - SS 304/316L EP Tube"," | Sanitary Tube Supply"," - Mill Certified Supply"," | ASME BPE SF1-SF4"," - EP Tube Stockist"),"Electropolished Pipes Manufacturer in "&$E8)) -> Electropolished Pipes Manufacturer in Ambernath | AA8: =IF(LEN($Z8)>65,"TRIM ("&LEN($Z8)&")",IF(LEN($Z8)<35,"SHORT ("&LEN($Z8)&")","OK ("&LEN($Z8)&")")) -> OK (47) | AB8: =IF($AS8<>"",$AS8,CHOOSE($R8,"EP-finished SS 304/316L pipes & tubes for "&$K8&" plants in "&$E8&". ASTM A270, ASME BPE SF1-SF4, EN 10204 3.1 MTC. PMI tested.","Electropolished tube supply to "&$I8&", "&$E8&". Ra from 0.25 um, SF4 finish, mill test certificate with every lot.","EP stainless tube for "&$K8&" lines in "&$E8&". "&$M8&". ASTM A270 S2, PMI tested, EN 10204 3.1.","Sanitary electropolished pipes in "&$E8&" for "&$K8&" plants. ASME BPE SF1-SF4, orbital-weld ready, 3.1 MTC. Mumbai-made.","Manufacturer of electropolished SS 316L tube serving "&$E8&". "&$M8&". Ra 0.25-0.5 um, EN 10204 3.1 MTC.",IF(LEN("EP tube and pipe for "&$K8&" plants around "&$I8&", "&$E8&". Made at our Mumbai works to ASTM A270 and ASME BPE SF1-SF4, with 3.1 MTC.")<=160,"EP tube and pipe for "&$K8&" plants around "&$I8&", "&$E8&". Made at our Mumbai works to ASTM A270 and ASME BPE SF1-SF4, with 3.1 MTC.","EP tube and pipe for "&$K8&" plants around "&$I8&", "&$E8&". ASTM A270, ASME BPE SF1-SF4, EN 10204 3.1 MTC."),"Electropolished pipes in "&$E8&": 304, 304L, 316 and 316L in SF1-SF4. "&$M8&". Mill certified.")) -> Manufacturer of electropolished SS 316L tube serving Ambernath. same-day to next-day road from our Mumbai works. Ra 0.25-0.5 um, EN 10204 3.1 MTC. | AC8: =IF($G8="VERIFY","PENDING RESEARCH",IF(LEN($AB8)>160,"TRIM ("&LEN($AB8)&")",IF(LEN($AB8)<110,"SHORT ("&LEN($AB8)&")","OK ("&LEN($AB8)&")"))) -> OK (146) | AD8: ="Electropolished Pipes Manufacturer in "&$E8 -> Electropolished Pipes Manufacturer in Ambernath | AE8: =CHOOSE($S8,"Electropolished Pipe & Tube Manufacturing for "&$E8&" - Grades, Finishes & Certification","How We Manufacture Electropolished Tube for "&$E8&" Plants","Electropolished Pipes Manufacturer in "&$E8&" - Our Process & Capability","Manufacturing Electropolished SS Tube for "&$E8&": The Standards We Build To","Electropolished Tube Manufacturing Capability Serving "&$E8) -> Electropolished Tube Manufacturing Capability Serving Ambernath | AF8: =CHOOSE($S8,"Electropolished Pipes Supplier in "&$E8&" - Stock Sizes, Lead Time & Delivery","Supplying Electropolished Pipes in "&$E8&": Availability, Sizes & Dispatch","Electropolished Pipes Supplier in "&$E8&" - What We Hold in Stock","Electropolished Pipe Supply Into "&$E8&" - Certification & Transit","Electropolished Pipes Supplier in "&$E8&" - From Order to Delivery") -> Electropolished Pipes Supplier in Ambernath - From Order to Delivery | AG8: =CHOOSE($S8,"Electropolished Pipes Wholesaler & Stockist in "&$E8&" - Bulk & Project Pricing","Wholesale Electropolished Pipe Supply for "&$E8&" Projects","Bulk & Wholesale Electropolished Pipe Rates for "&$E8&" Buyers","Electropolished Pipes Wholesaler in "&$E8&" - Project Quantities & Terms","Stockist & Wholesale Supply of Electropolished Pipes in "&$E8) -> Stockist & Wholesale Supply of Electropolished Pipes in Ambernath | AH8: ="electropolished pipes manufacturer in "&$D8&", electropolished pipes supplier in "&$D8&", electropolished pipes wholesaler in "&$D8&", electropolished tube manufacturer "&$D8&", EP pipe supplier "&$D8&", sanitary tube supplier "&$D8&", ASME BPE tubing "&$D8&", ASTM A270 tube "&$D8&", SS 316L electropolished pipe "&$D8 -> electropolished pipes manufacturer in Ambernath, electropolished pipes supplier in Ambernath, electropolished pipes wholesaler in Ambernath, electropolished tube manufacturer Ambernath, EP pipe supplier Ambernath, sanitary tube supplier Ambernath, ASME BPE tubing Ambernath, ASTM A270 tube Ambernath, SS 316L electropolished pipe Ambernath | AI8: ="Electropolished Pipes Manufacturer & Supplier in "&$E8 -> Electropolished Pipes Manufacturer & Supplier in Ambernath | AJ8: ="EP-finished SS 304/316L pipes and tubes for "&$K8&" plants in "&$E8&". ASME BPE SF1-SF4, Ra from 0.25 um, EN 10204 3.1 certificate with every lot." -> EP-finished SS 304/316L pipes and tubes for chemical plants in Ambernath. ASME BPE SF1-SF4, Ra from 0.25 um, EN 10204 3.1 certificate with every lot. | AK8: ="Electropolished stainless steel pipes supplied by Sakshi Forge to "&$K8&" plants at "&$I8&", "&$E8 -> Electropolished stainless steel pipes supplied by Sakshi Forge to chemical plants at Ambernath MIDC (Anand Nagar), Ambernath | AL8: ="Electropolished SS 316L tube stock for "&$E8&" - Sakshi Forge" -> Electropolished SS 316L tube stock for Ambernath - Sakshi Forge | AM8: ="Home > Market Area > "&$B8&" > "&$C8&" > "&$D8 -> Home > Market Area > India > Maharashtra > Ambernath | AN8: =IF($F8="A",1400,IF($F8="B",1000,750)) -> 1400 | AO8: =IF($F8="A",10,IF($F8="B",8,6)) -> 10 | AP8: =IF($F8="A",12,IF($F8="B",8,6)) -> 12 | AQ8: =ROUNDUP((ROW()-3)/60,0) -> 1 | AT8: Not started
A9: CTY-0006 | B9: India | C9: Punjab | D9: Amritsar | E9: Amritsar | F9: A | G9: VERIFIED | H9: Focal Point Amritsar, Mehta Road Estate | I9: Focal Point Amritsar | J9: Food processing, textiles, engineering | K9: food processing | L9: ICD Ludhiana (140 km) | M9: 1-2 day road transit from our Mumbai works | N9: FSSAI licensing; 3-A Sanitary Standards on product-contact lines | O9: VERIFY | P9: =IF($K9="VERIFY","VERIFY",IF(ISNUMBER(SEARCH("semicon",$K9)),"SEMI",IF(ISNUMBER(SEARCH("electronic",$K9)),"SEMI",IF(ISNUMBER(SEARCH("biotech",$K9)),"BIOTECH",IF(ISNUMBER(SEARCH("pharma",$K9)),"PHARMA",IF(ISNUMBER(SEARCH("medical",$K9)),"PHARMA",IF(ISNUMBER(SEARCH("dairy",$K9)),"DAIRY",IF(ISNUMBER(SEARCH("brewery",$K9)),"BREWERY",IF(ISNUMBER(SEARCH("food",$K9)),"FOOD",IF(ISNUMBER(SEARCH("personal care",$K9)),"FOOD",IF(ISNUMBER(SEARCH("chemical",$K9)),"CHEM",IF(ISNUMBER(SEARCH("refining",$K9)),"CHEM",IF(ISNUMBER(SEARCH("petrochem",$K9)),"CHEM",IF(ISNUMBER(SEARCH("fertilis",$K9)),"CHEM",IF(ISNUMBER(SEARCH("water",$K9)),"CHEM","GENERAL"))))))))))))))) -> FOOD | Q9: =MOD(ROW()-4,8)+1 -> 6 | R9: =MOD(ROW()-4,7)+1 -> 6 | S9: =MOD(ROW()-4,5)+1 -> 1 | T9: =$F9&"-"&(MOD(ROW()-4,6)+1) -> A-6 | U9: ="T"&$Q9&"-M"&$R9&"-H"&$S9&"-F"&$T9&"-"&$P9 -> T6-M6-H1-FA-6-FOOD | V9: =COUNTIF($U$4:$U$1835,$U9)-1 -> 0 | X9: =IF($W9<>"",$W9,IF($B9="India",LOWER(SUBSTITUTE(SUBSTITUTE($D9," ","-"),".","")),LOWER(SUBSTITUTE(SUBSTITUTE($D9," ","-"),".",""))&"-"&LOWER(SUBSTITUTE($B9," ","-")))) -> amritsar | Y9: ="https://steelmanufacturer.in/market-area/electropolished-pipes-manufacturer-in-"&$X9&"/" -> https://steelmanufacturer.in/market-area/electropolished-pipes-manufacturer-in-amritsar/ | Z9: =IF($AR9<>"",$AR9,IF(LEN("Electropolished Pipes Manufacturer in "&$E9&CHOOSE($Q9," | Sakshi Forge"," - ASTM A270 & ASME BPE"," | EP Tube Supplier"," - SS 304/316L EP Tube"," | Sanitary Tube Supply"," - Mill Certified Supply"," | ASME BPE SF1-SF4"," - EP Tube Stockist"))<=65,"Electropolished Pipes Manufacturer in "&$E9&CHOOSE($Q9," | Sakshi Forge"," - ASTM A270 & ASME BPE"," | EP Tube Supplier"," - SS 304/316L EP Tube"," | Sanitary Tube Supply"," - Mill Certified Supply"," | ASME BPE SF1-SF4"," - EP Tube Stockist"),"Electropolished Pipes Manufacturer in "&$E9)) -> Electropolished Pipes Manufacturer in Amritsar | AA9: =IF(LEN($Z9)>65,"TRIM ("&LEN($Z9)&")",IF(LEN($Z9)<35,"SHORT ("&LEN($Z9)&")","OK ("&LEN($Z9)&")")) -> OK (46) | AB9: =IF($AS9<>"",$AS9,CHOOSE($R9,"EP-finished SS 304/316L pipes & tubes for "&$K9&" plants in "&$E9&". ASTM A270, ASME BPE SF1-SF4, EN 10204 3.1 MTC. PMI tested.","Electropolished tube supply to "&$I9&", "&$E9&". Ra from 0.25 um, SF4 finish, mill test certificate with every lot.","EP stainless tube for "&$K9&" lines in "&$E9&". "&$M9&". ASTM A270 S2, PMI tested, EN 10204 3.1.","Sanitary electropolished pipes in "&$E9&" for "&$K9&" plants. ASME BPE SF1-SF4, orbital-weld ready, 3.1 MTC. Mumbai-made.","Manufacturer of electropolished SS 316L tube serving "&$E9&". "&$M9&". Ra 0.25-0.5 um, EN 10204 3.1 MTC.",IF(LEN("EP tube and pipe for "&$K9&" plants around "&$I9&", "&$E9&". Made at our Mumbai works to ASTM A270 and ASME BPE SF1-SF4, with 3.1 MTC.")<=160,"EP tube and pipe for "&$K9&" plants around "&$I9&", "&$E9&". Made at our Mumbai works to ASTM A270 and ASME BPE SF1-SF4, with 3.1 MTC.","EP tube and pipe for "&$K9&" plants around "&$I9&", "&$E9&". ASTM A270, ASME BPE SF1-SF4, EN 10204 3.1 MTC."),"Electropolished pipes in "&$E9&": 304, 304L, 316 and 316L in SF1-SF4. "&$M9&". Mill certified.")) -> EP tube and pipe for food processing plants around Focal Point Amritsar, Amritsar. Made at our Mumbai works to ASTM A270 and ASME BPE SF1-SF4, with 3.1 MTC. | AC9: =IF($G9="VERIFY","PENDING RESEARCH",IF(LEN($AB9)>160,"TRIM ("&LEN($AB9)&")",IF(LEN($AB9)<110,"SHORT ("&LEN($AB9)&")","OK ("&LEN($AB9)&")"))) -> OK (156) | AD9: ="Electropolished Pipes Manufacturer in "&$E9 -> Electropolished Pipes Manufacturer in Amritsar | AE9: =CHOOSE($S9,"Electropolished Pipe & Tube Manufacturing for "&$E9&" - Grades, Finishes & Certification","How We Manufacture Electropolished Tube for "&$E9&" Plants","Electropolished Pipes Manufacturer in "&$E9&" - Our Process & Capability","Manufacturing Electropolished SS Tube for "&$E9&": The Standards We Build To","Electropolished Tube Manufacturing Capability Serving "&$E9) -> Electropolished Pipe & Tube Manufacturing for Amritsar - Grades, Finishes & Certification | AF9: =CHOOSE($S9,"Electropolished Pipes Supplier in "&$E9&" - Stock Sizes, Lead Time & Delivery","Supplying Electropolished Pipes in "&$E9&": Availability, Sizes & Dispatch","Electropolished Pipes Supplier in "&$E9&" - What We Hold in Stock","Electropolished Pipe Supply Into "&$E9&" - Certification & Transit","Electropolished Pipes Supplier in "&$E9&" - From Order to Delivery") -> Electropolished Pipes Supplier in Amritsar - Stock Sizes, Lead Time & Delivery | AG9: =CHOOSE($S9,"Electropolished Pipes Wholesaler & Stockist in "&$E9&" - Bulk & Project Pricing","Wholesale Electropolished Pipe Supply for "&$E9&" Projects","Bulk & Wholesale Electropolished Pipe Rates for "&$E9&" Buyers","Electropolished Pipes Wholesaler in "&$E9&" - Project Quantities & Terms","Stockist & Wholesale Supply of Electropolished Pipes in "&$E9) -> Electropolished Pipes Wholesaler & Stockist in Amritsar - Bulk & Project Pricing | AH9: ="electropolished pipes manufacturer in "&$D9&", electropolished pipes supplier in "&$D9&", electropolished pipes wholesaler in "&$D9&", electropolished tube manufacturer "&$D9&", EP pipe supplier "&$D9&", sanitary tube supplier "&$D9&", ASME BPE tubing "&$D9&", ASTM A270 tube "&$D9&", SS 316L electropolished pipe "&$D9 -> electropolished pipes manufacturer in Amritsar, electropolished pipes supplier in Amritsar, electropolished pipes wholesaler in Amritsar, electropolished tube manufacturer Amritsar, EP pipe supplier Amritsar, sanitary tube supplier Amritsar, ASME BPE tubing Amritsar, ASTM A270 tube Amritsar, SS 316L electropolished pipe Amritsar | AI9: ="Electropolished Pipes Manufacturer & Supplier in "&$E9 -> Electropolished Pipes Manufacturer & Supplier in Amritsar | AJ9: ="EP-finished SS 304/316L pipes and tubes for "&$K9&" plants in "&$E9&". ASME BPE SF1-SF4, Ra from 0.25 um, EN 10204 3.1 certificate with every lot." -> EP-finished SS 304/316L pipes and tubes for food processing plants in Amritsar. ASME BPE SF1-SF4, Ra from 0.25 um, EN 10204 3.1 certificate with every lot. | AK9: ="Electropolished stainless steel pipes supplied by Sakshi Forge to "&$K9&" plants at "&$I9&", "&$E9 -> Electropolished stainless steel pipes supplied by Sakshi Forge to food processing plants at Focal Point Amritsar, Amritsar | AL9: ="Electropolished SS 316L tube stock for "&$E9&" - Sakshi Forge" -> Electropolished SS 316L tube stock for Amritsar - Sakshi Forge | AM9: ="Home > Market Area > "&$B9&" > "&$C9&" > "&$D9 -> Home > Market Area > India > Punjab > Amritsar | AN9: =IF($F9="A",1400,IF($F9="B",1000,750)) -> 1400 | AO9: =IF($F9="A",10,IF($F9="B",8,6)) -> 10 | AP9: =IF($F9="A",12,IF($F9="B",8,6)) -> 12 | AQ9: =ROUNDUP((ROW()-3)/60,0) -> 1 | AT9: Not started
A10: CTY-0007 | B10: India | C10: Gujarat | D10: Anand | E10: Anand | F10: A | G10: VERIFIED | H10: Vithal Udyognagar GIDC, Anand GIDC | I10: Vithal Udyognagar GIDC | J10: Dairy processing, pharmaceutical, food | K10: pharma & food & dairy | L10: Hazira Port (170 km) | M10: 1-2 day road transit from our Mumbai works | N10: CDSCO + state FDA licensed plants; WHO-GMP and USFDA documentation common | O10: VERIFY | P10: =IF($K10="VERIFY","VERIFY",IF(ISNUMBER(SEARCH("semicon",$K10)),"SEMI",IF(ISNUMBER(SEARCH("electronic",$K10)),"SEMI",IF(ISNUMBER(SEARCH("biotech",$K10)),"BIOTECH",IF(ISNUMBER(SEARCH("pharma",$K10)),"PHARMA",IF(ISNUMBER(SEARCH("medical",$K10)),"PHARMA",IF(ISNUMBER(SEARCH("dairy",$K10)),"DAIRY",IF(ISNUMBER(SEARCH("brewery",$K10)),"BREWERY",IF(ISNUMBER(SEARCH("food",$K10)),"FOOD",IF(ISNUMBER(SEARCH("personal care",$K10)),"FOOD",IF(ISNUMBER(SEARCH("chemical",$K10)),"CHEM",IF(ISNUMBER(SEARCH("refining",$K10)),"CHEM",IF(ISNUMBER(SEARCH("petrochem",$K10)),"CHEM",IF(ISNUMBER(SEARCH("fertilis",$K10)),"CHEM",IF(ISNUMBER(SEARCH("water",$K10)),"CHEM","GENERAL"))))))))))))))) -> PHARMA | Q10: =MOD(ROW()-4,8)+1 -> 7 | R10: =MOD(ROW()-4,7)+1 -> 7 | S10: =MOD(ROW()-4,5)+1 -> 2 | T10: =$F10&"-"&(MOD(ROW()-4,6)+1) -> A-1 | U10: ="T"&$Q10&"-M"&$R10&"-H"&$S10&"-F"&$T10&"-"&$P10 -> T7-M7-H2-FA-1-PHARMA | V10: =COUNTIF($U$4:$U$1835,$U10)-1 -> 0 | X10: =IF($W10<>"",$W10,IF($B10="India",LOWER(SUBSTITUTE(SUBSTITUTE($D10," ","-"),".","")),LOWER(SUBSTITUTE(SUBSTITUTE($D10," ","-"),".",""))&"-"&LOWER(SUBSTITUTE($B10," ","-")))) -> anand | Y10: ="https://steelmanufacturer.in/market-area/electropolished-pipes-manufacturer-in-"&$X10&"/" -> https://steelmanufacturer.in/market-area/electropolished-pipes-manufacturer-in-anand/ | Z10: =IF($AR10<>"",$AR10,IF(LEN("Electropolished Pipes Manufacturer in "&$E10&CHOOSE($Q10," | Sakshi Forge"," - ASTM A270 & ASME BPE"," | EP Tube Supplier"," - SS 304/316L EP Tube"," | Sanitary Tube Supply"," - Mill Certified Supply"," | ASME BPE SF1-SF4"," - EP Tube Stockist"))<=65,"Electropolished Pipes Manufacturer in "&$E10&CHOOSE($Q10," | Sakshi Forge"," - ASTM A270 & ASME BPE"," | EP Tube Supplier"," - SS 304/316L EP Tube"," | Sanitary Tube Supply"," - Mill Certified Supply"," | ASME BPE SF1-SF4"," - EP Tube Stockist"),"Electropolished Pipes Manufacturer in "&$E10)) -> Electropolished Pipes Manufacturer in Anand | ASME BPE SF1-SF4 | AA10: =IF(LEN($Z10)>65,"TRIM ("&LEN($Z10)&")",IF(LEN($Z10)<35,"SHORT ("&LEN($Z10)&")","OK ("&LEN($Z10)&")")) -> OK (62) | AB10: =IF($AS10<>"",$AS10,CHOOSE($R10,"EP-finished SS 304/316L pipes & tubes for "&$K10&" plants in "&$E10&". ASTM A270, ASME BPE SF1-SF4, EN 10204 3.1 MTC. PMI tested.","Electropolished tube supply to "&$I10&", "&$E10&". Ra from 0.25 um, SF4 finish, mill test certificate with every lot.","EP stainless tube for "&$K10&" lines in "&$E10&". "&$M10&". ASTM A270 S2, PMI tested, EN 10204 3.1.","Sanitary electropolished pipes in "&$E10&" for "&$K10&" plants. ASME BPE SF1-SF4, orbital-weld ready, 3.1 MTC. Mumbai-made.","Manufacturer of electropolished SS 316L tube serving "&$E10&". "&$M10&". Ra 0.25-0.5 um, EN 10204 3.1 MTC.",IF(LEN("EP tube and pipe for "&$K10&" plants around "&$I10&", "&$E10&". Made at our Mumbai works to ASTM A270 and ASME BPE SF1-SF4, with 3.1 MTC.")<=160,"EP tube and pipe for "&$K10&" plants around "&$I10&", "&$E10&". Made at our Mumbai works to ASTM A270 and ASME BPE SF1-SF4, with 3.1 MTC.","EP tube and pipe for "&$K10&" plants around "&$I10&", "&$E10&". ASTM A270, ASME BPE SF1-SF4, EN 10204 3.1 MTC."),"Electropolished pipes in "&$E10&": 304, 304L, 316 and 316L in SF1-SF4. "&$M10&". Mill certified.")) -> Electropolished pipes in Anand: 304, 304L, 316 and 316L in SF1-SF4. 1-2 day road transit from our Mumbai works. Mill certified. | AC10: =IF($G10="VERIFY","PENDING RESEARCH",IF(LEN($AB10)>160,"TRIM ("&LEN($AB10)&")",IF(LEN($AB10)<110,"SHORT ("&LEN($AB10)&")","OK ("&LEN($AB10)&")"))) -> OK (127) | AD10: ="Electropolished Pipes Manufacturer in "&$E10 -> Electropolished Pipes Manufacturer in Anand | AE10: =CHOOSE($S10,"Electropolished Pipe & Tube Manufacturing for "&$E10&" - Grades, Finishes & Certification","How We Manufacture Electropolished Tube for "&$E10&" Plants","Electropolished Pipes Manufacturer in "&$E10&" - Our Process & Capability","Manufacturing Electropolished SS Tube for "&$E10&": The Standards We Build To","Electropolished Tube Manufacturing Capability Serving "&$E10) -> How We Manufacture Electropolished Tube for Anand Plants | AF10: =CHOOSE($S10,"Electropolished Pipes Supplier in "&$E10&" - Stock Sizes, Lead Time & Delivery","Supplying Electropolished Pipes in "&$E10&": Availability, Sizes & Dispatch","Electropolished Pipes Supplier in "&$E10&" - What We Hold in Stock","Electropolished Pipe Supply Into "&$E10&" - Certification & Transit","Electropolished Pipes Supplier in "&$E10&" - From Order to Delivery") -> Supplying Electropolished Pipes in Anand: Availability, Sizes & Dispatch | AG10: =CHOOSE($S10,"Electropolished Pipes Wholesaler & Stockist in "&$E10&" - Bulk & Project Pricing","Wholesale Electropolished Pipe Supply for "&$E10&" Projects","Bulk & Wholesale Electropolished Pipe Rates for "&$E10&" Buyers","Electropolished Pipes Wholesaler in "&$E10&" - Project Quantities & Terms","Stockist & Wholesale Supply of Electropolished Pipes in "&$E10) -> Wholesale Electropolished Pipe Supply for Anand Projects | AH10: ="electropolished pipes manufacturer in "&$D10&", electropolished pipes supplier in "&$D10&", electropolished pipes wholesaler in "&$D10&", electropolished tube manufacturer "&$D10&", EP pipe supplier "&$D10&", sanitary tube supplier "&$D10&", ASME BPE tubing "&$D10&", ASTM A270 tube "&$D10&", SS 316L electropolished pipe "&$D10 -> electropolished pipes manufacturer in Anand, electropolished pipes supplier in Anand, electropolished pipes wholesaler in Anand, electropolished tube manufacturer Anand, EP pipe supplier Anand, sanitary tube supplier Anand, ASME BPE tubing Anand, ASTM A270 tube Anand, SS 316L electropolished pipe Anand | AI10: ="Electropolished Pipes Manufacturer & Supplier in "&$E10 -> Electropolished Pipes Manufacturer & Supplier in Anand | AJ10: ="EP-finished SS 304/316L pipes and tubes for "&$K10&" plants in "&$E10&". ASME BPE SF1-SF4, Ra from 0.25 um, EN 10204 3.1 certificate with every lot." -> EP-finished SS 304/316L pipes and tubes for pharma & food & dairy plants in Anand. ASME BPE SF1-SF4, Ra from 0.25 um, EN 10204 3.1 certificate with every lot. | AK10: ="Electropolished stainless steel pipes supplied by Sakshi Forge to "&$K10&" plants at "&$I10&", "&$E10 -> Electropolished stainless steel pipes supplied by Sakshi Forge to pharma & food & dairy plants at Vithal Udyognagar GIDC, Anand | AL10: ="Electropolished SS 316L tube stock for "&$E10&" - Sakshi Forge" -> Electropolished SS 316L tube stock for Anand - Sakshi Forge | AM10: ="Home > Market Area > "&$B10&" > "&$C10&" > "&$D10 -> Home > Market Area > India > Gujarat > Anand | AN10: =IF($F10="A",1400,IF($F10="B",1000,750)) -> 1400 | AO10: =IF($F10="A",10,IF($F10="B",8,6)) -> 10 | AP10: =IF($F10="A",12,IF($F10="B",8,6)) -> 12 | AQ10: =ROUNDUP((ROW()-3)/60,0) -> 1 | AT10: Not started
A11: CTY-0008 | B11: India | C11: Andhra Pradesh | D11: Anantapur | E11: Anantapur | F11: A | G11: VERIFIED | H11: Hindupur APIIC, Anantapur Industrial Park | I11: Hindupur APIIC | J11: Automotive, textiles, food processing | K11: food processing | L11: Krishnapatnam Port (400 km) | M11: 2-3 day road transit from our Mumbai works | N11: FSSAI licensing; 3-A Sanitary Standards on product-contact lines | O11: VERIFY | P11: =IF($K11="VERIFY","VERIFY",IF(ISNUMBER(SEARCH("semicon",$K11)),"SEMI",IF(ISNUMBER(SEARCH("electronic",$K11)),"SEMI",IF(ISNUMBER(SEARCH("biotech",$K11)),"BIOTECH",IF(ISNUMBER(SEARCH("pharma",$K11)),"PHARMA",IF(ISNUMBER(SEARCH("medical",$K11)),"PHARMA",IF(ISNUMBER(SEARCH("dairy",$K11)),"DAIRY",IF(ISNUMBER(SEARCH("brewery",$K11)),"BREWERY",IF(ISNUMBER(SEARCH("food",$K11)),"FOOD",IF(ISNUMBER(SEARCH("personal care",$K11)),"FOOD",IF(ISNUMBER(SEARCH("chemical",$K11)),"CHEM",IF(ISNUMBER(SEARCH("refining",$K11)),"CHEM",IF(ISNUMBER(SEARCH("petrochem",$K11)),"CHEM",IF(ISNUMBER(SEARCH("fertilis",$K11)),"CHEM",IF(ISNUMBER(SEARCH("water",$K11)),"CHEM","GENERAL"))))))))))))))) -> FOOD | Q11: =MOD(ROW()-4,8)+1 -> 8 | R11: =MOD(ROW()-4,7)+1 -> 1 | S11: =MOD(ROW()-4,5)+1 -> 3 | T11: =$F11&"-"&(MOD(ROW()-4,6)+1) -> A-2 | U11: ="T"&$Q11&"-M"&$R11&"-H"&$S11&"-F"&$T11&"-"&$P11 -> T8-M1-H3-FA-2-FOOD | V11: =COUNTIF($U$4:$U$1835,$U11)-1 -> 0 | X11: =IF($W11<>"",$W11,IF($B11="India",LOWER(SUBSTITUTE(SUBSTITUTE($D11," ","-"),".","")),LOWER(SUBSTITUTE(SUBSTITUTE($D11," ","-"),".",""))&"-"&LOWER(SUBSTITUTE($B11," ","-")))) -> anantapur | Y11: ="https://steelmanufacturer.in/market-area/electropolished-pipes-manufacturer-in-"&$X11&"/" -> https://steelmanufacturer.in/market-area/electropolished-pipes-manufacturer-in-anantapur/ | Z11: =IF($AR11<>"",$AR11,IF(LEN("Electropolished Pipes Manufacturer in "&$E11&CHOOSE($Q11," | Sakshi Forge"," - ASTM A270 & ASME BPE"," | EP Tube Supplier"," - SS 304/316L EP Tube"," | Sanitary Tube Supply"," - Mill Certified Supply"," | ASME BPE SF1-SF4"," - EP Tube Stockist"))<=65,"Electropolished Pipes Manufacturer in "&$E11&CHOOSE($Q11," | Sakshi Forge"," - ASTM A270 & ASME BPE"," | EP Tube Supplier"," - SS 304/316L EP Tube"," | Sanitary Tube Supply"," - Mill Certified Supply"," | ASME BPE SF1-SF4"," - EP Tube Stockist"),"Electropolished Pipes Manufacturer in "&$E11)) -> Electropolished Pipes Manufacturer in Anantapur | AA11: =IF(LEN($Z11)>65,"TRIM ("&LEN($Z11)&")",IF(LEN($Z11)<35,"SHORT ("&LEN($Z11)&")","OK ("&LEN($Z11)&")")) -> OK (47) | AB11: =IF($AS11<>"",$AS11,CHOOSE($R11,"EP-finished SS 304/316L pipes & tubes for "&$K11&" plants in "&$E11&". ASTM A270, ASME BPE SF1-SF4, EN 10204 3.1 MTC. PMI tested.","Electropolished tube supply to "&$I11&", "&$E11&". Ra from 0.25 um, SF4 finish, mill test certificate with every lot.","EP stainless tube for "&$K11&" lines in "&$E11&". "&$M11&". ASTM A270 S2, PMI tested, EN 10204 3.1.","Sanitary electropolished pipes in "&$E11&" for "&$K11&" plants. ASME BPE SF1-SF4, orbital-weld ready, 3.1 MTC. Mumbai-made.","Manufacturer of electropolished SS 316L tube serving "&$E11&". "&$M11&". Ra 0.25-0.5 um, EN 10204 3.1 MTC.",IF(LEN("EP tube and pipe for "&$K11&" plants around "&$I11&", "&$E11&". Made at our Mumbai works to ASTM A270 and ASME BPE SF1-SF4, with 3.1 MTC.")<=160,"EP tube and pipe for "&$K11&" plants around "&$I11&", "&$E11&". Made at our Mumbai works to ASTM A270 and ASME BPE SF1-SF4, with 3.1 MTC.","EP tube and pipe for "&$K11&" plants around "&$I11&", "&$E11&". ASTM A270, ASME BPE SF1-SF4, EN 10204 3.1 MTC."),"Electropolished pipes in "&$E11&": 304, 304L, 316 and 316L in SF1-SF4. "&$M11&". Mill certified.")) -> EP-finished SS 304/316L pipes & tubes for food processing plants in Anantapur. ASTM A270, ASME BPE SF1-SF4, EN 10204 3.1 MTC. PMI tested. | AC11: =IF($G11="VERIFY","PENDING RESEARCH",IF(LEN($AB11)>160,"TRIM ("&LEN($AB11)&")",IF(LEN($AB11)<110,"SHORT ("&LEN($AB11)&")","OK ("&LEN($AB11)&")"))) -> OK (137) | AD11: ="Electropolished Pipes Manufacturer in "&$E11 -> Electropolished Pipes Manufacturer in Anantapur | AE11: =CHOOSE($S11,"Electropolished Pipe & Tube Manufacturing for "&$E11&" - Grades, Finishes & Certification","How We Manufacture Electropolished Tube for "&$E11&" Plants","Electropolished Pipes Manufacturer in "&$E11&" - Our Process & Capability","Manufacturing Electropolished SS Tube for "&$E11&": The Standards We Build To","Electropolished Tube Manufacturing Capability Serving "&$E11) -> Electropolished Pipes Manufacturer in Anantapur - Our Process & Capability | AF11: =CHOOSE($S11,"Electropolished Pipes Supplier in "&$E11&" - Stock Sizes, Lead Time & Delivery","Supplying Electropolished Pipes in "&$E11&": Availability, Sizes & Dispatch","Electropolished Pipes Supplier in "&$E11&" - What We Hold in Stock","Electropolished Pipe Supply Into "&$E11&" - Certification & Transit","Electropolished Pipes Supplier in "&$E11&" - From Order to Delivery") -> Electropolished Pipes Supplier in Anantapur - What We Hold in Stock | AG11: =CHOOSE($S11,"Electropolished Pipes Wholesaler & Stockist in "&$E11&" - Bulk & Project Pricing","Wholesale Electropolished Pipe Supply for "&$E11&" Projects","Bulk & Wholesale Electropolished Pipe Rates for "&$E11&" Buyers","Electropolished Pipes Wholesaler in "&$E11&" - Project Quantities & Terms","Stockist & Wholesale Supply of Electropolished Pipes in "&$E11) -> Bulk & Wholesale Electropolished Pipe Rates for Anantapur Buyers | AH11: ="electropolished pipes manufacturer in "&$D11&", electropolished pipes supplier in "&$D11&", electropolished pipes wholesaler in "&$D11&", electropolished tube manufacturer "&$D11&", EP pipe supplier "&$D11&", sanitary tube supplier "&$D11&", ASME BPE tubing "&$D11&", ASTM A270 tube "&$D11&", SS 316L electropolished pipe "&$D11 -> electropolished pipes manufacturer in Anantapur, electropolished pipes supplier in Anantapur, electropolished pipes wholesaler in Anantapur, electropolished tube manufacturer Anantapur, EP pipe supplier Anantapur, sanitary tube supplier Anantapur, ASME BPE tubing Anantapur, ASTM A270 tube Anantapur, SS 316L electropolished pipe Anantapur | AI11: ="Electropolished Pipes Manufacturer & Supplier in "&$E11 -> Electropolished Pipes Manufacturer & Supplier in Anantapur | AJ11: ="EP-finished SS 304/316L pipes and tubes for "&$K11&" plants in "&$E11&". ASME BPE SF1-SF4, Ra from 0.25 um, EN 10204 3.1 certificate with every lot." -> EP-finished SS 304/316L pipes and tubes for food processing plants in Anantapur. ASME BPE SF1-SF4, Ra from 0.25 um, EN 10204 3.1 certificate with every lot. | AK11: ="Electropolished stainless steel pipes supplied by Sakshi Forge to "&$K11&" plants at "&$I11&", "&$E11 -> Electropolished stainless steel pipes supplied by Sakshi Forge to food processing plants at Hindupur APIIC, Anantapur | AL11: ="Electropolished SS 316L tube stock for "&$E11&" - Sakshi Forge" -> Electropolished SS 316L tube stock for Anantapur - Sakshi Forge | AM11: ="Home > Market Area > "&$B11&" > "&$C11&" > "&$D11 -> Home > Market Area > India > Andhra Pradesh > Anantapur | AN11: =IF($F11="A",1400,IF($F11="B",1000,750)) -> 1400 | AO11: =IF($F11="A",10,IF($F11="B",8,6)) -> 10 | AP11: =IF($F11="A",12,IF($F11="B",8,6)) -> 12 | AQ11: =ROUNDUP((ROW()-3)/60,0) -> 1 | AT11: Not started
A12: CTY-0009 | B12: India | C12: Odisha | D12: Angul | E12: Angul | F12: A | G12: VERIFIED | H12: Angul Industrial Belt IDCO | I12: Angul Industrial Belt IDCO | J12: Aluminium, steel, power | K12: engineering & process | L12: Paradip Port (200 km) | M12: 1-2 day road transit from our Mumbai works | N12: BIS and buyer-specified ASTM A270 / ASME BPE; EN 10204 3.1 MTC standard | O12: VERIFY | P12: =IF($K12="VERIFY","VERIFY",IF(ISNUMBER(SEARCH("semicon",$K12)),"SEMI",IF(ISNUMBER(SEARCH("electronic",$K12)),"SEMI",IF(ISNUMBER(SEARCH("biotech",$K12)),"BIOTECH",IF(ISNUMBER(SEARCH("pharma",$K12)),"PHARMA",IF(ISNUMBER(SEARCH("medical",$K12)),"PHARMA",IF(ISNUMBER(SEARCH("dairy",$K12)),"DAIRY",IF(ISNUMBER(SEARCH("brewery",$K12)),"BREWERY",IF(ISNUMBER(SEARCH("food",$K12)),"FOOD",IF(ISNUMBER(SEARCH("personal care",$K12)),"FOOD",IF(ISNUMBER(SEARCH("chemical",$K12)),"CHEM",IF(ISNUMBER(SEARCH("refining",$K12)),"CHEM",IF(ISNUMBER(SEARCH("petrochem",$K12)),"CHEM",IF(ISNUMBER(SEARCH("fertilis",$K12)),"CHEM",IF(ISNUMBER(SEARCH("water",$K12)),"CHEM","GENERAL"))))))))))))))) -> GENERAL | Q12: =MOD(ROW()-4,8)+1 -> 1 | R12: =MOD(ROW()-4,7)+1 -> 2 | S12: =MOD(ROW()-4,5)+1 -> 4 | T12: =$F12&"-"&(MOD(ROW()-4,6)+1) -> A-3 | U12: ="T"&$Q12&"-M"&$R12&"-H"&$S12&"-F"&$T12&"-"&$P12 -> T1-M2-H4-FA-3-GENERAL | V12: =COUNTIF($U$4:$U$1835,$U12)-1 -> 0 | X12: =IF($W12<>"",$W12,IF($B12="India",LOWER(SUBSTITUTE(SUBSTITUTE($D12," ","-"),".","")),LOWER(SUBSTITUTE(SUBSTITUTE($D12," ","-"),".",""))&"-"&LOWER(SUBSTITUTE($B12," ","-")))) -> angul | Y12: ="https://steelmanufacturer.in/market-area/electropolished-pipes-manufacturer-in-"&$X12&"/" -> https://steelmanufacturer.in/market-area/electropolished-pipes-manufacturer-in-angul/ | Z12: =IF($AR12<>"",$AR12,IF(LEN("Electropolished Pipes Manufacturer in "&$E12&CHOOSE($Q12," | Sakshi Forge"," - ASTM A270 & ASME BPE"," | EP Tube Supplier"," - SS 304/316L EP Tube"," | Sanitary Tube Supply"," - Mill Certified Supply"," | ASME BPE SF1-SF4"," - EP Tube Stockist"))<=65,"Electropolished Pipes Manufacturer in "&$E12&CHOOSE($Q12," | Sakshi Forge"," - ASTM A270 & ASME BPE"," | EP Tube Supplier"," - SS 304/316L EP Tube"," | Sanitary Tube Supply"," - Mill Certified Supply"," | ASME BPE SF1-SF4"," - EP Tube Stockist"),"Electropolished Pipes Manufacturer in "&$E12)) -> Electropolished Pipes Manufacturer in Angul | Sakshi Forge | AA12: =IF(LEN($Z12)>65,"TRIM ("&LEN($Z12)&")",IF(LEN($Z12)<35,"SHORT ("&LEN($Z12)&")","OK ("&LEN($Z12)&")")) -> OK (58) | AB12: =IF($AS12<>"",$AS12,CHOOSE($R12,"EP-finished SS 304/316L pipes & tubes for "&$K12&" plants in "&$E12&". ASTM A270, ASME BPE SF1-SF4, EN 10204 3.1 MTC. PMI tested.","Electropolished tube supply to "&$I12&", "&$E12&". Ra from 0.25 um, SF4 finish, mill test certificate with every lot.","EP stainless tube for "&$K12&" lines in "&$E12&". "&$M12&". ASTM A270 S2, PMI tested, EN 10204 3.1.","Sanitary electropolished pipes in "&$E12&" for "&$K12&" plants. ASME BPE SF1-SF4, orbital-weld ready, 3.1 MTC. Mumbai-made.","Manufacturer of electropolished SS 316L tube serving "&$E12&". "&$M12&". Ra 0.25-0.5 um, EN 10204 3.1 MTC.",IF(LEN("EP tube and pipe for "&$K12&" plants around "&$I12&", "&$E12&". Made at our Mumbai works to ASTM A270 and ASME BPE SF1-SF4, with 3.1 MTC.")<=160,"EP tube and pipe for "&$K12&" plants around "&$I12&", "&$E12&". Made at our Mumbai works to ASTM A270 and ASME BPE SF1-SF4, with 3.1 MTC.","EP tube and pipe for "&$K12&" plants around "&$I12&", "&$E12&". ASTM A270, ASME BPE SF1-SF4, EN 10204 3.1 MTC."),"Electropolished pipes in "&$E12&": 304, 304L, 316 and 316L in SF1-SF4. "&$M12&". Mill certified.")) -> Electropolished tube supply to Angul Industrial Belt IDCO, Angul. Ra from 0.25 um, SF4 finish, mill test certificate with every lot. | AC12: =IF($G12="VERIFY","PENDING RESEARCH",IF(LEN($AB12)>160,"TRIM ("&LEN($AB12)&")",IF(LEN($AB12)<110,"SHORT ("&LEN($AB12)&")","OK ("&LEN($AB12)&")"))) -> OK (132) | AD12: ="Electropolished Pipes Manufacturer in "&$E12 -> Electropolished Pipes Manufacturer in Angul | AE12: =CHOOSE($S12,"Electropolished Pipe & Tube Manufacturing for "&$E12&" - Grades, Finishes & Certification","How We Manufacture Electropolished Tube for "&$E12&" Plants","Electropolished Pipes Manufacturer in "&$E12&" - Our Process & Capability","Manufacturing Electropolished SS Tube for "&$E12&": The Standards We Build To","Electropolished Tube Manufacturing Capability Serving "&$E12) -> Manufacturing Electropolished SS Tube for Angul: The Standards We Build To | AF12: =CHOOSE($S12,"Electropolished Pipes Supplier in "&$E12&" - Stock Sizes, Lead Time & Delivery","Supplying Electropolished Pipes in "&$E12&": Availability, Sizes & Dispatch","Electropolished Pipes Supplier in "&$E12&" - What We Hold in Stock","Electropolished Pipe Supply Into "&$E12&" - Certification & Transit","Electropolished Pipes Supplier in "&$E12&" - From Order to Delivery") -> Electropolished Pipe Supply Into Angul - Certification & Transit | AG12: =CHOOSE($S12,"Electropolished Pipes Wholesaler & Stockist in "&$E12&" - Bulk & Project Pricing","Wholesale Electropolished Pipe Supply for "&$E12&" Projects","Bulk & Wholesale Electropolished Pipe Rates for "&$E12&" Buyers","Electropolished Pipes Wholesaler in "&$E12&" - Project Quantities & Terms","Stockist & Wholesale Supply of Electropolished Pipes in "&$E12) -> Electropolished Pipes Wholesaler in Angul - Project Quantities & Terms | AH12: ="electropolished pipes manufacturer in "&$D12&", electropolished pipes supplier in "&$D12&", electropolished pipes wholesaler in "&$D12&", electropolished tube manufacturer "&$D12&", EP pipe supplier "&$D12&", sanitary tube supplier "&$D12&", ASME BPE tubing "&$D12&", ASTM A270 tube "&$D12&", SS 316L electropolished pipe "&$D12 -> electropolished pipes manufacturer in Angul, electropolished pipes supplier in Angul, electropolished pipes wholesaler in Angul, electropolished tube manufacturer Angul, EP pipe supplier Angul, sanitary tube supplier Angul, ASME BPE tubing Angul, ASTM A270 tube Angul, SS 316L electropolished pipe Angul | AI12: ="Electropolished Pipes Manufacturer & Supplier in "&$E12 -> Electropolished Pipes Manufacturer & Supplier in Angul | AJ12: ="EP-finished SS 304/316L pipes and tubes for "&$K12&" plants in "&$E12&". ASME BPE SF1-SF4, Ra from 0.25 um, EN 10204 3.1 certificate with every lot." -> EP-finished SS 304/316L pipes and tubes for engineering & process plants in Angul. ASME BPE SF1-SF4, Ra from 0.25 um, EN 10204 3.1 certificate with every lot. | AK12: ="Electropolished stainless steel pipes supplied by Sakshi Forge to "&$K12&" plants at "&$I12&", "&$E12 -> Electropolished stainless steel pipes supplied by Sakshi Forge to engineering & process plants at Angul Industrial Belt IDCO, Angul | AL12: ="Electropolished SS 316L tube stock for "&$E12&" - Sakshi Forge" -> Electropolished SS 316L tube stock for Angul - Sakshi Forge | AM12: ="Home > Market Area > "&$B12&" > "&$C12&" > "&$D12 -> Home > Market Area > India > Odisha > Angul | AN12: =IF($F12="A",1400,IF($F12="B",1000,750)) -> 1400 | AO12: =IF($F12="A",10,IF($F12="B",8,6)) -> 10 | AP12: =IF($F12="A",12,IF($F12="B",8,6)) -> 12 | AQ12: =ROUNDUP((ROW()-3)/60,0) -> 1 | AT12: Not started
A13: CTY-0010 | B13: India | C13: Gujarat | D13: Ankleshwar | E13: Ankleshwar | F13: A | G13: VERIFIED | H13: Ankleshwar GIDC, Panoli GIDC | I13: Ankleshwar GIDC | J13: Bulk drugs, API, agrochemicals, dyes and intermediates | K13: pharma & API | L13: Hazira Port (75 km) | M13: 1-2 day road transit from our Mumbai works | N13: CDSCO + state FDA licensed plants; WHO-GMP and USFDA documentation common | O13: VERIFY | P13: =IF($K13="VERIFY","VERIFY",IF(ISNUMBER(SEARCH("semicon",$K13)),"SEMI",IF(ISNUMBER(SEARCH("electronic",$K13)),"SEMI",IF(ISNUMBER(SEARCH("biotech",$K13)),"BIOTECH",IF(ISNUMBER(SEARCH("pharma",$K13)),"PHARMA",IF(ISNUMBER(SEARCH("medical",$K13)),"PHARMA",IF(ISNUMBER(SEARCH("dairy",$K13)),"DAIRY",IF(ISNUMBER(SEARCH("brewery",$K13)),"BREWERY",IF(ISNUMBER(SEARCH("food",$K13)),"FOOD",IF(ISNUMBER(SEARCH("personal care",$K13)),"FOOD",IF(ISNUMBER(SEARCH("chemical",$K13)),"CHEM",IF(ISNUMBER(SEARCH("refining",$K13)),"CHEM",IF(ISNUMBER(SEARCH("petrochem",$K13)),"CHEM",IF(ISNUMBER(SEARCH("fertilis",$K13)),"CHEM",IF(ISNUMBER(SEARCH("water",$K13)),"CHEM","GENERAL"))))))))))))))) -> PHARMA | Q13: =MOD(ROW()-4,8)+1 -> 2 | R13: =MOD(ROW()-4,7)+1 -> 3 | S13: =MOD(ROW()-4,5)+1 -> 5 | T13: =$F13&"-"&(MOD(ROW()-4,6)+1) -> A-4 | U13: ="T"&$Q13&"-M"&$R13&"-H"&$S13&"-F"&$T13&"-"&$P13 -> T2-M3-H5-FA-4-PHARMA | V13: =COUNTIF($U$4:$U$1835,$U13)-1 -> 0 | X13: =IF($W13<>"",$W13,IF($B13="India",LOWER(SUBSTITUTE(SUBSTITUTE($D13," ","-"),".","")),LOWER(SUBSTITUTE(SUBSTITUTE($D13," ","-"),".",""))&"-"&LOWER(SUBSTITUTE($B13," ","-")))) -> ankleshwar | Y13: ="https://steelmanufacturer.in/market-area/electropolished-pipes-manufacturer-in-"&$X13&"/" -> https://steelmanufacturer.in/market-area/electropolished-pipes-manufacturer-in-ankleshwar/ | Z13: =IF($AR13<>"",$AR13,IF(LEN("Electropolished Pipes Manufacturer in "&$E13&CHOOSE($Q13," | Sakshi Forge"," - ASTM A270 & ASME BPE"," | EP Tube Supplier"," - SS 304/316L EP Tube"," | Sanitary Tube Supply"," - Mill Certified Supply"," | ASME BPE SF1-SF4"," - EP Tube Stockist"))<=65,"Electropolished Pipes Manufacturer in "&$E13&CHOOSE($Q13," | Sakshi Forge"," - ASTM A270 & ASME BPE"," | EP Tube Supplier"," - SS 304/316L EP Tube"," | Sanitary Tube Supply"," - Mill Certified Supply"," | ASME BPE SF1-SF4"," - EP Tube Stockist"),"Electropolished Pipes Manufacturer in "&$E13)) -> Electropolished Pipes Manufacturer in Ankleshwar | AA13: =IF(LEN($Z13)>65,"TRIM ("&LEN($Z13)&")",IF(LEN($Z13)<35,"SHORT ("&LEN($Z13)&")","OK ("&LEN($Z13)&")")) -> OK (48) | AB13: =IF($AS13<>"",$AS13,CHOOSE($R13,"EP-finished SS 304/316L pipes & tubes for "&$K13&" plants in "&$E13&". ASTM A270, ASME BPE SF1-SF4, EN 10204 3.1 MTC. PMI tested.","Electropolished tube supply to "&$I13&", "&$E13&". Ra from 0.25 um, SF4 finish, mill test certificate with every lot.","EP stainless tube for "&$K13&" lines in "&$E13&". "&$M13&". ASTM A270 S2, PMI tested, EN 10204 3.1.","Sanitary electropolished pipes in "&$E13&" for "&$K13&" plants. ASME BPE SF1-SF4, orbital-weld ready, 3.1 MTC. Mumbai-made.","Manufacturer of electropolished SS 316L tube serving "&$E13&". "&$M13&". Ra 0.25-0.5 um, EN 10204 3.1 MTC.",IF(LEN("EP tube and pipe for "&$K13&" plants around "&$I13&", "&$E13&". Made at our Mumbai works to ASTM A270 and ASME BPE SF1-SF4, with 3.1 MTC.")<=160,"EP tube and pipe for "&$K13&" plants around "&$I13&", "&$E13&". Made at our Mumbai works to ASTM A270 and ASME BPE SF1-SF4, with 3.1 MTC.","EP tube and pipe for "&$K13&" plants around "&$I13&", "&$E13&". ASTM A270, ASME BPE SF1-SF4, EN 10204 3.1 MTC."),"Electropolished pipes in "&$E13&": 304, 304L, 316 and 316L in SF1-SF4. "&$M13&". Mill certified.")) -> EP stainless tube for pharma & API lines in Ankleshwar. 1-2 day road transit from our Mumbai works. ASTM A270 S2, PMI tested, EN 10204 3.1. | AC13: =IF($G13="VERIFY","PENDING RESEARCH",IF(LEN($AB13)>160,"TRIM ("&LEN($AB13)&")",IF(LEN($AB13)<110,"SHORT ("&LEN($AB13)&")","OK ("&LEN($AB13)&")"))) -> OK (139) | AD13: ="Electropolished Pipes Manufacturer in "&$E13 -> Electropolished Pipes Manufacturer in Ankleshwar | AE13: =CHOOSE($S13,"Electropolished Pipe & Tube Manufacturing for "&$E13&" - Grades, Finishes & Certification","How We Manufacture Electropolished Tube for "&$E13&" Plants","Electropolished Pipes Manufacturer in "&$E13&" - Our Process & Capability","Manufacturing Electropolished SS Tube for "&$E13&": The Standards We Build To","Electropolished Tube Manufacturing Capability Serving "&$E13) -> Electropolished Tube Manufacturing Capability Serving Ankleshwar | AF13: =CHOOSE($S13,"Electropolished Pipes Supplier in "&$E13&" - Stock Sizes, Lead Time & Delivery","Supplying Electropolished Pipes in "&$E13&": Availability, Sizes & Dispatch","Electropolished Pipes Supplier in "&$E13&" - What We Hold in Stock","Electropolished Pipe Supply Into "&$E13&" - Certification & Transit","Electropolished Pipes Supplier in "&$E13&" - From Order to Delivery") -> Electropolished Pipes Supplier in Ankleshwar - From Order to Delivery | AG13: =CHOOSE($S13,"Electropolished Pipes Wholesaler & Stockist in "&$E13&" - Bulk & Project Pricing","Wholesale Electropolished Pipe Supply for "&$E13&" Projects","Bulk & Wholesale Electropolished Pipe Rates for "&$E13&" Buyers","Electropolished Pipes Wholesaler in "&$E13&" - Project Quantities & Terms","Stockist & Wholesale Supply of Electropolished Pipes in "&$E13) -> Stockist & Wholesale Supply of Electropolished Pipes in Ankleshwar | AH13: ="electropolished pipes manufacturer in "&$D13&", electropolished pipes supplier in "&$D13&", electropolished pipes wholesaler in "&$D13&", electropolished tube manufacturer "&$D13&", EP pipe supplier "&$D13&", sanitary tube supplier "&$D13&", ASME BPE tubing "&$D13&", ASTM A270 tube "&$D13&", SS 316L electropolished pipe "&$D13 -> electropolished pipes manufacturer in Ankleshwar, electropolished pipes supplier in Ankleshwar, electropolished pipes wholesaler in Ankleshwar, electropolished tube manufacturer Ankleshwar, EP pipe supplier Ankleshwar, sanitary tube supplier Ankleshwar, ASME BPE tubing Ankleshwar, ASTM A270 tube Ankleshwar, SS 316L electropolished pipe Ankleshwar | AI13: ="Electropolished Pipes Manufacturer & Supplier in "&$E13 -> Electropolished Pipes Manufacturer & Supplier in Ankleshwar | AJ13: ="EP-finished SS 304/316L pipes and tubes for "&$K13&" plants in "&$E13&". ASME BPE SF1-SF4, Ra from 0.25 um, EN 10204 3.1 certificate with every lot." -> EP-finished SS 304/316L pipes and tubes for pharma & API plants in Ankleshwar. ASME BPE SF1-SF4, Ra from 0.25 um, EN 10204 3.1 certificate with every lot. | AK13: ="Electropolished stainless steel pipes supplied by Sakshi Forge to "&$K13&" plants at "&$I13&", "&$E13 -> Electropolished stainless steel pipes supplied by Sakshi Forge to pharma & API plants at Ankleshwar GIDC, Ankleshwar | AL13: ="Electropolished SS 316L tube stock for "&$E13&" - Sakshi Forge" -> Electropolished SS 316L tube stock for Ankleshwar - Sakshi Forge | AM13: ="Home > Market Area > "&$B13&" > "&$C13&" > "&$D13 -> Home > Market Area > India > Gujarat > Ankleshwar | AN13: =IF($F13="A",1400,IF($F13="B",1000,750)) -> 1400 | AO13: =IF($F13="A",10,IF($F13="B",8,6)) -> 10 | AP13: =IF($F13="A",12,IF($F13="B",8,6)) -> 12 | AQ13: =ROUNDUP((ROW()-3)/60,0) -> 1 | AT13: Not started
A14: CTY-0011 | B14: India | C14: Maharashtra | D14: Aurangabad | E14: Aurangabad | F14: A | G14: VERIFIED | H14: Waluj MIDC, Shendra MIDC, Chikalthana MIDC, AURIC Bidkin | I14: Waluj MIDC | J14: Pharmaceutical formulations, brewery, food and dairy, automotive | K14: pharma & food & dairy | L14: JNPT Nhava Sheva (380 km) | M14: 2-3 day road transit from our Mumbai works | N14: CDSCO + state FDA licensed plants; WHO-GMP and USFDA documentation common | O14: VERIFY | P14: =IF($K14="VERIFY","VERIFY",IF(ISNUMBER(SEARCH("semicon",$K14)),"SEMI",IF(ISNUMBER(SEARCH("electronic",$K14)),"SEMI",IF(ISNUMBER(SEARCH("biotech",$K14)),"BIOTECH",IF(ISNUMBER(SEARCH("pharma",$K14)),"PHARMA",IF(ISNUMBER(SEARCH("medical",$K14)),"PHARMA",IF(ISNUMBER(SEARCH("dairy",$K14)),"DAIRY",IF(ISNUMBER(SEARCH("brewery",$K14)),"BREWERY",IF(ISNUMBER(SEARCH("food",$K14)),"FOOD",IF(ISNUMBER(SEARCH("personal care",$K14)),"FOOD",IF(ISNUMBER(SEARCH("chemical",$K14)),"CHEM",IF(ISNUMBER(SEARCH("refining",$K14)),"CHEM",IF(ISNUMBER(SEARCH("petrochem",$K14)),"CHEM",IF(ISNUMBER(SEARCH("fertilis",$K14)),"CHEM",IF(ISNUMBER(SEARCH("water",$K14)),"CHEM","GENERAL"))))))))))))))) -> PHARMA | Q14: =MOD(ROW()-4,8)+1 -> 3 | R14: =MOD(ROW()-4,7)+1 -> 4 | S14: =MOD(ROW()-4,5)+1 -> 1 | T14: =$F14&"-"&(MOD(ROW()-4,6)+1) -> A-5 | U14: ="T"&$Q14&"-M"&$R14&"-H"&$S14&"-F"&$T14&"-"&$P14 -> T3-M4-H1-FA-5-PHARMA | V14: =COUNTIF($U$4:$U$1835,$U14)-1 -> 0 | X14: =IF($W14<>"",$W14,IF($B14="India",LOWER(SUBSTITUTE(SUBSTITUTE($D14," ","-"),".","")),LOWER(SUBSTITUTE(SUBSTITUTE($D14," ","-"),".",""))&"-"&LOWER(SUBSTITUTE($B14," ","-")))) -> aurangabad | Y14: ="https://steelmanufacturer.in/market-area/electropolished-pipes-manufacturer-in-"&$X14&"/" -> https://steelmanufacturer.in/market-area/electropolished-pipes-manufacturer-in-aurangabad/ | Z14: =IF($AR14<>"",$AR14,IF(LEN("Electropolished Pipes Manufacturer in "&$E14&CHOOSE($Q14," | Sakshi Forge"," - ASTM A270 & ASME BPE"," | EP Tube Supplier"," - SS 304/316L EP Tube"," | Sanitary Tube Supply"," - Mill Certified Supply"," | ASME BPE SF1-SF4"," - EP Tube Stockist"))<=65,"Electropolished Pipes Manufacturer in "&$E14&CHOOSE($Q14," | Sakshi Forge"," - ASTM A270 & ASME BPE"," | EP Tube Supplier"," - SS 304/316L EP Tube"," | Sanitary Tube Supply"," - Mill Certified Supply"," | ASME BPE SF1-SF4"," - EP Tube Stockist"),"Electropolished Pipes Manufacturer in "&$E14)) -> Electropolished Pipes Manufacturer in Aurangabad | AA14: =IF(LEN($Z14)>65,"TRIM ("&LEN($Z14)&")",IF(LEN($Z14)<35,"SHORT ("&LEN($Z14)&")","OK ("&LEN($Z14)&")")) -> OK (48) | AB14: =IF($AS14<>"",$AS14,CHOOSE($R14,"EP-finished SS 304/316L pipes & tubes for "&$K14&" plants in "&$E14&". ASTM A270, ASME BPE SF1-SF4, EN 10204 3.1 MTC. PMI tested.","Electropolished tube supply to "&$I14&", "&$E14&". Ra from 0.25 um, SF4 finish, mill test certificate with every lot.","EP stainless tube for "&$K14&" lines in "&$E14&". "&$M14&". ASTM A270 S2, PMI tested, EN 10204 3.1.","Sanitary electropolished pipes in "&$E14&" for "&$K14&" plants. ASME BPE SF1-SF4, orbital-weld ready, 3.1 MTC. Mumbai-made.","Manufacturer of electropolished SS 316L tube serving "&$E14&". "&$M14&". Ra 0.25-0.5 um, EN 10204 3.1 MTC.",IF(LEN("EP tube and pipe for "&$K14&" plants around "&$I14&", "&$E14&". Made at our Mumbai works to ASTM A270 and ASME BPE SF1-SF4, with 3.1 MTC.")<=160,"EP tube and pipe for "&$K14&" plants around "&$I14&", "&$E14&". Made at our Mumbai works to ASTM A270 and ASME BPE SF1-SF4, with 3.1 MTC.","EP tube and pipe for "&$K14&" plants around "&$I14&", "&$E14&". ASTM A270, ASME BPE SF1-SF4, EN 10204 3.1 MTC."),"Electropolished pipes in "&$E14&": 304, 304L, 316 and 316L in SF1-SF4. "&$M14&". Mill certified.")) -> Sanitary electropolished pipes in Aurangabad for pharma & food & dairy plants. ASME BPE SF1-SF4, orbital-weld ready, 3.1 MTC. Mumbai-made. | AC14: =IF($G14="VERIFY","PENDING RESEARCH",IF(LEN($AB14)>160,"TRIM ("&LEN($AB14)&")",IF(LEN($AB14)<110,"SHORT ("&LEN($AB14)&")","OK ("&LEN($AB14)&")"))) -> OK (138) | AD14: ="Electropolished Pipes Manufacturer in "&$E14 -> Electropolished Pipes Manufacturer in Aurangabad | AE14: =CHOOSE($S14,"Electropolished Pipe & Tube Manufacturing for "&$E14&" - Grades, Finishes & Certification","How We Manufacture Electropolished Tube for "&$E14&" Plants","Electropolished Pipes Manufacturer in "&$E14&" - Our Process & Capability","Manufacturing Electropolished SS Tube for "&$E14&": The Standards We Build To","Electropolished Tube Manufacturing Capability Serving "&$E14) -> Electropolished Pipe & Tube Manufacturing for Aurangabad - Grades, Finishes & Certification | AF14: =CHOOSE($S14,"Electropolished Pipes Supplier in "&$E14&" - Stock Sizes, Lead Time & Delivery","Supplying Electropolished Pipes in "&$E14&": Availability, Sizes & Dispatch","Electropolished Pipes Supplier in "&$E14&" - What We Hold in Stock","Electropolished Pipe Supply Into "&$E14&" - Certification & Transit","Electropolished Pipes Supplier in "&$E14&" - From Order to Delivery") -> Electropolished Pipes Supplier in Aurangabad - Stock Sizes, Lead Time & Delivery | AG14: =CHOOSE($S14,"Electropolished Pipes Wholesaler & Stockist in "&$E14&" - Bulk & Project Pricing","Wholesale Electropolished Pipe Supply for "&$E14&" Projects","Bulk & Wholesale Electropolished Pipe Rates for "&$E14&" Buyers","Electropolished Pipes Wholesaler in "&$E14&" - Project Quantities & Terms","Stockist & Wholesale Supply of Electropolished Pipes in "&$E14) -> Electropolished Pipes Wholesaler & Stockist in Aurangabad - Bulk & Project Pricing | AH14: ="electropolished pipes manufacturer in "&$D14&", electropolished pipes supplier in "&$D14&", electropolished pipes wholesaler in "&$D14&", electropolished tube manufacturer "&$D14&", EP pipe supplier "&$D14&", sanitary tube supplier "&$D14&", ASME BPE tubing "&$D14&", ASTM A270 tube "&$D14&", SS 316L electropolished pipe "&$D14 -> electropolished pipes manufacturer in Aurangabad, electropolished pipes supplier in Aurangabad, electropolished pipes wholesaler in Aurangabad, electropolished tube manufacturer Aurangabad, EP pipe supplier Aurangabad, sanitary tube supplier Aurangabad, ASME BPE tubing Aurangabad, ASTM A270 tube Aurangabad, SS 316L electropolished pipe Aurangabad | AI14: ="Electropolished Pipes Manufacturer & Supplier in "&$E14 -> Electropolished Pipes Manufacturer & Supplier in Aurangabad | AJ14: ="EP-finished SS 304/316L pipes and tubes for "&$K14&" plants in "&$E14&". ASME BPE SF1-SF4, Ra from 0.25 um, EN 10204 3.1 certificate with every lot." -> EP-finished SS 304/316L pipes and tubes for pharma & food & dairy plants in Aurangabad. ASME BPE SF1-SF4, Ra from 0.25 um, EN 10204 3.1 certificate with every lot. | AK14: ="Electropolished stainless steel pipes supplied by Sakshi Forge to "&$K14&" plants at "&$I14&", "&$E14 -> Electropolished stainless steel pipes supplied by Sakshi Forge to pharma & food & dairy plants at Waluj MIDC, Aurangabad | AL14: ="Electropolished SS 316L tube stock for "&$E14&" - Sakshi Forge" -> Electropolished SS 316L tube stock for Aurangabad - Sakshi Forge | AM14: ="Home > Market Area > "&$B14&" > "&$C14&" > "&$D14 -> Home > Market Area > India > Maharashtra > Aurangabad | AN14: =IF($F14="A",1400,IF($F14="B",1000,750)) -> 1400 | AO14: =IF($F14="A",10,IF($F14="B",8,6)) -> 10 | AP14: =IF($F14="A",12,IF($F14="B",8,6)) -> 12 | AQ14: =ROUNDUP((ROW()-3)/60,0) -> 1 | AT14: Not started
A15: CTY-0012 | B15: India | C15: Himachal Pradesh | D15: Baddi | E15: Baddi | F15: A | G15: VERIFIED | H15: Baddi Industrial Area, EPIP Phase I & II | I15: Baddi Industrial Area | J15: Pharmaceutical formulations, FMCG, packaging | K15: pharma | L15: ICD Ludhiana (120 km) | M15: 1-2 day road transit from our Mumbai works | N15: CDSCO + state FDA licensed plants; WHO-GMP and USFDA documentation common | O15: VERIFY | P15: =IF($K15="VERIFY","VERIFY",IF(ISNUMBER(SEARCH("semicon",$K15)),"SEMI",IF(ISNUMBER(SEARCH("electronic",$K15)),"SEMI",IF(ISNUMBER(SEARCH("biotech",$K15)),"BIOTECH",IF(ISNUMBER(SEARCH("pharma",$K15)),"PHARMA",IF(ISNUMBER(SEARCH("medical",$K15)),"PHARMA",IF(ISNUMBER(SEARCH("dairy",$K15)),"DAIRY",IF(ISNUMBER(SEARCH("brewery",$K15)),"BREWERY",IF(ISNUMBER(SEARCH("food",$K15)),"FOOD",IF(ISNUMBER(SEARCH("personal care",$K15)),"FOOD",IF(ISNUMBER(SEARCH("chemical",$K15)),"CHEM",IF(ISNUMBER(SEARCH("refining",$K15)),"CHEM",IF(ISNUMBER(SEARCH("petrochem",$K15)),"CHEM",IF(ISNUMBER(SEARCH("fertilis",$K15)),"CHEM",IF(ISNUMBER(SEARCH("water",$K15)),"CHEM","GENERAL"))))))))))))))) -> PHARMA | Q15: =MOD(ROW()-4,8)+1 -> 4 | R15: =MOD(ROW()-4,7)+1 -> 5 | S15: =MOD(ROW()-4,5)+1 -> 2 | T15: =$F15&"-"&(MOD(ROW()-4,6)+1) -> A-6 | U15: ="T"&$Q15&"-M"&$R15&"-H"&$S15&"-F"&$T15&"-"&$P15 -> T4-M5-H2-FA-6-PHARMA | V15: =COUNTIF($U$4:$U$1835,$U15)-1 -> 0 | X15: =IF($W15<>"",$W15,IF($B15="India",LOWER(SUBSTITUTE(SUBSTITUTE($D15," ","-"),".","")),LOWER(SUBSTITUTE(SUBSTITUTE($D15," ","-"),".",""))&"-"&LOWER(SUBSTITUTE($B15," ","-")))) -> baddi | Y15: ="https://steelmanufacturer.in/market-area/electropolished-pipes-manufacturer-in-"&$X15&"/" -> https://steelmanufacturer.in/market-area/electropolished-pipes-manufacturer-in-baddi/ | Z15: =IF($AR15<>"",$AR15,IF(LEN("Electropolished Pipes Manufacturer in "&$E15&CHOOSE($Q15," | Sakshi Forge"," - ASTM A270 & ASME BPE"," | EP Tube Supplier"," - SS 304/316L EP Tube"," | Sanitary Tube Supply"," - Mill Certified Supply"," | ASME BPE SF1-SF4"," - EP Tube Stockist"))<=65,"Electropolished Pipes Manufacturer in "&$E15&CHOOSE($Q15," | Sakshi Forge"," - ASTM A270 & ASME BPE"," | EP Tube Supplier"," - SS 304/316L EP Tube"," | Sanitary Tube Supply"," - Mill Certified Supply"," | ASME BPE SF1-SF4"," - EP Tube Stockist"),"Electropolished Pipes Manufacturer in "&$E15)) -> Electropolished Pipes Manufacturer in Baddi - SS 304/316L EP Tube | AA15: =IF(LEN($Z15)>65,"TRIM ("&LEN($Z15)&")",IF(LEN($Z15)<35,"SHORT ("&LEN($Z15)&")","OK ("&LEN($Z15)&")")) -> OK (65) | AB15: =IF($AS15<>"",$AS15,CHOOSE($R15,"EP-finished SS 304/316L pipes & tubes for "&$K15&" plants in "&$E15&". ASTM A270, ASME BPE SF1-SF4, EN 10204 3.1 MTC. PMI tested.","Electropolished tube supply to "&$I15&", "&$E15&". Ra from 0.25 um, SF4 finish, mill test certificate with every lot.","EP stainless tube for "&$K15&" lines in "&$E15&". "&$M15&". ASTM A270 S2, PMI tested, EN 10204 3.1.","Sanitary electropolished pipes in "&$E15&" for "&$K15&" plants. ASME BPE SF1-SF4, orbital-weld ready, 3.1 MTC. Mumbai-made.","Manufacturer of electropolished SS 316L tube serving "&$E15&". "&$M15&". Ra 0.25-0.5 um, EN 10204 3.1 MTC.",IF(LEN("EP tube and pipe for "&$K15&" plants around "&$I15&", "&$E15&". Made at our Mumbai works to ASTM A270 and ASME BPE SF1-SF4, with 3.1 MTC.")<=160,"EP tube and pipe for "&$K15&" plants around "&$I15&", "&$E15&". Made at our Mumbai works to ASTM A270 and ASME BPE SF1-SF4, with 3.1 MTC.","EP tube and pipe for "&$K15&" plants around "&$I15&", "&$E15&". ASTM A270, ASME BPE SF1-SF4, EN 10204 3.1 MTC."),"Electropolished pipes in "&$E15&": 304, 304L, 316 and 316L in SF1-SF4. "&$M15&". Mill certified.")) -> Manufacturer of electropolished SS 316L tube serving Baddi. 1-2 day road transit from our Mumbai works. Ra 0.25-0.5 um, EN 10204 3.1 MTC. | AC15: =IF($G15="VERIFY","PENDING RESEARCH",IF(LEN($AB15)>160,"TRIM ("&LEN($AB15)&")",IF(LEN($AB15)<110,"SHORT ("&LEN($AB15)&")","OK ("&LEN($AB15)&")"))) -> OK (137) | AD15: ="Electropolished Pipes Manufacturer in "&$E15 -> Electropolished Pipes Manufacturer in Baddi | AE15: =CHOOSE($S15,"Electropolished Pipe & Tube Manufacturing for "&$E15&" - Grades, Finishes & Certification","How We Manufacture Electropolished Tube for "&$E15&" Plants","Electropolished Pipes Manufacturer in "&$E15&" - Our Process & Capability","Manufacturing Electropolished SS Tube for "&$E15&": The Standards We Build To","Electropolished Tube Manufacturing Capability Serving "&$E15) -> How We Manufacture Electropolished Tube for Baddi Plants | AF15: =CHOOSE($S15,"Electropolished Pipes Supplier in "&$E15&" - Stock Sizes, Lead Time & Delivery","Supplying Electropolished Pipes in "&$E15&": Availability, Sizes & Dispatch","Electropolished Pipes Supplier in "&$E15&" - What We Hold in Stock","Electropolished Pipe Supply Into "&$E15&" - Certification & Transit","Electropolished Pipes Supplier in "&$E15&" - From Order to Delivery") -> Supplying Electropolished Pipes in Baddi: Availability, Sizes & Dispatch | AG15: =CHOOSE($S15,"Electropolished Pipes Wholesaler & Stockist in "&$E15&" - Bulk & Project Pricing","Wholesale Electropolished Pipe Supply for "&$E15&" Projects","Bulk & Wholesale Electropolished Pipe Rates for "&$E15&" Buyers","Electropolished Pipes Wholesaler in "&$E15&" - Project Quantities & Terms","Stockist & Wholesale Supply of Electropolished Pipes in "&$E15) -> Wholesale Electropolished Pipe Supply for Baddi Projects | AH15: ="electropolished pipes manufacturer in "&$D15&", electropolished pipes supplier in "&$D15&", electropolished pipes wholesaler in "&$D15&", electropolished tube manufacturer "&$D15&", EP pipe supplier "&$D15&", sanitary tube supplier "&$D15&", ASME BPE tubing "&$D15&", ASTM A270 tube "&$D15&", SS 316L electropolished pipe "&$D15 -> electropolished pipes manufacturer in Baddi, electropolished pipes supplier in Baddi, electropolished pipes wholesaler in Baddi, electropolished tube manufacturer Baddi, EP pipe supplier Baddi, sanitary tube supplier Baddi, ASME BPE tubing Baddi, ASTM A270 tube Baddi, SS 316L electropolished pipe Baddi | AI15: ="Electropolished Pipes Manufacturer & Supplier in "&$E15 -> Electropolished Pipes Manufacturer & Supplier in Baddi | AJ15: ="EP-finished SS 304/316L pipes and tubes for "&$K15&" plants in "&$E15&". ASME BPE SF1-SF4, Ra from 0.25 um, EN 10204 3.1 certificate with every lot." -> EP-finished SS 304/316L pipes and tubes for pharma plants in Baddi. ASME BPE SF1-SF4, Ra from 0.25 um, EN 10204 3.1 certificate with every lot. | AK15: ="Electropolished stainless steel pipes supplied by Sakshi Forge to "&$K15&" plants at "&$I15&", "&$E15 -> Electropolished stainless steel pipes supplied by Sakshi Forge to pharma plants at Baddi Industrial Area, Baddi | AL15: ="Electropolished SS 316L tube stock for "&$E15&" - Sakshi Forge" -> Electropolished SS 316L tube stock for Baddi - Sakshi Forge | AM15: ="Home > Market Area > "&$B15&" > "&$C15&" > "&$D15 -> Home > Market Area > India > Himachal Pradesh > Baddi | AN15: =IF($F15="A",1400,IF($F15="B",1000,750)) -> 1400 | AO15: =IF($F15="A",10,IF($F15="B",8,6)) -> 10 | AP15: =IF($F15="A",12,IF($F15="B",8,6)) -> 12 | AQ15: =ROUNDUP((ROW()-3)/60,0) -> 1 | AT15: Not started
... A994: CTY-0991 | B994: India | C994: Maharashtra | D994: Dindori | E994: Dindori, Maharashtra | F994: C | G994: VERIFY | H994: MIDC Industrial Area, Dindori | I994: MIDC Industrial Area | J994: VERIFY | K994: VERIFY | L994: VERIFY | M994: VERIFY | N994: VERIFY | O994: VERIFY | P994: =IF($K994="VERIFY","VERIFY",IF(ISNUMBER(SEARCH("semicon",$K994)),"SEMI",IF(ISNUMBER(SEARCH("electronic",$K994)),"SEMI",IF(ISNUMBER(SEARCH("biotech",$K994)),"BIOTECH",IF(ISNUMBER(SEARCH("pharma",$K994)),"PHARMA",IF(ISNUMBER(SEARCH("medical",$K994)),"PHARMA",IF(ISNUMBER(SEARCH("dairy",$K994)),"DAIRY",IF(ISNUMBER(SEARCH("brewery",$K994)),"BREWERY",IF(ISNUMBER(SEARCH("food",$K994)),"FOOD",IF(ISNUMBER(SEARCH("personal care",$K994)),"FOOD",IF(ISNUMBER(SEARCH("chemical",$K994)),"CHEM",IF(ISNUMBER(SEARCH("refining",$K994)),"CHEM",IF(ISNUMBER(SEARCH("petrochem",$K994)),"CHEM",IF(ISNUMBER(SEARCH("fertilis",$K994)),"CHEM",IF(ISNUMBER(SEARCH("water",$K994)),"CHEM","GENERAL"))))))))))))))) -> VERIFY | Q994: =MOD(ROW()-4,8)+1 -> 7 | R994: =MOD(ROW()-4,7)+1 -> 4 | S994: =MOD(ROW()-4,5)+1 -> 1 | T994: =$F994&"-"&(MOD(ROW()-4,6)+1) -> C-1 | U994: ="T"&$Q994&"-M"&$R994&"-H"&$S994&"-F"&$T994&"-"&$P994 -> T7-M4-H1-FC-1-VERIFY | V994: =COUNTIF($U$4:$U$1835,$U994)-1 -> 1 | X994: =IF($W994<>"",$W994,IF($B994="India",LOWER(SUBSTITUTE(SUBSTITUTE($D994," ","-"),".","")),LOWER(SUBSTITUTE(SUBSTITUTE($D994," ","-"),".",""))&"-"&LOWER(SUBSTITUTE($B994," ","-")))) -> dindori | Y994: ="https://steelmanufacturer.in/market-area/electropolished-pipes-manufacturer-in-"&$X994&"/" -> https://steelmanufacturer.in/market-area/electropolished-pipes-manufacturer-in-dindori/ | Z994: =IF($AR994<>"",$AR994,IF(LEN("Electropolished Pipes Manufacturer in "&$E994&CHOOSE($Q994," | Sakshi Forge"," - ASTM A270 & ASME BPE"," | EP Tube Supplier"," - SS 304/316L EP Tube"," | Sanitary Tube Supply"," - Mill Certified Supply"," | ASME BPE SF1-SF4"," - EP Tube Stockist"))<=65,"Electropolished Pipes Manufacturer in "&$E994&CHOOSE($Q994," | Sakshi Forge"," - ASTM A270 & ASME BPE"," | EP Tube Supplier"," - SS 304/316L EP Tube"," | Sanitary Tube Supply"," - Mill Certified Supply"," | ASME BPE SF1-SF4"," - EP Tube Stockist"),"Electropolished Pipes Manufacturer in "&$E994)) -> Electropolished Pipes Manufacturer in Dindori, Maharashtra | AA994: =IF(LEN($Z994)>65,"TRIM ("&LEN($Z994)&")",IF(LEN($Z994)<35,"SHORT ("&LEN($Z994)&")","OK ("&LEN($Z994)&")")) -> OK (58) | AB994: =IF($AS994<>"",$AS994,CHOOSE($R994,"EP-finished SS 304/316L pipes & tubes for "&$K994&" plants in "&$E994&". ASTM A270, ASME BPE SF1-SF4, EN 10204 3.1 MTC. PMI tested.","Electropolished tube supply to "&$I994&", "&$E994&". Ra from 0.25 um, SF4 finish, mill test certificate with every lot.","EP stainless tube for "&$K994&" lines in "&$E994&". "&$M994&". ASTM A270 S2, PMI tested, EN 10204 3.1.","Sanitary electropolished pipes in "&$E994&" for "&$K994&" plants. ASME BPE SF1-SF4, orbital-weld ready, 3.1 MTC. Mumbai-made.","Manufacturer of electropolished SS 316L tube serving "&$E994&". "&$M994&". Ra 0.25-0.5 um, EN 10204 3.1 MTC.",IF(LEN("EP tube and pipe for "&$K994&" plants around "&$I994&", "&$E994&". Made at our Mumbai works to ASTM A270 and ASME BPE SF1-SF4, with 3.1 MTC.")<=160,"EP tube and pipe for "&$K994&" plants around "&$I994&", "&$E994&". Made at our Mumbai works to ASTM A270 and ASME BPE SF1-SF4, with 3.1 MTC.","EP tube and pipe for "&$K994&" plants around "&$I994&", "&$E994&". ASTM A270, ASME BPE SF1-SF4, EN 10204 3.1 MTC."),"Electropolished pipes in "&$E994&": 304, 304L, 316 and 316L in SF1-SF4. "&$M994&". Mill certified.")) -> Sanitary electropolished pipes in Dindori, Maharashtra for VERIFY plants. ASME BPE SF1-SF4, orbital-weld ready, 3.1 MTC. Mumbai-made. | AC994: =IF($G994="VERIFY","PENDING RESEARCH",IF(LEN($AB994)>160,"TRIM ("&LEN($AB994)&")",IF(LEN($AB994)<110,"SHORT ("&LEN($AB994)&")","OK ("&LEN($AB994)&")"))) -> PENDING RESEARCH | AD994: ="Electropolished Pipes Manufacturer in "&$E994 -> Electropolished Pipes Manufacturer in Dindori, Maharashtra | AE994: =CHOOSE($S994,"Electropolished Pipe & Tube Manufacturing for "&$E994&" - Grades, Finishes & Certification","How We Manufacture Electropolished Tube for "&$E994&" Plants","Electropolished Pipes Manufacturer in "&$E994&" - Our Process & Capability","Manufacturing Electropolished SS Tube for "&$E994&": The Standards We Build To","Electropolished Tube Manufacturing Capability Serving "&$E994) -> Electropolished Pipe & Tube Manufacturing for Dindori, Maharashtra - Grades, Finishes & Certification | AF994: =CHOOSE($S994,"Electropolished Pipes Supplier in "&$E994&" - Stock Sizes, Lead Time & Delivery","Supplying Electropolished Pipes in "&$E994&": Availability, Sizes & Dispatch","Electropolished Pipes Supplier in "&$E994&" - What We Hold in Stock","Electropolished Pipe Supply Into "&$E994&" - Certification & Transit","Electropolished Pipes Supplier in "&$E994&" - From Order to Delivery") -> Electropolished Pipes Supplier in Dindori, Maharashtra - Stock Sizes, Lead Time & Delivery | AG994: =CHOOSE($S994,"Electropolished Pipes Wholesaler & Stockist in "&$E994&" - Bulk & Project Pricing","Wholesale Electropolished Pipe Supply for "&$E994&" Projects","Bulk & Wholesale Electropolished Pipe Rates for "&$E994&" Buyers","Electropolished Pipes Wholesaler in "&$E994&" - Project Quantities & Terms","Stockist & Wholesale Supply of Electropolished Pipes in "&$E994) -> Electropolished Pipes Wholesaler & Stockist in Dindori, Maharashtra - Bulk & Project Pricing | AH994: ="electropolished pipes manufacturer in "&$D994&", electropolished pipes supplier in "&$D994&", electropolished pipes wholesaler in "&$D994&", electropolished tube manufacturer "&$D994&", EP pipe supplier "&$D994&", sanitary tube supplier "&$D994&", ASME BPE tubing "&$D994&", ASTM A270 tube "&$D994&", SS 316L electropolished pipe "&$D994 -> electropolished pipes manufacturer in Dindori, electropolished pipes supplier in Dindori, electropolished pipes wholesaler in Dindori, electropolished tube manufacturer Dindori, EP pipe supplier Dindori, sanitary tube supplier Dindori, ASME BPE tubing Dindori, ASTM A270 tube Dindori, SS 316L electropolished pipe Dindori | AI994: ="Electropolished Pipes Manufacturer & Supplier in "&$E994 -> Electropolished Pipes Manufacturer & Supplier in Dindori, Maharashtra | AJ994: ="EP-finished SS 304/316L pipes and tubes for "&$K994&" plants in "&$E994&". ASME BPE SF1-SF4, Ra from 0.25 um, EN 10204 3.1 certificate with every lot." -> EP-finished SS 304/316L pipes and tubes for VERIFY plants in Dindori, Maharashtra. ASME BPE SF1-SF4, Ra from 0.25 um, EN 10204 3.1 certificate with every lot. | AK994: ="Electropolished stainless steel pipes supplied by Sakshi Forge to "&$K994&" plants at "&$I994&", "&$E994 -> Electropolished stainless steel pipes supplied by Sakshi Forge to VERIFY plants at MIDC Industrial Area, Dindori, Maharashtra | AL994: ="Electropolished SS 316L tube stock for "&$E994&" - Sakshi Forge" -> Electropolished SS 316L tube stock for Dindori, Maharashtra - Sakshi Forge | AM994: ="Home > Market Area > "&$B994&" > "&$C994&" > "&$D994 -> Home > Market Area > India > Maharashtra > Dindori | AN994: =IF($F994="A",1400,IF($F994="B",1000,750)) -> 750 | AO994: =IF($F994="A",10,IF($F994="B",8,6)) -> 6 | AP994: =IF($F994="A",12,IF($F994="B",8,6)) -> 6 | AQ994: =ROUNDUP((ROW()-3)/60,0) -> 17 | AT994: Not started
A995: CTY-0992 | B995: India | C995: Madhya Pradesh | D995: Dindori | E995: Dindori, Madhya Pradesh | F995: C | G995: VERIFY | H995: MPIDC Industrial Area, Dindori | I995: MPIDC Industrial Area | J995: VERIFY | K995: VERIFY | L995: VERIFY | M995: VERIFY | N995: VERIFY | O995: VERIFY | P995: =IF($K995="VERIFY","VERIFY",IF(ISNUMBER(SEARCH("semicon",$K995)),"SEMI",IF(ISNUMBER(SEARCH("electronic",$K995)),"SEMI",IF(ISNUMBER(SEARCH("biotech",$K995)),"BIOTECH",IF(ISNUMBER(SEARCH("pharma",$K995)),"PHARMA",IF(ISNUMBER(SEARCH("medical",$K995)),"PHARMA",IF(ISNUMBER(SEARCH("dairy",$K995)),"DAIRY",IF(ISNUMBER(SEARCH("brewery",$K995)),"BREWERY",IF(ISNUMBER(SEARCH("food",$K995)),"FOOD",IF(ISNUMBER(SEARCH("personal care",$K995)),"FOOD",IF(ISNUMBER(SEARCH("chemical",$K995)),"CHEM",IF(ISNUMBER(SEARCH("refining",$K995)),"CHEM",IF(ISNUMBER(SEARCH("petrochem",$K995)),"CHEM",IF(ISNUMBER(SEARCH("fertilis",$K995)),"CHEM",IF(ISNUMBER(SEARCH("water",$K995)),"CHEM","GENERAL"))))))))))))))) -> VERIFY | Q995: =MOD(ROW()-4,8)+1 -> 8 | R995: =MOD(ROW()-4,7)+1 -> 5 | S995: =MOD(ROW()-4,5)+1 -> 2 | T995: =$F995&"-"&(MOD(ROW()-4,6)+1) -> C-2 | U995: ="T"&$Q995&"-M"&$R995&"-H"&$S995&"-F"&$T995&"-"&$P995 -> T8-M5-H2-FC-2-VERIFY | V995: =COUNTIF($U$4:$U$1835,$U995)-1 -> 1 | W995: dindori-madhya-pradesh | X995: =IF($W995<>"",$W995,IF($B995="India",LOWER(SUBSTITUTE(SUBSTITUTE($D995," ","-"),".","")),LOWER(SUBSTITUTE(SUBSTITUTE($D995," ","-"),".",""))&"-"&LOWER(SUBSTITUTE($B995," ","-")))) -> dindori-madhya-pradesh | Y995: ="https://steelmanufacturer.in/market-area/electropolished-pipes-manufacturer-in-"&$X995&"/" -> https://steelmanufacturer.in/market-area/electropolished-pipes-manufacturer-in-dindori-madhya-pradesh/ | Z995: =IF($AR995<>"",$AR995,IF(LEN("Electropolished Pipes Manufacturer in "&$E995&CHOOSE($Q995," | Sakshi Forge"," - ASTM A270 & ASME BPE"," | EP Tube Supplier"," - SS 304/316L EP Tube"," | Sanitary Tube Supply"," - Mill Certified Supply"," | ASME BPE SF1-SF4"," - EP Tube Stockist"))<=65,"Electropolished Pipes Manufacturer in "&$E995&CHOOSE($Q995," | Sakshi Forge"," - ASTM A270 & ASME BPE"," | EP Tube Supplier"," - SS 304/316L EP Tube"," | Sanitary Tube Supply"," - Mill Certified Supply"," | ASME BPE SF1-SF4"," - EP Tube Stockist"),"Electropolished Pipes Manufacturer in "&$E995)) -> Electropolished Pipes Manufacturer in Dindori, Madhya Pradesh | AA995: =IF(LEN($Z995)>65,"TRIM ("&LEN($Z995)&")",IF(LEN($Z995)<35,"SHORT ("&LEN($Z995)&")","OK ("&LEN($Z995)&")")) -> OK (61) | AB995: =IF($AS995<>"",$AS995,CHOOSE($R995,"EP-finished SS 304/316L pipes & tubes for "&$K995&" plants in "&$E995&". ASTM A270, ASME BPE SF1-SF4, EN 10204 3.1 MTC. PMI tested.","Electropolished tube supply to "&$I995&", "&$E995&". Ra from 0.25 um, SF4 finish, mill test certificate with every lot.","EP stainless tube for "&$K995&" lines in "&$E995&". "&$M995&". ASTM A270 S2, PMI tested, EN 10204 3.1.","Sanitary electropolished pipes in "&$E995&" for "&$K995&" plants. ASME BPE SF1-SF4, orbital-weld ready, 3.1 MTC. Mumbai-made.","Manufacturer of electropolished SS 316L tube serving "&$E995&". "&$M995&". Ra 0.25-0.5 um, EN 10204 3.1 MTC.",IF(LEN("EP tube and pipe for "&$K995&" plants around "&$I995&", "&$E995&". Made at our Mumbai works to ASTM A270 and ASME BPE SF1-SF4, with 3.1 MTC.")<=160,"EP tube and pipe for "&$K995&" plants around "&$I995&", "&$E995&". Made at our Mumbai works to ASTM A270 and ASME BPE SF1-SF4, with 3.1 MTC.","EP tube and pipe for "&$K995&" plants around "&$I995&", "&$E995&". ASTM A270, ASME BPE SF1-SF4, EN 10204 3.1 MTC."),"Electropolished pipes in "&$E995&": 304, 304L, 316 and 316L in SF1-SF4. "&$M995&". Mill certified.")) -> Manufacturer of electropolished SS 316L tube serving Dindori, Madhya Pradesh. VERIFY. Ra 0.25-0.5 um, EN 10204 3.1 MTC. | AC995: =IF($G995="VERIFY","PENDING RESEARCH",IF(LEN($AB995)>160,"TRIM ("&LEN($AB995)&")",IF(LEN($AB995)<110,"SHORT ("&LEN($AB995)&")","OK ("&LEN($AB995)&")"))) -> PENDING RESEARCH | AD995: ="Electropolished Pipes Manufacturer in "&$E995 -> Electropolished Pipes Manufacturer in Dindori, Madhya Pradesh | AE995: =CHOOSE($S995,"Electropolished Pipe & Tube Manufacturing for "&$E995&" - Grades, Finishes & Certification","How We Manufacture Electropolished Tube for "&$E995&" Plants","Electropolished Pipes Manufacturer in "&$E995&" - Our Process & Capability","Manufacturing Electropolished SS Tube for "&$E995&": The Standards We Build To","Electropolished Tube Manufacturing Capability Serving "&$E995) -> How We Manufacture Electropolished Tube for Dindori, Madhya Pradesh Plants | AF995: =CHOOSE($S995,"Electropolished Pipes Supplier in "&$E995&" - Stock Sizes, Lead Time & Delivery","Supplying Electropolished Pipes in "&$E995&": Availability, Sizes & Dispatch","Electropolished Pipes Supplier in "&$E995&" - What We Hold in Stock","Electropolished Pipe Supply Into "&$E995&" - Certification & Transit","Electropolished Pipes Supplier in "&$E995&" - From Order to Delivery") -> Supplying Electropolished Pipes in Dindori, Madhya Pradesh: Availability, Sizes & Dispatch | AG995: =CHOOSE($S995,"Electropolished Pipes Wholesaler & Stockist in "&$E995&" - Bulk & Project Pricing","Wholesale Electropolished Pipe Supply for "&$E995&" Projects","Bulk & Wholesale Electropolished Pipe Rates for "&$E995&" Buyers","Electropolished Pipes Wholesaler in "&$E995&" - Project Quantities & Terms","Stockist & Wholesale Supply of Electropolished Pipes in "&$E995) -> Wholesale Electropolished Pipe Supply for Dindori, Madhya Pradesh Projects | AH995: ="electropolished pipes manufacturer in "&$D995&", electropolished pipes supplier in "&$D995&", electropolished pipes wholesaler in "&$D995&", electropolished tube manufacturer "&$D995&", EP pipe supplier "&$D995&", sanitary tube supplier "&$D995&", ASME BPE tubing "&$D995&", ASTM A270 tube "&$D995&", SS 316L electropolished pipe "&$D995 -> electropolished pipes manufacturer in Dindori, electropolished pipes supplier in Dindori, electropolished pipes wholesaler in Dindori, electropolished tube manufacturer Dindori, EP pipe supplier Dindori, sanitary tube supplier Dindori, ASME BPE tubing Dindori, ASTM A270 tube Dindori, SS 316L electropolished pipe Dindori | AI995: ="Electropolished Pipes Manufacturer & Supplier in "&$E995 -> Electropolished Pipes Manufacturer & Supplier in Dindori, Madhya Pradesh | AJ995: ="EP-finished SS 304/316L pipes and tubes for "&$K995&" plants in "&$E995&". ASME BPE SF1-SF4, Ra from 0.25 um, EN 10204 3.1 certificate with every lot." -> EP-finished SS 304/316L pipes and tubes for VERIFY plants in Dindori, Madhya Pradesh. ASME BPE SF1-SF4, Ra from 0.25 um, EN 10204 3.1 certificate with every lot. | AK995: ="Electropolished stainless steel pipes supplied by Sakshi Forge to "&$K995&" plants at "&$I995&", "&$E995 -> Electropolished stainless steel pipes supplied by Sakshi Forge to VERIFY plants at MPIDC Industrial Area, Dindori, Madhya Pradesh | AL995: ="Electropolished SS 316L tube stock for "&$E995&" - Sakshi Forge" -> Electropolished SS 316L tube stock for Dindori, Madhya Pradesh - Sakshi Forge | AM995: ="Home > Market Area > "&$B995&" > "&$C995&" > "&$D995 -> Home > Market Area > India > Madhya Pradesh > Dindori | AN995: =IF($F995="A",1400,IF($F995="B",1000,750)) -> 750 | AO995: =IF($F995="A",10,IF($F995="B",8,6)) -> 6 | AP995: =IF($F995="A",12,IF($F995="B",8,6)) -> 6 | AQ995: =ROUNDUP((ROW()-3)/60,0) -> 17 | AT995: Not started
A996: CTY-0993 | B996: India | C996: Assam | D996: Diphu | E996: Diphu | F996: C | G996: VERIFY | H996: AIDC Industrial Area, Diphu | I996: AIDC Industrial Area | J996: VERIFY | K996: VERIFY | L996: VERIFY | M996: VERIFY | N996: VERIFY | O996: VERIFY | P996: =IF($K996="VERIFY","VERIFY",IF(ISNUMBER(SEARCH("semicon",$K996)),"SEMI",IF(ISNUMBER(SEARCH("electronic",$K996)),"SEMI",IF(ISNUMBER(SEARCH("biotech",$K996)),"BIOTECH",IF(ISNUMBER(SEARCH("pharma",$K996)),"PHARMA",IF(ISNUMBER(SEARCH("medical",$K996)),"PHARMA",IF(ISNUMBER(SEARCH("dairy",$K996)),"DAIRY",IF(ISNUMBER(SEARCH("brewery",$K996)),"BREWERY",IF(ISNUMBER(SEARCH("food",$K996)),"FOOD",IF(ISNUMBER(SEARCH("personal care",$K996)),"FOOD",IF(ISNUMBER(SEARCH("chemical",$K996)),"CHEM",IF(ISNUMBER(SEARCH("refining",$K996)),"CHEM",IF(ISNUMBER(SEARCH("petrochem",$K996)),"CHEM",IF(ISNUMBER(SEARCH("fertilis",$K996)),"CHEM",IF(ISNUMBER(SEARCH("water",$K996)),"CHEM","GENERAL"))))))))))))))) -> VERIFY | Q996: =MOD(ROW()-4,8)+1 -> 1 | R996: =MOD(ROW()-4,7)+1 -> 6 | S996: =MOD(ROW()-4,5)+1 -> 3 | T996: =$F996&"-"&(MOD(ROW()-4,6)+1) -> C-3 | U996: ="T"&$Q996&"-M"&$R996&"-H"&$S996&"-F"&$T996&"-"&$P996 -> T1-M6-H3-FC-3-VERIFY | V996: =COUNTIF($U$4:$U$1835,$U996)-1 -> 0 | X996: =IF($W996<>"",$W996,IF($B996="India",LOWER(SUBSTITUTE(SUBSTITUTE($D996," ","-"),".","")),LOWER(SUBSTITUTE(SUBSTITUTE($D996," ","-"),".",""))&"-"&LOWER(SUBSTITUTE($B996," ","-")))) -> diphu | Y996: ="https://steelmanufacturer.in/market-area/electropolished-pipes-manufacturer-in-"&$X996&"/" -> https://steelmanufacturer.in/market-area/electropolished-pipes-manufacturer-in-diphu/ | Z996: =IF($AR996<>"",$AR996,IF(LEN("Electropolished Pipes Manufacturer in "&$E996&CHOOSE($Q996," | Sakshi Forge"," - ASTM A270 & ASME BPE"," | EP Tube Supplier"," - SS 304/316L EP Tube"," | Sanitary Tube Supply"," - Mill Certified Supply"," | ASME BPE SF1-SF4"," - EP Tube Stockist"))<=65,"Electropolished Pipes Manufacturer in "&$E996&CHOOSE($Q996," | Sakshi Forge"," - ASTM A270 & ASME BPE"," | EP Tube Supplier"," - SS 304/316L EP Tube"," | Sanitary Tube Supply"," - Mill Certified Supply"," | ASME BPE SF1-SF4"," - EP Tube Stockist"),"Electropolished Pipes Manufacturer in "&$E996)) -> Electropolished Pipes Manufacturer in Diphu | Sakshi Forge | AA996: =IF(LEN($Z996)>65,"TRIM ("&LEN($Z996)&")",IF(LEN($Z996)<35,"SHORT ("&LEN($Z996)&")","OK ("&LEN($Z996)&")")) -> OK (58) | AB996: =IF($AS996<>"",$AS996,CHOOSE($R996,"EP-finished SS 304/316L pipes & tubes for "&$K996&" plants in "&$E996&". ASTM A270, ASME BPE SF1-SF4, EN 10204 3.1 MTC. PMI tested.","Electropolished tube supply to "&$I996&", "&$E996&". Ra from 0.25 um, SF4 finish, mill test certificate with every lot.","EP stainless tube for "&$K996&" lines in "&$E996&". "&$M996&". ASTM A270 S2, PMI tested, EN 10204 3.1.","Sanitary electropolished pipes in "&$E996&" for "&$K996&" plants. ASME BPE SF1-SF4, orbital-weld ready, 3.1 MTC. Mumbai-made.","Manufacturer of electropolished SS 316L tube serving "&$E996&". "&$M996&". Ra 0.25-0.5 um, EN 10204 3.1 MTC.",IF(LEN("EP tube and pipe for "&$K996&" plants around "&$I996&", "&$E996&". Made at our Mumbai works to ASTM A270 and ASME BPE SF1-SF4, with 3.1 MTC.")<=160,"EP tube and pipe for "&$K996&" plants around "&$I996&", "&$E996&". Made at our Mumbai works to ASTM A270 and ASME BPE SF1-SF4, with 3.1 MTC.","EP tube and pipe for "&$K996&" plants around "&$I996&", "&$E996&". ASTM A270, ASME BPE SF1-SF4, EN 10204 3.1 MTC."),"Electropolished pipes in "&$E996&": 304, 304L, 316 and 316L in SF1-SF4. "&$M996&". Mill certified.")) -> EP tube and pipe for VERIFY plants around AIDC Industrial Area, Diphu. Made at our Mumbai works to ASTM A270 and ASME BPE SF1-SF4, with 3.1 MTC. | AC996: =IF($G996="VERIFY","PENDING RESEARCH",IF(LEN($AB996)>160,"TRIM ("&LEN($AB996)&")",IF(LEN($AB996)<110,"SHORT ("&LEN($AB996)&")","OK ("&LEN($AB996)&")"))) -> PENDING RESEARCH | AD996: ="Electropolished Pipes Manufacturer in "&$E996 -> Electropolished Pipes Manufacturer in Diphu | AE996: =CHOOSE($S996,"Electropolished Pipe & Tube Manufacturing for "&$E996&" - Grades, Finishes & Certification","How We Manufacture Electropolished Tube for "&$E996&" Plants","Electropolished Pipes Manufacturer in "&$E996&" - Our Process & Capability","Manufacturing Electropolished SS Tube for "&$E996&": The Standards We Build To","Electropolished Tube Manufacturing Capability Serving "&$E996) -> Electropolished Pipes Manufacturer in Diphu - Our Process & Capability | AF996: =CHOOSE($S996,"Electropolished Pipes Supplier in "&$E996&" - Stock Sizes, Lead Time & Delivery","Supplying Electropolished Pipes in "&$E996&": Availability, Sizes & Dispatch","Electropolished Pipes Supplier in "&$E996&" - What We Hold in Stock","Electropolished Pipe Supply Into "&$E996&" - Certification & Transit","Electropolished Pipes Supplier in "&$E996&" - From Order to Delivery") -> Electropolished Pipes Supplier in Diphu - What We Hold in Stock | AG996: =CHOOSE($S996,"Electropolished Pipes Wholesaler & Stockist in "&$E996&" - Bulk & Project Pricing","Wholesale Electropolished Pipe Supply for "&$E996&" Projects","Bulk & Wholesale Electropolished Pipe Rates for "&$E996&" Buyers","Electropolished Pipes Wholesaler in "&$E996&" - Project Quantities & Terms","Stockist & Wholesale Supply of Electropolished Pipes in "&$E996) -> Bulk & Wholesale Electropolished Pipe Rates for Diphu Buyers | AH996: ="electropolished pipes manufacturer in "&$D996&", electropolished pipes supplier in "&$D996&", electropolished pipes wholesaler in "&$D996&", electropolished tube manufacturer "&$D996&", EP pipe supplier "&$D996&", sanitary tube supplier "&$D996&", ASME BPE tubing "&$D996&", ASTM A270 tube "&$D996&", SS 316L electropolished pipe "&$D996 -> electropolished pipes manufacturer in Diphu, electropolished pipes supplier in Diphu, electropolished pipes wholesaler in Diphu, electropolished tube manufacturer Diphu, EP pipe supplier Diphu, sanitary tube supplier Diphu, ASME BPE tubing Diphu, ASTM A270 tube Diphu, SS 316L electropolished pipe Diphu | AI996: ="Electropolished Pipes Manufacturer & Supplier in "&$E996 -> Electropolished Pipes Manufacturer & Supplier in Diphu | AJ996: ="EP-finished SS 304/316L pipes and tubes for "&$K996&" plants in "&$E996&". ASME BPE SF1-SF4, Ra from 0.25 um, EN 10204 3.1 certificate with every lot." -> EP-finished SS 304/316L pipes and tubes for VERIFY plants in Diphu. ASME BPE SF1-SF4, Ra from 0.25 um, EN 10204 3.1 certificate with every lot. | AK996: ="Electropolished stainless steel pipes supplied by Sakshi Forge to "&$K996&" plants at "&$I996&", "&$E996 -> Electropolished stainless steel pipes supplied by Sakshi Forge to VERIFY plants at AIDC Industrial Area, Diphu | AL996: ="Electropolished SS 316L tube stock for "&$E996&" - Sakshi Forge" -> Electropolished SS 316L tube stock for Diphu - Sakshi Forge | AM996: ="Home > Market Area > "&$B996&" > "&$C996&" > "&$D996 -> Home > Market Area > India > Assam > Diphu | AN996: =IF($F996="A",1400,IF($F996="B",1000,750)) -> 750 | AO996: =IF($F996="A",10,IF($F996="B",8,6)) -> 6 | AP996: =IF($F996="A",12,IF($F996="B",8,6)) -> 6 | AQ996: =ROUNDUP((ROW()-3)/60,0) -> 17 | AT996: Not started
A997: CTY-0994 | B997: India | C997: Karnataka | D997: Doddaballapur | E997: Doddaballapur | F997: C | G997: VERIFY | H997: KIADB Industrial Area, Doddaballapur | I997: KIADB Industrial Area | J997: VERIFY | K997: VERIFY | L997: VERIFY | M997: VERIFY | N997: VERIFY | O997: VERIFY | P997: =IF($K997="VERIFY","VERIFY",IF(ISNUMBER(SEARCH("semicon",$K997)),"SEMI",IF(ISNUMBER(SEARCH("electronic",$K997)),"SEMI",IF(ISNUMBER(SEARCH("biotech",$K997)),"BIOTECH",IF(ISNUMBER(SEARCH("pharma",$K997)),"PHARMA",IF(ISNUMBER(SEARCH("medical",$K997)),"PHARMA",IF(ISNUMBER(SEARCH("dairy",$K997)),"DAIRY",IF(ISNUMBER(SEARCH("brewery",$K997)),"BREWERY",IF(ISNUMBER(SEARCH("food",$K997)),"FOOD",IF(ISNUMBER(SEARCH("personal care",$K997)),"FOOD",IF(ISNUMBER(SEARCH("chemical",$K997)),"CHEM",IF(ISNUMBER(SEARCH("refining",$K997)),"CHEM",IF(ISNUMBER(SEARCH("petrochem",$K997)),"CHEM",IF(ISNUMBER(SEARCH("fertilis",$K997)),"CHEM",IF(ISNUMBER(SEARCH("water",$K997)),"CHEM","GENERAL"))))))))))))))) -> VERIFY | Q997: =MOD(ROW()-4,8)+1 -> 2 | R997: =MOD(ROW()-4,7)+1 -> 7 | S997: =MOD(ROW()-4,5)+1 -> 4 | T997: =$F997&"-"&(MOD(ROW()-4,6)+1) -> C-4 | U997: ="T"&$Q997&"-M"&$R997&"-H"&$S997&"-F"&$T997&"-"&$P997 -> T2-M7-H4-FC-4-VERIFY | V997: =COUNTIF($U$4:$U$1835,$U997)-1 -> 0 | X997: =IF($W997<>"",$W997,IF($B997="India",LOWER(SUBSTITUTE(SUBSTITUTE($D997," ","-"),".","")),LOWER(SUBSTITUTE(SUBSTITUTE($D997," ","-"),".",""))&"-"&LOWER(SUBSTITUTE($B997," ","-")))) -> doddaballapur | Y997: ="https://steelmanufacturer.in/market-area/electropolished-pipes-manufacturer-in-"&$X997&"/" -> https://steelmanufacturer.in/market-area/electropolished-pipes-manufacturer-in-doddaballapur/ | Z997: =IF($AR997<>"",$AR997,IF(LEN("Electropolished Pipes Manufacturer in "&$E997&CHOOSE($Q997," | Sakshi Forge"," - ASTM A270 & ASME BPE"," | EP Tube Supplier"," - SS 304/316L EP Tube"," | Sanitary Tube Supply"," - Mill Certified Supply"," | ASME BPE SF1-SF4"," - EP Tube Stockist"))<=65,"Electropolished Pipes Manufacturer in "&$E997&CHOOSE($Q997," | Sakshi Forge"," - ASTM A270 & ASME BPE"," | EP Tube Supplier"," - SS 304/316L EP Tube"," | Sanitary Tube Supply"," - Mill Certified Supply"," | ASME BPE SF1-SF4"," - EP Tube Stockist"),"Electropolished Pipes Manufacturer in "&$E997)) -> Electropolished Pipes Manufacturer in Doddaballapur | AA997: =IF(LEN($Z997)>65,"TRIM ("&LEN($Z997)&")",IF(LEN($Z997)<35,"SHORT ("&LEN($Z997)&")","OK ("&LEN($Z997)&")")) -> OK (51) | AB997: =IF($AS997<>"",$AS997,CHOOSE($R997,"EP-finished SS 304/316L pipes & tubes for "&$K997&" plants in "&$E997&". ASTM A270, ASME BPE SF1-SF4, EN 10204 3.1 MTC. PMI tested.","Electropolished tube supply to "&$I997&", "&$E997&". Ra from 0.25 um, SF4 finish, mill test certificate with every lot.","EP stainless tube for "&$K997&" lines in "&$E997&". "&$M997&". ASTM A270 S2, PMI tested, EN 10204 3.1.","Sanitary electropolished pipes in "&$E997&" for "&$K997&" plants. ASME BPE SF1-SF4, orbital-weld ready, 3.1 MTC. Mumbai-made.","Manufacturer of electropolished SS 316L tube serving "&$E997&". "&$M997&". Ra 0.25-0.5 um, EN 10204 3.1 MTC.",IF(LEN("EP tube and pipe for "&$K997&" plants around "&$I997&", "&$E997&". Made at our Mumbai works to ASTM A270 and ASME BPE SF1-SF4, with 3.1 MTC.")<=160,"EP tube and pipe for "&$K997&" plants around "&$I997&", "&$E997&". Made at our Mumbai works to ASTM A270 and ASME BPE SF1-SF4, with 3.1 MTC.","EP tube and pipe for "&$K997&" plants around "&$I997&", "&$E997&". ASTM A270, ASME BPE SF1-SF4, EN 10204 3.1 MTC."),"Electropolished pipes in "&$E997&": 304, 304L, 316 and 316L in SF1-SF4. "&$M997&". Mill certified.")) -> Electropolished pipes in Doddaballapur: 304, 304L, 316 and 316L in SF1-SF4. VERIFY. Mill certified. | AC997: =IF($G997="VERIFY","PENDING RESEARCH",IF(LEN($AB997)>160,"TRIM ("&LEN($AB997)&")",IF(LEN($AB997)<110,"SHORT ("&LEN($AB997)&")","OK ("&LEN($AB997)&")"))) -> PENDING RESEARCH | AD997: ="Electropolished Pipes Manufacturer in "&$E997 -> Electropolished Pipes Manufacturer in Doddaballapur | AE997: =CHOOSE($S997,"Electropolished Pipe & Tube Manufacturing for "&$E997&" - Grades, Finishes & Certification","How We Manufacture Electropolished Tube for "&$E997&" Plants","Electropolished Pipes Manufacturer in "&$E997&" - Our Process & Capability","Manufacturing Electropolished SS Tube for "&$E997&": The Standards We Build To","Electropolished Tube Manufacturing Capability Serving "&$E997) -> Manufacturing Electropolished SS Tube for Doddaballapur: The Standards We Build To | AF997: =CHOOSE($S997,"Electropolished Pipes Supplier in "&$E997&" - Stock Sizes, Lead Time & Delivery","Supplying Electropolished Pipes in "&$E997&": Availability, Sizes & Dispatch","Electropolished Pipes Supplier in "&$E997&" - What We Hold in Stock","Electropolished Pipe Supply Into "&$E997&" - Certification & Transit","Electropolished Pipes Supplier in "&$E997&" - From Order to Delivery") -> Electropolished Pipe Supply Into Doddaballapur - Certification & Transit | AG997: =CHOOSE($S997,"Electropolished Pipes Wholesaler & Stockist in "&$E997&" - Bulk & Project Pricing","Wholesale Electropolished Pipe Supply for "&$E997&" Projects","Bulk & Wholesale Electropolished Pipe Rates for "&$E997&" Buyers","Electropolished Pipes Wholesaler in "&$E997&" - Project Quantities & Terms","Stockist & Wholesale Supply of Electropolished Pipes in "&$E997) -> Electropolished Pipes Wholesaler in Doddaballapur - Project Quantities & Terms | AH997: ="electropolished pipes manufacturer in "&$D997&", electropolished pipes supplier in "&$D997&", electropolished pipes wholesaler in "&$D997&", electropolished tube manufacturer "&$D997&", EP pipe supplier "&$D997&", sanitary tube supplier "&$D997&", ASME BPE tubing "&$D997&", ASTM A270 tube "&$D997&", SS 316L electropolished pipe "&$D997 -> electropolished pipes manufacturer in Doddaballapur, electropolished pipes supplier in Doddaballapur, electropolished pipes wholesaler in Doddaballapur, electropolished tube manufacturer Doddaballapur, EP pipe supplier Doddaballapur, sanitary tube supplier Doddaballapur, ASME BPE tubing Doddaballapur, ASTM A270 tube Doddaballapur, SS 316L electropolished pipe Doddaballapur | AI997: ="Electropolished Pipes Manufacturer & Supplier in "&$E997 -> Electropolished Pipes Manufacturer & Supplier in Doddaballapur | AJ997: ="EP-finished SS 304/316L pipes and tubes for "&$K997&" plants in "&$E997&". ASME BPE SF1-SF4, Ra from 0.25 um, EN 10204 3.1 certificate with every lot." -> EP-finished SS 304/316L pipes and tubes for VERIFY plants in Doddaballapur. ASME BPE SF1-SF4, Ra from 0.25 um, EN 10204 3.1 certificate with every lot. | AK997: ="Electropolished stainless steel pipes supplied by Sakshi Forge to "&$K997&" plants at "&$I997&", "&$E997 -> Electropolished stainless steel pipes supplied by Sakshi Forge to VERIFY plants at KIADB Industrial Area, Doddaballapur | AL997: ="Electropolished SS 316L tube stock for "&$E997&" - Sakshi Forge" -> Electropolished SS 316L tube stock for Doddaballapur - Sakshi Forge | AM997: ="Home > Market Area > "&$B997&" > "&$C997&" > "&$D997 -> Home > Market Area > India > Karnataka > Doddaballapur | AN997: =IF($F997="A",1400,IF($F997="B",1000,750)) -> 750 | AO997: =IF($F997="A",10,IF($F997="B",8,6)) -> 6 | AP997: =IF($F997="A",12,IF($F997="B",8,6)) -> 6 | AQ997: =ROUNDUP((ROW()-3)/60,0) -> 17 | AT997: Not started
A998: CTY-0995 | B998: India | C998: Uttarakhand | D998: Doiwala | E998: Doiwala | F998: C | G998: VERIFY | H998: SIIDCUL Industrial Area, Doiwala | I998: SIIDCUL Industrial Area | J998: VERIFY | K998: VERIFY | L998: VERIFY | M998: VERIFY | N998: VERIFY | O998: VERIFY | P998: =IF($K998="VERIFY","VERIFY",IF(ISNUMBER(SEARCH("semicon",$K998)),"SEMI",IF(ISNUMBER(SEARCH("electronic",$K998)),"SEMI",IF(ISNUMBER(SEARCH("biotech",$K998)),"BIOTECH",IF(ISNUMBER(SEARCH("pharma",$K998)),"PHARMA",IF(ISNUMBER(SEARCH("medical",$K998)),"PHARMA",IF(ISNUMBER(SEARCH("dairy",$K998)),"DAIRY",IF(ISNUMBER(SEARCH("brewery",$K998)),"BREWERY",IF(ISNUMBER(SEARCH("food",$K998)),"FOOD",IF(ISNUMBER(SEARCH("personal care",$K998)),"FOOD",IF(ISNUMBER(SEARCH("chemical",$K998)),"CHEM",IF(ISNUMBER(SEARCH("refining",$K998)),"CHEM",IF(ISNUMBER(SEARCH("petrochem",$K998)),"CHEM",IF(ISNUMBER(SEARCH("fertilis",$K998)),"CHEM",IF(ISNUMBER(SEARCH("water",$K998)),"CHEM","GENERAL"))))))))))))))) -> VERIFY | Q998: =MOD(ROW()-4,8)+1 -> 3 | R998: =MOD(ROW()-4,7)+1 -> 1 | S998: =MOD(ROW()-4,5)+1 -> 5 | T998: =$F998&"-"&(MOD(ROW()-4,6)+1) -> C-5 | U998: ="T"&$Q998&"-M"&$R998&"-H"&$S998&"-F"&$T998&"-"&$P998 -> T3-M1-H5-FC-5-VERIFY | V998: =COUNTIF($U$4:$U$1835,$U998)-1 -> 0 | X998: =IF($W998<>"",$W998,IF($B998="India",LOWER(SUBSTITUTE(SUBSTITUTE($D998," ","-"),".","")),LOWER(SUBSTITUTE(SUBSTITUTE($D998," ","-"),".",""))&"-"&LOWER(SUBSTITUTE($B998," ","-")))) -> doiwala | Y998: ="https://steelmanufacturer.in/market-area/electropolished-pipes-manufacturer-in-"&$X998&"/" -> https://steelmanufacturer.in/market-area/electropolished-pipes-manufacturer-in-doiwala/ | Z998: =IF($AR998<>"",$AR998,IF(LEN("Electropolished Pipes Manufacturer in "&$E998&CHOOSE($Q998," | Sakshi Forge"," - ASTM A270 & ASME BPE"," | EP Tube Supplier"," - SS 304/316L EP Tube"," | Sanitary Tube Supply"," - Mill Certified Supply"," | ASME BPE SF1-SF4"," - EP Tube Stockist"))<=65,"Electropolished Pipes Manufacturer in "&$E998&CHOOSE($Q998," | Sakshi Forge"," - ASTM A270 & ASME BPE"," | EP Tube Supplier"," - SS 304/316L EP Tube"," | Sanitary Tube Supply"," - Mill Certified Supply"," | ASME BPE SF1-SF4"," - EP Tube Stockist"),"Electropolished Pipes Manufacturer in "&$E998)) -> Electropolished Pipes Manufacturer in Doiwala | EP Tube Supplier | AA998: =IF(LEN($Z998)>65,"TRIM ("&LEN($Z998)&")",IF(LEN($Z998)<35,"SHORT ("&LEN($Z998)&")","OK ("&LEN($Z998)&")")) -> OK (64) | AB998: =IF($AS998<>"",$AS998,CHOOSE($R998,"EP-finished SS 304/316L pipes & tubes for "&$K998&" plants in "&$E998&". ASTM A270, ASME BPE SF1-SF4, EN 10204 3.1 MTC. PMI tested.","Electropolished tube supply to "&$I998&", "&$E998&". Ra from 0.25 um, SF4 finish, mill test certificate with every lot.","EP stainless tube for "&$K998&" lines in "&$E998&". "&$M998&". ASTM A270 S2, PMI tested, EN 10204 3.1.","Sanitary electropolished pipes in "&$E998&" for "&$K998&" plants. ASME BPE SF1-SF4, orbital-weld ready, 3.1 MTC. Mumbai-made.","Manufacturer of electropolished SS 316L tube serving "&$E998&". "&$M998&". Ra 0.25-0.5 um, EN 10204 3.1 MTC.",IF(LEN("EP tube and pipe for "&$K998&" plants around "&$I998&", "&$E998&". Made at our Mumbai works to ASTM A270 and ASME BPE SF1-SF4, with 3.1 MTC.")<=160,"EP tube and pipe for "&$K998&" plants around "&$I998&", "&$E998&". Made at our Mumbai works to ASTM A270 and ASME BPE SF1-SF4, with 3.1 MTC.","EP tube and pipe for "&$K998&" plants around "&$I998&", "&$E998&". ASTM A270, ASME BPE SF1-SF4, EN 10204 3.1 MTC."),"Electropolished pipes in "&$E998&": 304, 304L, 316 and 316L in SF1-SF4. "&$M998&". Mill certified.")) -> EP-finished SS 304/316L pipes & tubes for VERIFY plants in Doiwala. ASTM A270, ASME BPE SF1-SF4, EN 10204 3.1 MTC. PMI tested. | AC998: =IF($G998="VERIFY","PENDING RESEARCH",IF(LEN($AB998)>160,"TRIM ("&LEN($AB998)&")",IF(LEN($AB998)<110,"SHORT ("&LEN($AB998)&")","OK ("&LEN($AB998)&")"))) -> PENDING RESEARCH | AD998: ="Electropolished Pipes Manufacturer in "&$E998 -> Electropolished Pipes Manufacturer in Doiwala | AE998: =CHOOSE($S998,"Electropolished Pipe & Tube Manufacturing for "&$E998&" - Grades, Finishes & Certification","How We Manufacture Electropolished Tube for "&$E998&" Plants","Electropolished Pipes Manufacturer in "&$E998&" - Our Process & Capability","Manufacturing Electropolished SS Tube for "&$E998&": The Standards We Build To","Electropolished Tube Manufacturing Capability Serving "&$E998) -> Electropolished Tube Manufacturing Capability Serving Doiwala | AF998: =CHOOSE($S998,"Electropolished Pipes Supplier in "&$E998&" - Stock Sizes, Lead Time & Delivery","Supplying Electropolished Pipes in "&$E998&": Availability, Sizes & Dispatch","Electropolished Pipes Supplier in "&$E998&" - What We Hold in Stock","Electropolished Pipe Supply Into "&$E998&" - Certification & Transit","Electropolished Pipes Supplier in "&$E998&" - From Order to Delivery") -> Electropolished Pipes Supplier in Doiwala - From Order to Delivery | AG998: =CHOOSE($S998,"Electropolished Pipes Wholesaler & Stockist in "&$E998&" - Bulk & Project Pricing","Wholesale Electropolished Pipe Supply for "&$E998&" Projects","Bulk & Wholesale Electropolished Pipe Rates for "&$E998&" Buyers","Electropolished Pipes Wholesaler in "&$E998&" - Project Quantities & Terms","Stockist & Wholesale Supply of Electropolished Pipes in "&$E998) -> Stockist & Wholesale Supply of Electropolished Pipes in Doiwala | AH998: ="electropolished pipes manufacturer in "&$D998&", electropolished pipes supplier in "&$D998&", electropolished pipes wholesaler in "&$D998&", electropolished tube manufacturer "&$D998&", EP pipe supplier "&$D998&", sanitary tube supplier "&$D998&", ASME BPE tubing "&$D998&", ASTM A270 tube "&$D998&", SS 316L electropolished pipe "&$D998 -> electropolished pipes manufacturer in Doiwala, electropolished pipes supplier in Doiwala, electropolished pipes wholesaler in Doiwala, electropolished tube manufacturer Doiwala, EP pipe supplier Doiwala, sanitary tube supplier Doiwala, ASME BPE tubing Doiwala, ASTM A270 tube Doiwala, SS 316L electropolished pipe Doiwala | AI998: ="Electropolished Pipes Manufacturer & Supplier in "&$E998 -> Electropolished Pipes Manufacturer & Supplier in Doiwala | AJ998: ="EP-finished SS 304/316L pipes and tubes for "&$K998&" plants in "&$E998&". ASME BPE SF1-SF4, Ra from 0.25 um, EN 10204 3.1 certificate with every lot." -> EP-finished SS 304/316L pipes and tubes for VERIFY plants in Doiwala. ASME BPE SF1-SF4, Ra from 0.25 um, EN 10204 3.1 certificate with every lot. | AK998: ="Electropolished stainless steel pipes supplied by Sakshi Forge to "&$K998&" plants at "&$I998&", "&$E998 -> Electropolished stainless steel pipes supplied by Sakshi Forge to VERIFY plants at SIIDCUL Industrial Area, Doiwala | AL998: ="Electropolished SS 316L tube stock for "&$E998&" - Sakshi Forge" -> Electropolished SS 316L tube stock for Doiwala - Sakshi Forge | AM998: ="Home > Market Area > "&$B998&" > "&$C998&" > "&$D998 -> Home > Market Area > India > Uttarakhand > Doiwala | AN998: =IF($F998="A",1400,IF($F998="B",1000,750)) -> 750 | AO998: =IF($F998="A",10,IF($F998="B",8,6)) -> 6 | AP998: =IF($F998="A",12,IF($F998="B",8,6)) -> 6 | AQ998: =ROUNDUP((ROW()-3)/60,0) -> 17 | AT998: Not started
A999: CTY-0996 | B999: India | C999: Gujarat | D999: Dolvan | E999: Dolvan | F999: C | G999: VERIFY | H999: GIDC Industrial Area, Dolvan | I999: GIDC Industrial Area | J999: VERIFY | K999: VERIFY | L999: VERIFY | M999: VERIFY | N999: VERIFY | O999: VERIFY | P999: =IF($K999="VERIFY","VERIFY",IF(ISNUMBER(SEARCH("semicon",$K999)),"SEMI",IF(ISNUMBER(SEARCH("electronic",$K999)),"SEMI",IF(ISNUMBER(SEARCH("biotech",$K999)),"BIOTECH",IF(ISNUMBER(SEARCH("pharma",$K999)),"PHARMA",IF(ISNUMBER(SEARCH("medical",$K999)),"PHARMA",IF(ISNUMBER(SEARCH("dairy",$K999)),"DAIRY",IF(ISNUMBER(SEARCH("brewery",$K999)),"BREWERY",IF(ISNUMBER(SEARCH("food",$K999)),"FOOD",IF(ISNUMBER(SEARCH("personal care",$K999)),"FOOD",IF(ISNUMBER(SEARCH("chemical",$K999)),"CHEM",IF(ISNUMBER(SEARCH("refining",$K999)),"CHEM",IF(ISNUMBER(SEARCH("petrochem",$K999)),"CHEM",IF(ISNUMBER(SEARCH("fertilis",$K999)),"CHEM",IF(ISNUMBER(SEARCH("water",$K999)),"CHEM","GENERAL"))))))))))))))) -> VERIFY | Q999: =MOD(ROW()-4,8)+1 -> 4 | R999: =MOD(ROW()-4,7)+1 -> 2 | S999: =MOD(ROW()-4,5)+1 -> 1 | T999: =$F999&"-"&(MOD(ROW()-4,6)+1) -> C-6 | U999: ="T"&$Q999&"-M"&$R999&"-H"&$S999&"-F"&$T999&"-"&$P999 -> T4-M2-H1-FC-6-VERIFY | V999: =COUNTIF($U$4:$U$1835,$U999)-1 -> 0 | X999: =IF($W999<>"",$W999,IF($B999="India",LOWER(SUBSTITUTE(SUBSTITUTE($D999," ","-"),".","")),LOWER(SUBSTITUTE(SUBSTITUTE($D999," ","-"),".",""))&"-"&LOWER(SUBSTITUTE($B999," ","-")))) -> dolvan | Y999: ="https://steelmanufacturer.in/market-area/electropolished-pipes-manufacturer-in-"&$X999&"/" -> https://steelmanufacturer.in/market-area/electropolished-pipes-manufacturer-in-dolvan/ | Z999: =IF($AR999<>"",$AR999,IF(LEN("Electropolished Pipes Manufacturer in "&$E999&CHOOSE($Q999," | Sakshi Forge"," - ASTM A270 & ASME BPE"," | EP Tube Supplier"," - SS 304/316L EP Tube"," | Sanitary Tube Supply"," - Mill Certified Supply"," | ASME BPE SF1-SF4"," - EP Tube Stockist"))<=65,"Electropolished Pipes Manufacturer in "&$E999&CHOOSE($Q999," | Sakshi Forge"," - ASTM A270 & ASME BPE"," | EP Tube Supplier"," - SS 304/316L EP Tube"," | Sanitary Tube Supply"," - Mill Certified Supply"," | ASME BPE SF1-SF4"," - EP Tube Stockist"),"Electropolished Pipes Manufacturer in "&$E999)) -> Electropolished Pipes Manufacturer in Dolvan | AA999: =IF(LEN($Z999)>65,"TRIM ("&LEN($Z999)&")",IF(LEN($Z999)<35,"SHORT ("&LEN($Z999)&")","OK ("&LEN($Z999)&")")) -> OK (44) | AB999: =IF($AS999<>"",$AS999,CHOOSE($R999,"EP-finished SS 304/316L pipes & tubes for "&$K999&" plants in "&$E999&". ASTM A270, ASME BPE SF1-SF4, EN 10204 3.1 MTC. PMI tested.","Electropolished tube supply to "&$I999&", "&$E999&". Ra from 0.25 um, SF4 finish, mill test certificate with every lot.","EP stainless tube for "&$K999&" lines in "&$E999&". "&$M999&". ASTM A270 S2, PMI tested, EN 10204 3.1.","Sanitary electropolished pipes in "&$E999&" for "&$K999&" plants. ASME BPE SF1-SF4, orbital-weld ready, 3.1 MTC. Mumbai-made.","Manufacturer of electropolished SS 316L tube serving "&$E999&". "&$M999&". Ra 0.25-0.5 um, EN 10204 3.1 MTC.",IF(LEN("EP tube and pipe for "&$K999&" plants around "&$I999&", "&$E999&". Made at our Mumbai works to ASTM A270 and ASME BPE SF1-SF4, with 3.1 MTC.")<=160,"EP tube and pipe for "&$K999&" plants around "&$I999&", "&$E999&". Made at our Mumbai works to ASTM A270 and ASME BPE SF1-SF4, with 3.1 MTC.","EP tube and pipe for "&$K999&" plants around "&$I999&", "&$E999&". ASTM A270, ASME BPE SF1-SF4, EN 10204 3.1 MTC."),"Electropolished pipes in "&$E999&": 304, 304L, 316 and 316L in SF1-SF4. "&$M999&". Mill certified.")) -> Electropolished tube supply to GIDC Industrial Area, Dolvan. Ra from 0.25 um, SF4 finish, mill test certificate with every lot. | AC999: =IF($G999="VERIFY","PENDING RESEARCH",IF(LEN($AB999)>160,"TRIM ("&LEN($AB999)&")",IF(LEN($AB999)<110,"SHORT ("&LEN($AB999)&")","OK ("&LEN($AB999)&")"))) -> PENDING RESEARCH | AD999: ="Electropolished Pipes Manufacturer in "&$E999 -> Electropolished Pipes Manufacturer in Dolvan | AE999: =CHOOSE($S999,"Electropolished Pipe & Tube Manufacturing for "&$E999&" - Grades, Finishes & Certification","How We Manufacture Electropolished Tube for "&$E999&" Plants","Electropolished Pipes Manufacturer in "&$E999&" - Our Process & Capability","Manufacturing Electropolished SS Tube for "&$E999&": The Standards We Build To","Electropolished Tube Manufacturing Capability Serving "&$E999) -> Electropolished Pipe & Tube Manufacturing for Dolvan - Grades, Finishes & Certification | AF999: =CHOOSE($S999,"Electropolished Pipes Supplier in "&$E999&" - Stock Sizes, Lead Time & Delivery","Supplying Electropolished Pipes in "&$E999&": Availability, Sizes & Dispatch","Electropolished Pipes Supplier in "&$E999&" - What We Hold in Stock","Electropolished Pipe Supply Into "&$E999&" - Certification & Transit","Electropolished Pipes Supplier in "&$E999&" - From Order to Delivery") -> Electropolished Pipes Supplier in Dolvan - Stock Sizes, Lead Time & Delivery | AG999: =CHOOSE($S999,"Electropolished Pipes Wholesaler & Stockist in "&$E999&" - Bulk & Project Pricing","Wholesale Electropolished Pipe Supply for "&$E999&" Projects","Bulk & Wholesale Electropolished Pipe Rates for "&$E999&" Buyers","Electropolished Pipes Wholesaler in "&$E999&" - Project Quantities & Terms","Stockist & Wholesale Supply of Electropolished Pipes in "&$E999) -> Electropolished Pipes Wholesaler & Stockist in Dolvan - Bulk & Project Pricing | AH999: ="electropolished pipes manufacturer in "&$D999&", electropolished pipes supplier in "&$D999&", electropolished pipes wholesaler in "&$D999&", electropolished tube manufacturer "&$D999&", EP pipe supplier "&$D999&", sanitary tube supplier "&$D999&", ASME BPE tubing "&$D999&", ASTM A270 tube "&$D999&", SS 316L electropolished pipe "&$D999 -> electropolished pipes manufacturer in Dolvan, electropolished pipes supplier in Dolvan, electropolished pipes wholesaler in Dolvan, electropolished tube manufacturer Dolvan, EP pipe supplier Dolvan, sanitary tube supplier Dolvan, ASME BPE tubing Dolvan, ASTM A270 tube Dolvan, SS 316L electropolished pipe Dolvan | AI999: ="Electropolished Pipes Manufacturer & Supplier in "&$E999 -> Electropolished Pipes Manufacturer & Supplier in Dolvan | AJ999: ="EP-finished SS 304/316L pipes and tubes for "&$K999&" plants in "&$E999&". ASME BPE SF1-SF4, Ra from 0.25 um, EN 10204 3.1 certificate with every lot." -> EP-finished SS 304/316L pipes and tubes for VERIFY plants in Dolvan. ASME BPE SF1-SF4, Ra from 0.25 um, EN 10204 3.1 certificate with every lot. | AK999: ="Electropolished stainless steel pipes supplied by Sakshi Forge to "&$K999&" plants at "&$I999&", "&$E999 -> Electropolished stainless steel pipes supplied by Sakshi Forge to VERIFY plants at GIDC Industrial Area, Dolvan | AL999: ="Electropolished SS 316L tube stock for "&$E999&" - Sakshi Forge" -> Electropolished SS 316L tube stock for Dolvan - Sakshi Forge | AM999: ="Home > Market Area > "&$B999&" > "&$C999&" > "&$D999 -> Home > Market Area > India > Gujarat > Dolvan | AN999: =IF($F999="A",1400,IF($F999="B",1000,750)) -> 750 | AO999: =IF($F999="A",10,IF($F999="B",8,6)) -> 6 | AP999: =IF($F999="A",12,IF($F999="B",8,6)) -> 6 | AQ999: =ROUNDUP((ROW()-3)/60,0) -> 17 | AT999: Not started
A1000: CTY-0997 | B1000: India | C1000: Punjab | D1000: Doraha | E1000: Doraha | F1000: C | G1000: VERIFY | H1000: PSIEC Industrial Area, Doraha | I1000: PSIEC Industrial Area | J1000: VERIFY | K1000: VERIFY | L1000: VERIFY | M1000: VERIFY | N1000: VERIFY | O1000: VERIFY | P1000: =IF($K1000="VERIFY","VERIFY",IF(ISNUMBER(SEARCH("semicon",$K1000)),"SEMI",IF(ISNUMBER(SEARCH("electronic",$K1000)),"SEMI",IF(ISNUMBER(SEARCH("biotech",$K1000)),"BIOTECH",IF(ISNUMBER(SEARCH("pharma",$K1000)),"PHARMA",IF(ISNUMBER(SEARCH("medical",$K1000)),"PHARMA",IF(ISNUMBER(SEARCH("dairy",$K1000)),"DAIRY",IF(ISNUMBER(SEARCH("brewery",$K1000)),"BREWERY",IF(ISNUMBER(SEARCH("food",$K1000)),"FOOD",IF(ISNUMBER(SEARCH("personal care",$K1000)),"FOOD",IF(ISNUMBER(SEARCH("chemical",$K1000)),"CHEM",IF(ISNUMBER(SEARCH("refining",$K1000)),"CHEM",IF(ISNUMBER(SEARCH("petrochem",$K1000)),"CHEM",IF(ISNUMBER(SEARCH("fertilis",$K1000)),"CHEM",IF(ISNUMBER(SEARCH("water",$K1000)),"CHEM","GENERAL"))))))))))))))) -> VERIFY | Q1000: =MOD(ROW()-4,8)+1 -> 5 | R1000: =MOD(ROW()-4,7)+1 -> 3 | S1000: =MOD(ROW()-4,5)+1 -> 2 | T1000: =$F1000&"-"&(MOD(ROW()-4,6)+1) -> C-1 | U1000: ="T"&$Q1000&"-M"&$R1000&"-H"&$S1000&"-F"&$T1000&"-"&$P1000 -> T5-M3-H2-FC-1-VERIFY | V1000: =COUNTIF($U$4:$U$1835,$U1000)-1 -> 0 | X1000: =IF($W1000<>"",$W1000,IF($B1000="India",LOWER(SUBSTITUTE(SUBSTITUTE($D1000," ","-"),".","")),LOWER(SUBSTITUTE(SUBSTITUTE($D1000," ","-"),".",""))&"-"&LOWER(SUBSTITUTE($B1000," ","-")))) -> doraha | Y1000: ="https://steelmanufacturer.in/market-area/electropolished-pipes-manufacturer-in-"&$X1000&"/" -> https://steelmanufacturer.in/market-area/electropolished-pipes-manufacturer-in-doraha/ | Z1000: =IF($AR1000<>"",$AR1000,IF(LEN("Electropolished Pipes Manufacturer in "&$E1000&CHOOSE($Q1000," | Sakshi Forge"," - ASTM A270 & ASME BPE"," | EP Tube Supplier"," - SS 304/316L EP Tube"," | Sanitary Tube Supply"," - Mill Certified Supply"," | ASME BPE SF1-SF4"," - EP Tube Stockist"))<=65,"Electropolished Pipes Manufacturer in "&$E1000&CHOOSE($Q1000," | Sakshi Forge"," - ASTM A270 & ASME BPE"," | EP Tube Supplier"," - SS 304/316L EP Tube"," | Sanitary Tube Supply"," - Mill Certified Supply"," | ASME BPE SF1-SF4"," - EP Tube Stockist"),"Electropolished Pipes Manufacturer in "&$E1000)) -> Electropolished Pipes Manufacturer in Doraha | AA1000: =IF(LEN($Z1000)>65,"TRIM ("&LEN($Z1000)&")",IF(LEN($Z1000)<35,"SHORT ("&LEN($Z1000)&")","OK ("&LEN($Z1000)&")")) -> OK (44) | AB1000: =IF($AS1000<>"",$AS1000,CHOOSE($R1000,"EP-finished SS 304/316L pipes & tubes for "&$K1000&" plants in "&$E1000&". ASTM A270, ASME BPE SF1-SF4, EN 10204 3.1 MTC. PMI tested.","Electropolished tube supply to "&$I1000&", "&$E1000&". Ra from 0.25 um, SF4 finish, mill test certificate with every lot.","EP stainless tube for "&$K1000&" lines in "&$E1000&". "&$M1000&". ASTM A270 S2, PMI tested, EN 10204 3.1.","Sanitary electropolished pipes in "&$E1000&" for "&$K1000&" plants. ASME BPE SF1-SF4, orbital-weld ready, 3.1 MTC. Mumbai-made.","Manufacturer of electropolished SS 316L tube serving "&$E1000&". "&$M1000&". Ra 0.25-0.5 um, EN 10204 3.1 MTC.",IF(LEN("EP tube and pipe for "&$K1000&" plants around "&$I1000&", "&$E1000&". Made at our Mumbai works to ASTM A270 and ASME BPE SF1-SF4, with 3.1 MTC.")<=160,"EP tube and pipe for "&$K1000&" plants around "&$I1000&", "&$E1000&". Made at our Mumbai works to ASTM A270 and ASME BPE SF1-SF4, with 3.1 MTC.","EP tube and pipe for "&$K1000&" plants around "&$I1000&", "&$E1000&". ASTM A270, ASME BPE SF1-SF4, EN 10204 3.1 MTC."),"Electropolished pipes in "&$E1000&": 304, 304L, 316 and 316L in SF1-SF4. "&$M1000&". Mill certified.")) -> EP stainless tube for VERIFY lines in Doraha. VERIFY. ASTM A270 S2, PMI tested, EN 10204 3.1. | AC1000: =IF($G1000="VERIFY","PENDING RESEARCH",IF(LEN($AB1000)>160,"TRIM ("&LEN($AB1000)&")",IF(LEN($AB1000)<110,"SHORT ("&LEN($AB1000)&")","OK ("&LEN($AB1000)&")"))) -> PENDING RESEARCH | AD1000: ="Electropolished Pipes Manufacturer in "&$E1000 -> Electropolished Pipes Manufacturer in Doraha | AE1000: =CHOOSE($S1000,"Electropolished Pipe & Tube Manufacturing for "&$E1000&" - Grades, Finishes & Certification","How We Manufacture Electropolished Tube for "&$E1000&" Plants","Electropolished Pipes Manufacturer in "&$E1000&" - Our Process & Capability","Manufacturing Electropolished SS Tube for "&$E1000&": The Standards We Build To","Electropolished Tube Manufacturing Capability Serving "&$E1000) -> How We Manufacture Electropolished Tube for Doraha Plants | AF1000: =CHOOSE($S1000,"Electropolished Pipes Supplier in "&$E1000&" - Stock Sizes, Lead Time & Delivery","Supplying Electropolished Pipes in "&$E1000&": Availability, Sizes & Dispatch","Electropolished Pipes Supplier in "&$E1000&" - What We Hold in Stock","Electropolished Pipe Supply Into "&$E1000&" - Certification & Transit","Electropolished Pipes Supplier in "&$E1000&" - From Order to Delivery") -> Supplying Electropolished Pipes in Doraha: Availability, Sizes & Dispatch | AG1000: =CHOOSE($S1000,"Electropolished Pipes Wholesaler & Stockist in "&$E1000&" - Bulk & Project Pricing","Wholesale Electropolished Pipe Supply for "&$E1000&" Projects","Bulk & Wholesale Electropolished Pipe Rates for "&$E1000&" Buyers","Electropolished Pipes Wholesaler in "&$E1000&" - Project Quantities & Terms","Stockist & Wholesale Supply of Electropolished Pipes in "&$E1000) -> Wholesale Electropolished Pipe Supply for Doraha Projects | AH1000: ="electropolished pipes manufacturer in "&$D1000&", electropolished pipes supplier in "&$D1000&", electropolished pipes wholesaler in "&$D1000&", electropolished tube manufacturer "&$D1000&", EP pipe supplier "&$D1000&", sanitary tube supplier "&$D1000&", ASME BPE tubing "&$D1000&", ASTM A270 tube "&$D1000&", SS 316L electropolished pipe "&$D1000 -> electropolished pipes manufacturer in Doraha, electropolished pipes supplier in Doraha, electropolished pipes wholesaler in Doraha, electropolished tube manufacturer Doraha, EP pipe supplier Doraha, sanitary tube supplier Doraha, ASME BPE tubing Doraha, ASTM A270 tube Doraha, SS 316L electropolished pipe Doraha | AI1000: ="Electropolished Pipes Manufacturer & Supplier in "&$E1000 -> Electropolished Pipes Manufacturer & Supplier in Doraha | AJ1000: ="EP-finished SS 304/316L pipes and tubes for "&$K1000&" plants in "&$E1000&". ASME BPE SF1-SF4, Ra from 0.25 um, EN 10204 3.1 certificate with every lot." -> EP-finished SS 304/316L pipes and tubes for VERIFY plants in Doraha. ASME BPE SF1-SF4, Ra from 0.25 um, EN 10204 3.1 certificate with every lot. | AK1000: ="Electropolished stainless steel pipes supplied by Sakshi Forge to "&$K1000&" plants at "&$I1000&", "&$E1000 -> Electropolished stainless steel pipes supplied by Sakshi Forge to VERIFY plants at PSIEC Industrial Area, Doraha | AL1000: ="Electropolished SS 316L tube stock for "&$E1000&" - Sakshi Forge" -> Electropolished SS 316L tube stock for Doraha - Sakshi Forge | AM1000: ="Home > Market Area > "&$B1000&" > "&$C1000&" > "&$D1000 -> Home > Market Area > India > Punjab > Doraha | AN1000: =IF($F1000="A",1400,IF($F1000="B",1000,750)) -> 750 | AO1000: =IF($F1000="A",10,IF($F1000="B",8,6)) -> 6 | AP1000: =IF($F1000="A",12,IF($F1000="B",8,6)) -> 6 | AQ1000: =ROUNDUP((ROW()-3)/60,0) -> 17 | AT1000: Not started
A1001: CTY-0998 | B1001: India | C1001: Telangana | D1001: Dubbak | E1001: Dubbak | F1001: C | G1001: VERIFY | H1001: TSIIC Industrial Area, Dubbak | I1001: TSIIC Industrial Area | J1001: VERIFY | K1001: VERIFY | L1001: VERIFY | M1001: VERIFY | N1001: VERIFY | O1001: VERIFY | P1001: =IF($K1001="VERIFY","VERIFY",IF(ISNUMBER(SEARCH("semicon",$K1001)),"SEMI",IF(ISNUMBER(SEARCH("electronic",$K1001)),"SEMI",IF(ISNUMBER(SEARCH("biotech",$K1001)),"BIOTECH",IF(ISNUMBER(SEARCH("pharma",$K1001)),"PHARMA",IF(ISNUMBER(SEARCH("medical",$K1001)),"PHARMA",IF(ISNUMBER(SEARCH("dairy",$K1001)),"DAIRY",IF(ISNUMBER(SEARCH("brewery",$K1001)),"BREWERY",IF(ISNUMBER(SEARCH("food",$K1001)),"FOOD",IF(ISNUMBER(SEARCH("personal care",$K1001)),"FOOD",IF(ISNUMBER(SEARCH("chemical",$K1001)),"CHEM",IF(ISNUMBER(SEARCH("refining",$K1001)),"CHEM",IF(ISNUMBER(SEARCH("petrochem",$K1001)),"CHEM",IF(ISNUMBER(SEARCH("fertilis",$K1001)),"CHEM",IF(ISNUMBER(SEARCH("water",$K1001)),"CHEM","GENERAL"))))))))))))))) -> VERIFY | Q1001: =MOD(ROW()-4,8)+1 -> 6 | R1001: =MOD(ROW()-4,7)+1 -> 4 | S1001: =MOD(ROW()-4,5)+1 -> 3 | T1001: =$F1001&"-"&(MOD(ROW()-4,6)+1) -> C-2 | U1001: ="T"&$Q1001&"-M"&$R1001&"-H"&$S1001&"-F"&$T1001&"-"&$P1001 -> T6-M4-H3-FC-2-VERIFY | V1001: =COUNTIF($U$4:$U$1835,$U1001)-1 -> 0 | X1001: =IF($W1001<>"",$W1001,IF($B1001="India",LOWER(SUBSTITUTE(SUBSTITUTE($D1001," ","-"),".","")),LOWER(SUBSTITUTE(SUBSTITUTE($D1001," ","-"),".",""))&"-"&LOWER(SUBSTITUTE($B1001," ","-")))) -> dubbak | Y1001: ="https://steelmanufacturer.in/market-area/electropolished-pipes-manufacturer-in-"&$X1001&"/" -> https://steelmanufacturer.in/market-area/electropolished-pipes-manufacturer-in-dubbak/ | Z1001: =IF($AR1001<>"",$AR1001,IF(LEN("Electropolished Pipes Manufacturer in "&$E1001&CHOOSE($Q1001," | Sakshi Forge"," - ASTM A270 & ASME BPE"," | EP Tube Supplier"," - SS 304/316L EP Tube"," | Sanitary Tube Supply"," - Mill Certified Supply"," | ASME BPE SF1-SF4"," - EP Tube Stockist"))<=65,"Electropolished Pipes Manufacturer in "&$E1001&CHOOSE($Q1001," | Sakshi Forge"," - ASTM A270 & ASME BPE"," | EP Tube Supplier"," - SS 304/316L EP Tube"," | Sanitary Tube Supply"," - Mill Certified Supply"," | ASME BPE SF1-SF4"," - EP Tube Stockist"),"Electropolished Pipes Manufacturer in "&$E1001)) -> Electropolished Pipes Manufacturer in Dubbak | AA1001: =IF(LEN($Z1001)>65,"TRIM ("&LEN($Z1001)&")",IF(LEN($Z1001)<35,"SHORT ("&LEN($Z1001)&")","OK ("&LEN($Z1001)&")")) -> OK (44) | AB1001: =IF($AS1001<>"",$AS1001,CHOOSE($R1001,"EP-finished SS 304/316L pipes & tubes for "&$K1001&" plants in "&$E1001&". ASTM A270, ASME BPE SF1-SF4, EN 10204 3.1 MTC. PMI tested.","Electropolished tube supply to "&$I1001&", "&$E1001&". Ra from 0.25 um, SF4 finish, mill test certificate with every lot.","EP stainless tube for "&$K1001&" lines in "&$E1001&". "&$M1001&". ASTM A270 S2, PMI tested, EN 10204 3.1.","Sanitary electropolished pipes in "&$E1001&" for "&$K1001&" plants. ASME BPE SF1-SF4, orbital-weld ready, 3.1 MTC. Mumbai-made.","Manufacturer of electropolished SS 316L tube serving "&$E1001&". "&$M1001&". Ra 0.25-0.5 um, EN 10204 3.1 MTC.",IF(LEN("EP tube and pipe for "&$K1001&" plants around "&$I1001&", "&$E1001&". Made at our Mumbai works to ASTM A270 and ASME BPE SF1-SF4, with 3.1 MTC.")<=160,"EP tube and pipe for "&$K1001&" plants around "&$I1001&", "&$E1001&". Made at our Mumbai works to ASTM A270 and ASME BPE SF1-SF4, with 3.1 MTC.","EP tube and pipe for "&$K1001&" plants around "&$I1001&", "&$E1001&". ASTM A270, ASME BPE SF1-SF4, EN 10204 3.1 MTC."),"Electropolished pipes in "&$E1001&": 304, 304L, 316 and 316L in SF1-SF4. "&$M1001&". Mill certified.")) -> Sanitary electropolished pipes in Dubbak for VERIFY plants. ASME BPE SF1-SF4, orbital-weld ready, 3.1 MTC. Mumbai-made. | AC1001: =IF($G1001="VERIFY","PENDING RESEARCH",IF(LEN($AB1001)>160,"TRIM ("&LEN($AB1001)&")",IF(LEN($AB1001)<110,"SHORT ("&LEN($AB1001)&")","OK ("&LEN($AB1001)&")"))) -> PENDING RESEARCH | AD1001: ="Electropolished Pipes Manufacturer in "&$E1001 -> Electropolished Pipes Manufacturer in Dubbak | AE1001: =CHOOSE($S1001,"Electropolished Pipe & Tube Manufacturing for "&$E1001&" - Grades, Finishes & Certification","How We Manufacture Electropolished Tube for "&$E1001&" Plants","Electropolished Pipes Manufacturer in "&$E1001&" - Our Process & Capability","Manufacturing Electropolished SS Tube for "&$E1001&": The Standards We Build To","Electropolished Tube Manufacturing Capability Serving "&$E1001) -> Electropolished Pipes Manufacturer in Dubbak - Our Process & Capability | AF1001: =CHOOSE($S1001,"Electropolished Pipes Supplier in "&$E1001&" - Stock Sizes, Lead Time & Delivery","Supplying Electropolished Pipes in "&$E1001&": Availability, Sizes & Dispatch","Electropolished Pipes Supplier in "&$E1001&" - What We Hold in Stock","Electropolished Pipe Supply Into "&$E1001&" - Certification & Transit","Electropolished Pipes Supplier in "&$E1001&" - From Order to Delivery") -> Electropolished Pipes Supplier in Dubbak - What We Hold in Stock | AG1001: =CHOOSE($S1001,"Electropolished Pipes Wholesaler & Stockist in "&$E1001&" - Bulk & Project Pricing","Wholesale Electropolished Pipe Supply for "&$E1001&" Projects","Bulk & Wholesale Electropolished Pipe Rates for "&$E1001&" Buyers","Electropolished Pipes Wholesaler in "&$E1001&" - Project Quantities & Terms","Stockist & Wholesale Supply of Electropolished Pipes in "&$E1001) -> Bulk & Wholesale Electropolished Pipe Rates for Dubbak Buyers | AH1001: ="electropolished pipes manufacturer in "&$D1001&", electropolished pipes supplier in "&$D1001&", electropolished pipes wholesaler in "&$D1001&", electropolished tube manufacturer "&$D1001&", EP pipe supplier "&$D1001&", sanitary tube supplier "&$D1001&", ASME BPE tubing "&$D1001&", ASTM A270 tube "&$D1001&", SS 316L electropolished pipe "&$D1001 -> electropolished pipes manufacturer in Dubbak, electropolished pipes supplier in Dubbak, electropolished pipes wholesaler in Dubbak, electropolished tube manufacturer Dubbak, EP pipe supplier Dubbak, sanitary tube supplier Dubbak, ASME BPE tubing Dubbak, ASTM A270 tube Dubbak, SS 316L electropolished pipe Dubbak | AI1001: ="Electropolished Pipes Manufacturer & Supplier in "&$E1001 -> Electropolished Pipes Manufacturer & Supplier in Dubbak | AJ1001: ="EP-finished SS 304/316L pipes and tubes for "&$K1001&" plants in "&$E1001&". ASME BPE SF1-SF4, Ra from 0.25 um, EN 10204 3.1 certificate with every lot." -> EP-finished SS 304/316L pipes and tubes for VERIFY plants in Dubbak. ASME BPE SF1-SF4, Ra from 0.25 um, EN 10204 3.1 certificate with every lot. | AK1001: ="Electropolished stainless steel pipes supplied by Sakshi Forge to "&$K1001&" plants at "&$I1001&", "&$E1001 -> Electropolished stainless steel pipes supplied by Sakshi Forge to VERIFY plants at TSIIC Industrial Area, Dubbak | AL1001: ="Electropolished SS 316L tube stock for "&$E1001&" - Sakshi Forge" -> Electropolished SS 316L tube stock for Dubbak - Sakshi Forge | AM1001: ="Home > Market Area > "&$B1001&" > "&$C1001&" > "&$D1001 -> Home > Market Area > India > Telangana > Dubbak | AN1001: =IF($F1001="A",1400,IF($F1001="B",1000,750)) -> 750 | AO1001: =IF($F1001="A",10,IF($F1001="B",8,6)) -> 6 | AP1001: =IF($F1001="A",12,IF($F1001="B",8,6)) -> 6 | AQ1001: =ROUNDUP((ROW()-3)/60,0) -> 17 | AT1001: Not started
A1002: CTY-0999 | B1002: India | C1002: West Bengal | D1002: Dubrajpur | E1002: Dubrajpur | F1002: C | G1002: VERIFY | H1002: WBIDC Industrial Area, Dubrajpur | I1002: WBIDC Industrial Area | J1002: VERIFY | K1002: VERIFY | L1002: VERIFY | M1002: VERIFY | N1002: VERIFY | O1002: VERIFY | P1002: =IF($K1002="VERIFY","VERIFY",IF(ISNUMBER(SEARCH("semicon",$K1002)),"SEMI",IF(ISNUMBER(SEARCH("electronic",$K1002)),"SEMI",IF(ISNUMBER(SEARCH("biotech",$K1002)),"BIOTECH",IF(ISNUMBER(SEARCH("pharma",$K1002)),"PHARMA",IF(ISNUMBER(SEARCH("medical",$K1002)),"PHARMA",IF(ISNUMBER(SEARCH("dairy",$K1002)),"DAIRY",IF(ISNUMBER(SEARCH("brewery",$K1002)),"BREWERY",IF(ISNUMBER(SEARCH("food",$K1002)),"FOOD",IF(ISNUMBER(SEARCH("personal care",$K1002)),"FOOD",IF(ISNUMBER(SEARCH("chemical",$K1002)),"CHEM",IF(ISNUMBER(SEARCH("refining",$K1002)),"CHEM",IF(ISNUMBER(SEARCH("petrochem",$K1002)),"CHEM",IF(ISNUMBER(SEARCH("fertilis",$K1002)),"CHEM",IF(ISNUMBER(SEARCH("water",$K1002)),"CHEM","GENERAL"))))))))))))))) -> VERIFY | Q1002: =MOD(ROW()-4,8)+1 -> 7 | R1002: =MOD(ROW()-4,7)+1 -> 5 | S1002: =MOD(ROW()-4,5)+1 -> 4 | T1002: =$F1002&"-"&(MOD(ROW()-4,6)+1) -> C-3 | U1002: ="T"&$Q1002&"-M"&$R1002&"-H"&$S1002&"-F"&$T1002&"-"&$P1002 -> T7-M5-H4-FC-3-VERIFY | V1002: =COUNTIF($U$4:$U$1835,$U1002)-1 -> 0 | X1002: =IF($W1002<>"",$W1002,IF($B1002="India",LOWER(SUBSTITUTE(SUBSTITUTE($D1002," ","-"),".","")),LOWER(SUBSTITUTE(SUBSTITUTE($D1002," ","-"),".",""))&"-"&LOWER(SUBSTITUTE($B1002," ","-")))) -> dubrajpur | Y1002: ="https://steelmanufacturer.in/market-area/electropolished-pipes-manufacturer-in-"&$X1002&"/" -> https://steelmanufacturer.in/market-area/electropolished-pipes-manufacturer-in-dubrajpur/ | Z1002: =IF($AR1002<>"",$AR1002,IF(LEN("Electropolished Pipes Manufacturer in "&$E1002&CHOOSE($Q1002," | Sakshi Forge"," - ASTM A270 & ASME BPE"," | EP Tube Supplier"," - SS 304/316L EP Tube"," | Sanitary Tube Supply"," - Mill Certified Supply"," | ASME BPE SF1-SF4"," - EP Tube Stockist"))<=65,"Electropolished Pipes Manufacturer in "&$E1002&CHOOSE($Q1002," | Sakshi Forge"," - ASTM A270 & ASME BPE"," | EP Tube Supplier"," - SS 304/316L EP Tube"," | Sanitary Tube Supply"," - Mill Certified Supply"," | ASME BPE SF1-SF4"," - EP Tube Stockist"),"Electropolished Pipes Manufacturer in "&$E1002)) -> Electropolished Pipes Manufacturer in Dubrajpur | AA1002: =IF(LEN($Z1002)>65,"TRIM ("&LEN($Z1002)&")",IF(LEN($Z1002)<35,"SHORT ("&LEN($Z1002)&")","OK ("&LEN($Z1002)&")")) -> OK (47) | AB1002: =IF($AS1002<>"",$AS1002,CHOOSE($R1002,"EP-finished SS 304/316L pipes & tubes for "&$K1002&" plants in "&$E1002&". ASTM A270, ASME BPE SF1-SF4, EN 10204 3.1 MTC. PMI tested.","Electropolished tube supply to "&$I1002&", "&$E1002&". Ra from 0.25 um, SF4 finish, mill test certificate with every lot.","EP stainless tube for "&$K1002&" lines in "&$E1002&". "&$M1002&". ASTM A270 S2, PMI tested, EN 10204 3.1.","Sanitary electropolished pipes in "&$E1002&" for "&$K1002&" plants. ASME BPE SF1-SF4, orbital-weld ready, 3.1 MTC. Mumbai-made.","Manufacturer of electropolished SS 316L tube serving "&$E1002&". "&$M1002&". Ra 0.25-0.5 um, EN 10204 3.1 MTC.",IF(LEN("EP tube and pipe for "&$K1002&" plants around "&$I1002&", "&$E1002&". Made at our Mumbai works to ASTM A270 and ASME BPE SF1-SF4, with 3.1 MTC.")<=160,"EP tube and pipe for "&$K1002&" plants around "&$I1002&", "&$E1002&". Made at our Mumbai works to ASTM A270 and ASME BPE SF1-SF4, with 3.1 MTC.","EP tube and pipe for "&$K1002&" plants around "&$I1002&", "&$E1002&". ASTM A270, ASME BPE SF1-SF4, EN 10204 3.1 MTC."),"Electropolished pipes in "&$E1002&": 304, 304L, 316 and 316L in SF1-SF4. "&$M1002&". Mill certified.")) -> Manufacturer of electropolished SS 316L tube serving Dubrajpur. VERIFY. Ra 0.25-0.5 um, EN 10204 3.1 MTC. | AC1002: =IF($G1002="VERIFY","PENDING RESEARCH",IF(LEN($AB1002)>160,"TRIM ("&LEN($AB1002)&")",IF(LEN($AB1002)<110,"SHORT ("&LEN($AB1002)&")","OK ("&LEN($AB1002)&")"))) -> PENDING RESEARCH | AD1002: ="Electropolished Pipes Manufacturer in "&$E1002 -> Electropolished Pipes Manufacturer in Dubrajpur | AE1002: =CHOOSE($S1002,"Electropolished Pipe & Tube Manufacturing for "&$E1002&" - Grades, Finishes & Certification","How We Manufacture Electropolished Tube for "&$E1002&" Plants","Electropolished Pipes Manufacturer in "&$E1002&" - Our Process & Capability","Manufacturing Electropolished SS Tube for "&$E1002&": The Standards We Build To","Electropolished Tube Manufacturing Capability Serving "&$E1002) -> Manufacturing Electropolished SS Tube for Dubrajpur: The Standards We Build To | AF1002: =CHOOSE($S1002,"Electropolished Pipes Supplier in "&$E1002&" - Stock Sizes, Lead Time & Delivery","Supplying Electropolished Pipes in "&$E1002&": Availability, Sizes & Dispatch","Electropolished Pipes Supplier in "&$E1002&" - What We Hold in Stock","Electropolished Pipe Supply Into "&$E1002&" - Certification & Transit","Electropolished Pipes Supplier in "&$E1002&" - From Order to Delivery") -> Electropolished Pipe Supply Into Dubrajpur - Certification & Transit | AG1002: =CHOOSE($S1002,"Electropolished Pipes Wholesaler & Stockist in "&$E1002&" - Bulk & Project Pricing","Wholesale Electropolished Pipe Supply for "&$E1002&" Projects","Bulk & Wholesale Electropolished Pipe Rates for "&$E1002&" Buyers","Electropolished Pipes Wholesaler in "&$E1002&" - Project Quantities & Terms","Stockist & Wholesale Supply of Electropolished Pipes in "&$E1002) -> Electropolished Pipes Wholesaler in Dubrajpur - Project Quantities & Terms | AH1002: ="electropolished pipes manufacturer in "&$D1002&", electropolished pipes supplier in "&$D1002&", electropolished pipes wholesaler in "&$D1002&", electropolished tube manufacturer "&$D1002&", EP pipe supplier "&$D1002&", sanitary tube supplier "&$D1002&", ASME BPE tubing "&$D1002&", ASTM A270 tube "&$D1002&", SS 316L electropolished pipe "&$D1002 -> electropolished pipes manufacturer in Dubrajpur, electropolished pipes supplier in Dubrajpur, electropolished pipes wholesaler in Dubrajpur, electropolished tube manufacturer Dubrajpur, EP pipe supplier Dubrajpur, sanitary tube supplier Dubrajpur, ASME BPE tubing Dubrajpur, ASTM A270 tube Dubrajpur, SS 316L electropolished pipe Dubrajpur | AI1002: ="Electropolished Pipes Manufacturer & Supplier in "&$E1002 -> Electropolished Pipes Manufacturer & Supplier in Dubrajpur | AJ1002: ="EP-finished SS 304/316L pipes and tubes for "&$K1002&" plants in "&$E1002&". ASME BPE SF1-SF4, Ra from 0.25 um, EN 10204 3.1 certificate with every lot." -> EP-finished SS 304/316L pipes and tubes for VERIFY plants in Dubrajpur. ASME BPE SF1-SF4, Ra from 0.25 um, EN 10204 3.1 certificate with every lot. | AK1002: ="Electropolished stainless steel pipes supplied by Sakshi Forge to "&$K1002&" plants at "&$I1002&", "&$E1002 -> Electropolished stainless steel pipes supplied by Sakshi Forge to VERIFY plants at WBIDC Industrial Area, Dubrajpur | AL1002: ="Electropolished SS 316L tube stock for "&$E1002&" - Sakshi Forge" -> Electropolished SS 316L tube stock for Dubrajpur - Sakshi Forge | AM1002: ="Home > Market Area > "&$B1002&" > "&$C1002&" > "&$D1002 -> Home > Market Area > India > West Bengal > Dubrajpur | AN1002: =IF($F1002="A",1400,IF($F1002="B",1000,750)) -> 750 | AO1002: =IF($F1002="A",10,IF($F1002="B",8,6)) -> 6 | AP1002: =IF($F1002="A",12,IF($F1002="B",8,6)) -> 6 | AQ1002: =ROUNDUP((ROW()-3)/60,0) -> 17 | AT1002: Not started
A1003: CTY-1000 | B1003: India | C1003: Rajasthan | D1003: Dudu | E1003: Dudu | F1003: C | G1003: VERIFY | H1003: RIICO Industrial Area, Dudu | I1003: RIICO Industrial Area | J1003: VERIFY | K1003: VERIFY | L1003: VERIFY | M1003: VERIFY | N1003: VERIFY | O1003: VERIFY | P1003: =IF($K1003="VERIFY","VERIFY",IF(ISNUMBER(SEARCH("semicon",$K1003)),"SEMI",IF(ISNUMBER(SEARCH("electronic",$K1003)),"SEMI",IF(ISNUMBER(SEARCH("biotech",$K1003)),"BIOTECH",IF(ISNUMBER(SEARCH("pharma",$K1003)),"PHARMA",IF(ISNUMBER(SEARCH("medical",$K1003)),"PHARMA",IF(ISNUMBER(SEARCH("dairy",$K1003)),"DAIRY",IF(ISNUMBER(SEARCH("brewery",$K1003)),"BREWERY",IF(ISNUMBER(SEARCH("food",$K1003)),"FOOD",IF(ISNUMBER(SEARCH("personal care",$K1003)),"FOOD",IF(ISNUMBER(SEARCH("chemical",$K1003)),"CHEM",IF(ISNUMBER(SEARCH("refining",$K1003)),"CHEM",IF(ISNUMBER(SEARCH("petrochem",$K1003)),"CHEM",IF(ISNUMBER(SEARCH("fertilis",$K1003)),"CHEM",IF(ISNUMBER(SEARCH("water",$K1003)),"CHEM","GENERAL"))))))))))))))) -> VERIFY | Q1003: =MOD(ROW()-4,8)+1 -> 8 | R1003: =MOD(ROW()-4,7)+1 -> 6 | S1003: =MOD(ROW()-4,5)+1 -> 5 | T1003: =$F1003&"-"&(MOD(ROW()-4,6)+1) -> C-4 | U1003: ="T"&$Q1003&"-M"&$R1003&"-H"&$S1003&"-F"&$T1003&"-"&$P1003 -> T8-M6-H5-FC-4-VERIFY | V1003: =COUNTIF($U$4:$U$1835,$U1003)-1 -> 0 | X1003: =IF($W1003<>"",$W1003,IF($B1003="India",LOWER(SUBSTITUTE(SUBSTITUTE($D1003," ","-"),".","")),LOWER(SUBSTITUTE(SUBSTITUTE($D1003," ","-"),".",""))&"-"&LOWER(SUBSTITUTE($B1003," ","-")))) -> dudu | Y1003: ="https://steelmanufacturer.in/market-area/electropolished-pipes-manufacturer-in-"&$X1003&"/" -> https://steelmanufacturer.in/market-area/electropolished-pipes-manufacturer-in-dudu/ | Z1003: =IF($AR1003<>"",$AR1003,IF(LEN("Electropolished Pipes Manufacturer in "&$E1003&CHOOSE($Q1003," | Sakshi Forge"," - ASTM A270 & ASME BPE"," | EP Tube Supplier"," - SS 304/316L EP Tube"," | Sanitary Tube Supply"," - Mill Certified Supply"," | ASME BPE SF1-SF4"," - EP Tube Stockist"))<=65,"Electropolished Pipes Manufacturer in "&$E1003&CHOOSE($Q1003," | Sakshi Forge"," - ASTM A270 & ASME BPE"," | EP Tube Supplier"," - SS 304/316L EP Tube"," | Sanitary Tube Supply"," - Mill Certified Supply"," | ASME BPE SF1-SF4"," - EP Tube Stockist"),"Electropolished Pipes Manufacturer in "&$E1003)) -> Electropolished Pipes Manufacturer in Dudu - EP Tube Stockist | AA1003: =IF(LEN($Z1003)>65,"TRIM ("&LEN($Z1003)&")",IF(LEN($Z1003)<35,"SHORT ("&LEN($Z1003)&")","OK ("&LEN($Z1003)&")")) -> OK (61) | AB1003: =IF($AS1003<>"",$AS1003,CHOOSE($R1003,"EP-finished SS 304/316L pipes & tubes for "&$K1003&" plants in "&$E1003&". ASTM A270, ASME BPE SF1-SF4, EN 10204 3.1 MTC. PMI tested.","Electropolished tube supply to "&$I1003&", "&$E1003&". Ra from 0.25 um, SF4 finish, mill test certificate with every lot.","EP stainless tube for "&$K1003&" lines in "&$E1003&". "&$M1003&". ASTM A270 S2, PMI tested, EN 10204 3.1.","Sanitary electropolished pipes in "&$E1003&" for "&$K1003&" plants. ASME BPE SF1-SF4, orbital-weld ready, 3.1 MTC. Mumbai-made.","Manufacturer of electropolished SS 316L tube serving "&$E1003&". "&$M1003&". Ra 0.25-0.5 um, EN 10204 3.1 MTC.",IF(LEN("EP tube and pipe for "&$K1003&" plants around "&$I1003&", "&$E1003&". Made at our Mumbai works to ASTM A270 and ASME BPE SF1-SF4, with 3.1 MTC.")<=160,"EP tube and pipe for "&$K1003&" plants around "&$I1003&", "&$E1003&". Made at our Mumbai works to ASTM A270 and ASME BPE SF1-SF4, with 3.1 MTC.","EP tube and pipe for "&$K1003&" plants around "&$I1003&", "&$E1003&". ASTM A270, ASME BPE SF1-SF4, EN 10204 3.1 MTC."),"Electropolished pipes in "&$E1003&": 304, 304L, 316 and 316L in SF1-SF4. "&$M1003&". Mill certified.")) -> EP tube and pipe for VERIFY plants around RIICO Industrial Area, Dudu. Made at our Mumbai works to ASTM A270 and ASME BPE SF1-SF4, with 3.1 MTC. | AC1003: =IF($G1003="VERIFY","PENDING RESEARCH",IF(LEN($AB1003)>160,"TRIM ("&LEN($AB1003)&")",IF(LEN($AB1003)<110,"SHORT ("&LEN($AB1003)&")","OK ("&LEN($AB1003)&")"))) -> PENDING RESEARCH | AD1003: ="Electropolished Pipes Manufacturer in "&$E1003 -> Electropolished Pipes Manufacturer in Dudu | AE1003: =CHOOSE($S1003,"Electropolished Pipe & Tube Manufacturing for "&$E1003&" - Grades, Finishes & Certification","How We Manufacture Electropolished Tube for "&$E1003&" Plants","Electropolished Pipes Manufacturer in "&$E1003&" - Our Process & Capability","Manufacturing Electropolished SS Tube for "&$E1003&": The Standards We Build To","Electropolished Tube Manufacturing Capability Serving "&$E1003) -> Electropolished Tube Manufacturing Capability Serving Dudu | AF1003: =CHOOSE($S1003,"Electropolished Pipes Supplier in "&$E1003&" - Stock Sizes, Lead Time & Delivery","Supplying Electropolished Pipes in "&$E1003&": Availability, Sizes & Dispatch","Electropolished Pipes Supplier in "&$E1003&" - What We Hold in Stock","Electropolished Pipe Supply Into "&$E1003&" - Certification & Transit","Electropolished Pipes Supplier in "&$E1003&" - From Order to Delivery") -> Electropolished Pipes Supplier in Dudu - From Order to Delivery | AG1003: =CHOOSE($S1003,"Electropolished Pipes Wholesaler & Stockist in "&$E1003&" - Bulk & Project Pricing","Wholesale Electropolished Pipe Supply for "&$E1003&" Projects","Bulk & Wholesale Electropolished Pipe Rates for "&$E1003&" Buyers","Electropolished Pipes Wholesaler in "&$E1003&" - Project Quantities & Terms","Stockist & Wholesale Supply of Electropolished Pipes in "&$E1003) -> Stockist & Wholesale Supply of Electropolished Pipes in Dudu | AH1003: ="electropolished pipes manufacturer in "&$D1003&", electropolished pipes supplier in "&$D1003&", electropolished pipes wholesaler in "&$D1003&", electropolished tube manufacturer "&$D1003&", EP pipe supplier "&$D1003&", sanitary tube supplier "&$D1003&", ASME BPE tubing "&$D1003&", ASTM A270 tube "&$D1003&", SS 316L electropolished pipe "&$D1003 -> electropolished pipes manufacturer in Dudu, electropolished pipes supplier in Dudu, electropolished pipes wholesaler in Dudu, electropolished tube manufacturer Dudu, EP pipe supplier Dudu, sanitary tube supplier Dudu, ASME BPE tubing Dudu, ASTM A270 tube Dudu, SS 316L electropolished pipe Dudu | AI1003: ="Electropolished Pipes Manufacturer & Supplier in "&$E1003 -> Electropolished Pipes Manufacturer & Supplier in Dudu | AJ1003: ="EP-finished SS 304/316L pipes and tubes for "&$K1003&" plants in "&$E1003&". ASME BPE SF1-SF4, Ra from 0.25 um, EN 10204 3.1 certificate with every lot." -> EP-finished SS 304/316L pipes and tubes for VERIFY plants in Dudu. ASME BPE SF1-SF4, Ra from 0.25 um, EN 10204 3.1 certificate with every lot. | AK1003: ="Electropolished stainless steel pipes supplied by Sakshi Forge to "&$K1003&" plants at "&$I1003&", "&$E1003 -> Electropolished stainless steel pipes supplied by Sakshi Forge to VERIFY plants at RIICO Industrial Area, Dudu | AL1003: ="Electropolished SS 316L tube stock for "&$E1003&" - Sakshi Forge" -> Electropolished SS 316L tube stock for Dudu - Sakshi Forge | AM1003: ="Home > Market Area > "&$B1003&" > "&$C1003&" > "&$D1003 -> Home > Market Area > India > Rajasthan > Dudu | AN1003: =IF($F1003="A",1400,IF($F1003="B",1000,750)) -> 750 | AO1003: =IF($F1003="A",10,IF($F1003="B",8,6)) -> 6 | AP1003: =IF($F1003="A",12,IF($F1003="B",8,6)) -> 6 | AQ1003: =ROUNDUP((ROW()-3)/60,0) -> 17 | AT1003: Not started
A1004: CTY-1001 | B1004: India | C1004: Haryana | D1004: Ellenabad | E1004: Ellenabad | F1004: C | G1004: VERIFY | H1004: HSIIDC Industrial Area, Ellenabad | I1004: HSIIDC Industrial Area | J1004: VERIFY | K1004: VERIFY | L1004: VERIFY | M1004: VERIFY | N1004: VERIFY | O1004: VERIFY | P1004: =IF($K1004="VERIFY","VERIFY",IF(ISNUMBER(SEARCH("semicon",$K1004)),"SEMI",IF(ISNUMBER(SEARCH("electronic",$K1004)),"SEMI",IF(ISNUMBER(SEARCH("biotech",$K1004)),"BIOTECH",IF(ISNUMBER(SEARCH("pharma",$K1004)),"PHARMA",IF(ISNUMBER(SEARCH("medical",$K1004)),"PHARMA",IF(ISNUMBER(SEARCH("dairy",$K1004)),"DAIRY",IF(ISNUMBER(SEARCH("brewery",$K1004)),"BREWERY",IF(ISNUMBER(SEARCH("food",$K1004)),"FOOD",IF(ISNUMBER(SEARCH("personal care",$K1004)),"FOOD",IF(ISNUMBER(SEARCH("chemical",$K1004)),"CHEM",IF(ISNUMBER(SEARCH("refining",$K1004)),"CHEM",IF(ISNUMBER(SEARCH("petrochem",$K1004)),"CHEM",IF(ISNUMBER(SEARCH("fertilis",$K1004)),"CHEM",IF(ISNUMBER(SEARCH("water",$K1004)),"CHEM","GENERAL"))))))))))))))) -> VERIFY | Q1004: =MOD(ROW()-4,8)+1 -> 1 | R1004: =MOD(ROW()-4,7)+1 -> 7 | S1004: =MOD(ROW()-4,5)+1 -> 1 | T1004: =$F1004&"-"&(MOD(ROW()-4,6)+1) -> C-5 | U1004: ="T"&$Q1004&"-M"&$R1004&"-H"&$S1004&"-F"&$T1004&"-"&$P1004 -> T1-M7-H1-FC-5-VERIFY | V1004: =COUNTIF($U$4:$U$1835,$U1004)-1 -> 0 | X1004: =IF($W1004<>"",$W1004,IF($B1004="India",LOWER(SUBSTITUTE(SUBSTITUTE($D1004," ","-"),".","")),LOWER(SUBSTITUTE(SUBSTITUTE($D1004," ","-"),".",""))&"-"&LOWER(SUBSTITUTE($B1004," ","-")))) -> ellenabad | Y1004: ="https://steelmanufacturer.in/market-area/electropolished-pipes-manufacturer-in-"&$X1004&"/" -> https://steelmanufacturer.in/market-area/electropolished-pipes-manufacturer-in-ellenabad/ | Z1004: =IF($AR1004<>"",$AR1004,IF(LEN("Electropolished Pipes Manufacturer in "&$E1004&CHOOSE($Q1004," | Sakshi Forge"," - ASTM A270 & ASME BPE"," | EP Tube Supplier"," - SS 304/316L EP Tube"," | Sanitary Tube Supply"," - Mill Certified Supply"," | ASME BPE SF1-SF4"," - EP Tube Stockist"))<=65,"Electropolished Pipes Manufacturer in "&$E1004&CHOOSE($Q1004," | Sakshi Forge"," - ASTM A270 & ASME BPE"," | EP Tube Supplier"," - SS 304/316L EP Tube"," | Sanitary Tube Supply"," - Mill Certified Supply"," | ASME BPE SF1-SF4"," - EP Tube Stockist"),"Electropolished Pipes Manufacturer in "&$E1004)) -> Electropolished Pipes Manufacturer in Ellenabad | Sakshi Forge | AA1004: =IF(LEN($Z1004)>65,"TRIM ("&LEN($Z1004)&")",IF(LEN($Z1004)<35,"SHORT ("&LEN($Z1004)&")","OK ("&LEN($Z1004)&")")) -> OK (62) | AB1004: =IF($AS1004<>"",$AS1004,CHOOSE($R1004,"EP-finished SS 304/316L pipes & tubes for "&$K1004&" plants in "&$E1004&". ASTM A270, ASME BPE SF1-SF4, EN 10204 3.1 MTC. PMI tested.","Electropolished tube supply to "&$I1004&", "&$E1004&". Ra from 0.25 um, SF4 finish, mill test certificate with every lot.","EP stainless tube for "&$K1004&" lines in "&$E1004&". "&$M1004&". ASTM A270 S2, PMI tested, EN 10204 3.1.","Sanitary electropolished pipes in "&$E1004&" for "&$K1004&" plants. ASME BPE SF1-SF4, orbital-weld ready, 3.1 MTC. Mumbai-made.","Manufacturer of electropolished SS 316L tube serving "&$E1004&". "&$M1004&". Ra 0.25-0.5 um, EN 10204 3.1 MTC.",IF(LEN("EP tube and pipe for "&$K1004&" plants around "&$I1004&", "&$E1004&". Made at our Mumbai works to ASTM A270 and ASME BPE SF1-SF4, with 3.1 MTC.")<=160,"EP tube and pipe for "&$K1004&" plants around "&$I1004&", "&$E1004&". Made at our Mumbai works to ASTM A270 and ASME BPE SF1-SF4, with 3.1 MTC.","EP tube and pipe for "&$K1004&" plants around "&$I1004&", "&$E1004&". ASTM A270, ASME BPE SF1-SF4, EN 10204 3.1 MTC."),"Electropolished pipes in "&$E1004&": 304, 304L, 316 and 316L in SF1-SF4. "&$M1004&". Mill certified.")) -> Electropolished pipes in Ellenabad: 304, 304L, 316 and 316L in SF1-SF4. VERIFY. Mill certified. | AC1004: =IF($G1004="VERIFY","PENDING RESEARCH",IF(LEN($AB1004)>160,"TRIM ("&LEN($AB1004)&")",IF(LEN($AB1004)<110,"SHORT ("&LEN($AB1004)&")","OK ("&LEN($AB1004)&")"))) -> PENDING RESEARCH | AD1004: ="Electropolished Pipes Manufacturer in "&$E1004 -> Electropolished Pipes Manufacturer in Ellenabad | AE1004: =CHOOSE($S1004,"Electropolished Pipe & Tube Manufacturing for "&$E1004&" - Grades, Finishes & Certification","How We Manufacture Electropolished Tube for "&$E1004&" Plants","Electropolished Pipes Manufacturer in "&$E1004&" - Our Process & Capability","Manufacturing Electropolished SS Tube for "&$E1004&": The Standards We Build To","Electropolished Tube Manufacturing Capability Serving "&$E1004) -> Electropolished Pipe & Tube Manufacturing for Ellenabad - Grades, Finishes & Certification | AF1004: =CHOOSE($S1004,"Electropolished Pipes Supplier in "&$E1004&" - Stock Sizes, Lead Time & Delivery","Supplying Electropolished Pipes in "&$E1004&": Availability, Sizes & Dispatch","Electropolished Pipes Supplier in "&$E1004&" - What We Hold in Stock","Electropolished Pipe Supply Into "&$E1004&" - Certification & Transit","Electropolished Pipes Supplier in "&$E1004&" - From Order to Delivery") -> Electropolished Pipes Supplier in Ellenabad - Stock Sizes, Lead Time & Delivery | AG1004: =CHOOSE($S1004,"Electropolished Pipes Wholesaler & Stockist in "&$E1004&" - Bulk & Project Pricing","Wholesale Electropolished Pipe Supply for "&$E1004&" Projects","Bulk & Wholesale Electropolished Pipe Rates for "&$E1004&" Buyers","Electropolished Pipes Wholesaler in "&$E1004&" - Project Quantities & Terms","Stockist & Wholesale Supply of Electropolished Pipes in "&$E1004) -> Electropolished Pipes Wholesaler & Stockist in Ellenabad - Bulk & Project Pricing | AH1004: ="electropolished pipes manufacturer in "&$D1004&", electropolished pipes supplier in "&$D1004&", electropolished pipes wholesaler in "&$D1004&", electropolished tube manufacturer "&$D1004&", EP pipe supplier "&$D1004&", sanitary tube supplier "&$D1004&", ASME BPE tubing "&$D1004&", ASTM A270 tube "&$D1004&", SS 316L electropolished pipe "&$D1004 -> electropolished pipes manufacturer in Ellenabad, electropolished pipes supplier in Ellenabad, electropolished pipes wholesaler in Ellenabad, electropolished tube manufacturer Ellenabad, EP pipe supplier Ellenabad, sanitary tube supplier Ellenabad, ASME BPE tubing Ellenabad, ASTM A270 tube Ellenabad, SS 316L electropolished pipe Ellenabad | AI1004: ="Electropolished Pipes Manufacturer & Supplier in "&$E1004 -> Electropolished Pipes Manufacturer & Supplier in Ellenabad | AJ1004: ="EP-finished SS 304/316L pipes and tubes for "&$K1004&" plants in "&$E1004&". ASME BPE SF1-SF4, Ra from 0.25 um, EN 10204 3.1 certificate with every lot." -> EP-finished SS 304/316L pipes and tubes for VERIFY plants in Ellenabad. ASME BPE SF1-SF4, Ra from 0.25 um, EN 10204 3.1 certificate with every lot. | AK1004: ="Electropolished stainless steel pipes supplied by Sakshi Forge to "&$K1004&" plants at "&$I1004&", "&$E1004 -> Electropolished stainless steel pipes supplied by Sakshi Forge to VERIFY plants at HSIIDC Industrial Area, Ellenabad | AL1004: ="Electropolished SS 316L tube stock for "&$E1004&" - Sakshi Forge" -> Electropolished SS 316L tube stock for Ellenabad - Sakshi Forge | AM1004: ="Home > Market Area > "&$B1004&" > "&$C1004&" > "&$D1004 -> Home > Market Area > India > Haryana > Ellenabad | AN1004: =IF($F1004="A",1400,IF($F1004="B",1000,750)) -> 750 | AO1004: =IF($F1004="A",10,IF($F1004="B",8,6)) -> 6 | AP1004: =IF($F1004="A",12,IF($F1004="B",8,6)) -> 6 | AQ1004: =ROUNDUP((ROW()-3)/60,0) -> 17 | AT1004: Not started
A1005: CTY-1002 | B1005: India | C1005: Uttar Pradesh | D1005: Etah | E1005: Etah | F1005: C | G1005: VERIFY | H1005: UPSIDA Industrial Area, Etah | I1005: UPSIDA Industrial Area | J1005: VERIFY | K1005: VERIFY | L1005: VERIFY | M1005: VERIFY | N1005: VERIFY | O1005: VERIFY | P1005: =IF($K1005="VERIFY","VERIFY",IF(ISNUMBER(SEARCH("semicon",$K1005)),"SEMI",IF(ISNUMBER(SEARCH("electronic",$K1005)),"SEMI",IF(ISNUMBER(SEARCH("biotech",$K1005)),"BIOTECH",IF(ISNUMBER(SEARCH("pharma",$K1005)),"PHARMA",IF(ISNUMBER(SEARCH("medical",$K1005)),"PHARMA",IF(ISNUMBER(SEARCH("dairy",$K1005)),"DAIRY",IF(ISNUMBER(SEARCH("brewery",$K1005)),"BREWERY",IF(ISNUMBER(SEARCH("food",$K1005)),"FOOD",IF(ISNUMBER(SEARCH("personal care",$K1005)),"FOOD",IF(ISNUMBER(SEARCH("chemical",$K1005)),"CHEM",IF(ISNUMBER(SEARCH("refining",$K1005)),"CHEM",IF(ISNUMBER(SEARCH("petrochem",$K1005)),"CHEM",IF(ISNUMBER(SEARCH("fertilis",$K1005)),"CHEM",IF(ISNUMBER(SEARCH("water",$K1005)),"CHEM","GENERAL"))))))))))))))) -> VERIFY | Q1005: =MOD(ROW()-4,8)+1 -> 2 | R1005: =MOD(ROW()-4,7)+1 -> 1 | S1005: =MOD(ROW()-4,5)+1 -> 2 | T1005: =$F1005&"-"&(MOD(ROW()-4,6)+1) -> C-6 | U1005: ="T"&$Q1005&"-M"&$R1005&"-H"&$S1005&"-F"&$T1005&"-"&$P1005 -> T2-M1-H2-FC-6-VERIFY | V1005: =COUNTIF($U$4:$U$1835,$U1005)-1 -> 0 | X1005: =IF($W1005<>"",$W1005,IF($B1005="India",LOWER(SUBSTITUTE(SUBSTITUTE($D1005," ","-"),".","")),LOWER(SUBSTITUTE(SUBSTITUTE($D1005," ","-"),".",""))&"-"&LOWER(SUBSTITUTE($B1005," ","-")))) -> etah | Y1005: ="https://steelmanufacturer.in/market-area/electropolished-pipes-manufacturer-in-"&$X1005&"/" -> https://steelmanufacturer.in/market-area/electropolished-pipes-manufacturer-in-etah/ | Z1005: =IF($AR1005<>"",$AR1005,IF(LEN("Electropolished Pipes Manufacturer in "&$E1005&CHOOSE($Q1005," | Sakshi Forge"," - ASTM A270 & ASME BPE"," | EP Tube Supplier"," - SS 304/316L EP Tube"," | Sanitary Tube Supply"," - Mill Certified Supply"," | ASME BPE SF1-SF4"," - EP Tube Stockist"))<=65,"Electropolished Pipes Manufacturer in "&$E1005&CHOOSE($Q1005," | Sakshi Forge"," - ASTM A270 & ASME BPE"," | EP Tube Supplier"," - SS 304/316L EP Tube"," | Sanitary Tube Supply"," - Mill Certified Supply"," | ASME BPE SF1-SF4"," - EP Tube Stockist"),"Electropolished Pipes Manufacturer in "&$E1005)) -> Electropolished Pipes Manufacturer in Etah - ASTM A270 & ASME BPE | AA1005: =IF(LEN($Z1005)>65,"TRIM ("&LEN($Z1005)&")",IF(LEN($Z1005)<35,"SHORT ("&LEN($Z1005)&")","OK ("&LEN($Z1005)&")")) -> OK (65) | AB1005: =IF($AS1005<>"",$AS1005,CHOOSE($R1005,"EP-finished SS 304/316L pipes & tubes for "&$K1005&" plants in "&$E1005&". ASTM A270, ASME BPE SF1-SF4, EN 10204 3.1 MTC. PMI tested.","Electropolished tube supply to "&$I1005&", "&$E1005&". Ra from 0.25 um, SF4 finish, mill test certificate with every lot.","EP stainless tube for "&$K1005&" lines in "&$E1005&". "&$M1005&". ASTM A270 S2, PMI tested, EN 10204 3.1.","Sanitary electropolished pipes in "&$E1005&" for "&$K1005&" plants. ASME BPE SF1-SF4, orbital-weld ready, 3.1 MTC. Mumbai-made.","Manufacturer of electropolished SS 316L tube serving "&$E1005&". "&$M1005&". Ra 0.25-0.5 um, EN 10204 3.1 MTC.",IF(LEN("EP tube and pipe for "&$K1005&" plants around "&$I1005&", "&$E1005&". Made at our Mumbai works to ASTM A270 and ASME BPE SF1-SF4, with 3.1 MTC.")<=160,"EP tube and pipe for "&$K1005&" plants around "&$I1005&", "&$E1005&". Made at our Mumbai works to ASTM A270 and ASME BPE SF1-SF4, with 3.1 MTC.","EP tube and pipe for "&$K1005&" plants around "&$I1005&", "&$E1005&". ASTM A270, ASME BPE SF1-SF4, EN 10204 3.1 MTC."),"Electropolished pipes in "&$E1005&": 304, 304L, 316 and 316L in SF1-SF4. "&$M1005&". Mill certified.")) -> EP-finished SS 304/316L pipes & tubes for VERIFY plants in Etah. ASTM A270, ASME BPE SF1-SF4, EN 10204 3.1 MTC. PMI tested. | AC1005: =IF($G1005="VERIFY","PENDING RESEARCH",IF(LEN($AB1005)>160,"TRIM ("&LEN($AB1005)&")",IF(LEN($AB1005)<110,"SHORT ("&LEN($AB1005)&")","OK ("&LEN($AB1005)&")"))) -> PENDING RESEARCH | AD1005: ="Electropolished Pipes Manufacturer in "&$E1005 -> Electropolished Pipes Manufacturer in Etah | AE1005: =CHOOSE($S1005,"Electropolished Pipe & Tube Manufacturing for "&$E1005&" - Grades, Finishes & Certification","How We Manufacture Electropolished Tube for "&$E1005&" Plants","Electropolished Pipes Manufacturer in "&$E1005&" - Our Process & Capability","Manufacturing Electropolished SS Tube for "&$E1005&": The Standards We Build To","Electropolished Tube Manufacturing Capability Serving "&$E1005) -> How We Manufacture Electropolished Tube for Etah Plants | AF1005: =CHOOSE($S1005,"Electropolished Pipes Supplier in "&$E1005&" - Stock Sizes, Lead Time & Delivery","Supplying Electropolished Pipes in "&$E1005&": Availability, Sizes & Dispatch","Electropolished Pipes Supplier in "&$E1005&" - What We Hold in Stock","Electropolished Pipe Supply Into "&$E1005&" - Certification & Transit","Electropolished Pipes Supplier in "&$E1005&" - From Order to Delivery") -> Supplying Electropolished Pipes in Etah: Availability, Sizes & Dispatch | AG1005: =CHOOSE($S1005,"Electropolished Pipes Wholesaler & Stockist in "&$E1005&" - Bulk & Project Pricing","Wholesale Electropolished Pipe Supply for "&$E1005&" Projects","Bulk & Wholesale Electropolished Pipe Rates for "&$E1005&" Buyers","Electropolished Pipes Wholesaler in "&$E1005&" - Project Quantities & Terms","Stockist & Wholesale Supply of Electropolished Pipes in "&$E1005) -> Wholesale Electropolished Pipe Supply for Etah Projects | AH1005: ="electropolished pipes manufacturer in "&$D1005&", electropolished pipes supplier in "&$D1005&", electropolished pipes wholesaler in "&$D1005&", electropolished tube manufacturer "&$D1005&", EP pipe supplier "&$D1005&", sanitary tube supplier "&$D1005&", ASME BPE tubing "&$D1005&", ASTM A270 tube "&$D1005&", SS 316L electropolished pipe "&$D1005 -> electropolished pipes manufacturer in Etah, electropolished pipes supplier in Etah, electropolished pipes wholesaler in Etah, electropolished tube manufacturer Etah, EP pipe supplier Etah, sanitary tube supplier Etah, ASME BPE tubing Etah, ASTM A270 tube Etah, SS 316L electropolished pipe Etah | AI1005: ="Electropolished Pipes Manufacturer & Supplier in "&$E1005 -> Electropolished Pipes Manufacturer & Supplier in Etah | AJ1005: ="EP-finished SS 304/316L pipes and tubes for "&$K1005&" plants in "&$E1005&". ASME BPE SF1-SF4, Ra from 0.25 um, EN 10204 3.1 certificate with every lot." -> EP-finished SS 304/316L pipes and tubes for VERIFY plants in Etah. ASME BPE SF1-SF4, Ra from 0.25 um, EN 10204 3.1 certificate with every lot. | AK1005: ="Electropolished stainless steel pipes supplied by Sakshi Forge to "&$K1005&" plants at "&$I1005&", "&$E1005 -> Electropolished stainless steel pipes supplied by Sakshi Forge to VERIFY plants at UPSIDA Industrial Area, Etah | AL1005: ="Electropolished SS 316L tube stock for "&$E1005&" - Sakshi Forge" -> Electropolished SS 316L tube stock for Etah - Sakshi Forge | AM1005: ="Home > Market Area > "&$B1005&" > "&$C1005&" > "&$D1005 -> Home > Market Area > India > Uttar Pradesh > Etah | AN1005: =IF($F1005="A",1400,IF($F1005="B",1000,750)) -> 750 | AO1005: =IF($F1005="A",10,IF($F1005="B",8,6)) -> 6 | AP1005: =IF($F1005="A",12,IF($F1005="B",8,6)) -> 6 | AQ1005: =ROUNDUP((ROW()-3)/60,0) -> 17 | AT1005: Not started
A1006: CTY-1003 | B1006: India | C1006: Andhra Pradesh | D1006: Etcherla | E1006: Etcherla | F1006: C | G1006: VERIFY | H1006: APIIC Industrial Area, Etcherla | I1006: APIIC Industrial Area | J1006: VERIFY | K1006: VERIFY | L1006: VERIFY | M1006: VERIFY | N1006: VERIFY | O1006: VERIFY | P1006: =IF($K1006="VERIFY","VERIFY",IF(ISNUMBER(SEARCH("semicon",$K1006)),"SEMI",IF(ISNUMBER(SEARCH("electronic",$K1006)),"SEMI",IF(ISNUMBER(SEARCH("biotech",$K1006)),"BIOTECH",IF(ISNUMBER(SEARCH("pharma",$K1006)),"PHARMA",IF(ISNUMBER(SEARCH("medical",$K1006)),"PHARMA",IF(ISNUMBER(SEARCH("dairy",$K1006)),"DAIRY",IF(ISNUMBER(SEARCH("brewery",$K1006)),"BREWERY",IF(ISNUMBER(SEARCH("food",$K1006)),"FOOD",IF(ISNUMBER(SEARCH("personal care",$K1006)),"FOOD",IF(ISNUMBER(SEARCH("chemical",$K1006)),"CHEM",IF(ISNUMBER(SEARCH("refining",$K1006)),"CHEM",IF(ISNUMBER(SEARCH("petrochem",$K1006)),"CHEM",IF(ISNUMBER(SEARCH("fertilis",$K1006)),"CHEM",IF(ISNUMBER(SEARCH("water",$K1006)),"CHEM","GENERAL"))))))))))))))) -> VERIFY | Q1006: =MOD(ROW()-4,8)+1 -> 3 | R1006: =MOD(ROW()-4,7)+1 -> 2 | S1006: =MOD(ROW()-4,5)+1 -> 3 | T1006: =$F1006&"-"&(MOD(ROW()-4,6)+1) -> C-1 | U1006: ="T"&$Q1006&"-M"&$R1006&"-H"&$S1006&"-F"&$T1006&"-"&$P1006 -> T3-M2-H3-FC-1-VERIFY | V1006: =COUNTIF($U$4:$U$1835,$U1006)-1 -> 0 | X1006: =IF($W1006<>"",$W1006,IF($B1006="India",LOWER(SUBSTITUTE(SUBSTITUTE($D1006," ","-"),".","")),LOWER(SUBSTITUTE(SUBSTITUTE($D1006," ","-"),".",""))&"-"&LOWER(SUBSTITUTE($B1006," ","-")))) -> etcherla | Y1006: ="https://steelmanufacturer.in/market-area/electropolished-pipes-manufacturer-in-"&$X1006&"/" -> https://steelmanufacturer.in/market-area/electropolished-pipes-manufacturer-in-etcherla/ | Z1006: =IF($AR1006<>"",$AR1006,IF(LEN("Electropolished Pipes Manufacturer in "&$E1006&CHOOSE($Q1006," | Sakshi Forge"," - ASTM A270 & ASME BPE"," | EP Tube Supplier"," - SS 304/316L EP Tube"," | Sanitary Tube Supply"," - Mill Certified Supply"," | ASME BPE SF1-SF4"," - EP Tube Stockist"))<=65,"Electropolished Pipes Manufacturer in "&$E1006&CHOOSE($Q1006," | Sakshi Forge"," - ASTM A270 & ASME BPE"," | EP Tube Supplier"," - SS 304/316L EP Tube"," | Sanitary Tube Supply"," - Mill Certified Supply"," | ASME BPE SF1-SF4"," - EP Tube Stockist"),"Electropolished Pipes Manufacturer in "&$E1006)) -> Electropolished Pipes Manufacturer in Etcherla | EP Tube Supplier | AA1006: =IF(LEN($Z1006)>65,"TRIM ("&LEN($Z1006)&")",IF(LEN($Z1006)<35,"SHORT ("&LEN($Z1006)&")","OK ("&LEN($Z1006)&")")) -> OK (65) | AB1006: =IF($AS1006<>"",$AS1006,CHOOSE($R1006,"EP-finished SS 304/316L pipes & tubes for "&$K1006&" plants in "&$E1006&". ASTM A270, ASME BPE SF1-SF4, EN 10204 3.1 MTC. PMI tested.","Electropolished tube supply to "&$I1006&", "&$E1006&". Ra from 0.25 um, SF4 finish, mill test certificate with every lot.","EP stainless tube for "&$K1006&" lines in "&$E1006&". "&$M1006&". ASTM A270 S2, PMI tested, EN 10204 3.1.","Sanitary electropolished pipes in "&$E1006&" for "&$K1006&" plants. ASME BPE SF1-SF4, orbital-weld ready, 3.1 MTC. Mumbai-made.","Manufacturer of electropolished SS 316L tube serving "&$E1006&". "&$M1006&". Ra 0.25-0.5 um, EN 10204 3.1 MTC.",IF(LEN("EP tube and pipe for "&$K1006&" plants around "&$I1006&", "&$E1006&". Made at our Mumbai works to ASTM A270 and ASME BPE SF1-SF4, with 3.1 MTC.")<=160,"EP tube and pipe for "&$K1006&" plants around "&$I1006&", "&$E1006&". Made at our Mumbai works to ASTM A270 and ASME BPE SF1-SF4, with 3.1 MTC.","EP tube and pipe for "&$K1006&" plants around "&$I1006&", "&$E1006&". ASTM A270, ASME BPE SF1-SF4, EN 10204 3.1 MTC."),"Electropolished pipes in "&$E1006&": 304, 304L, 316 and 316L in SF1-SF4. "&$M1006&". Mill certified.")) -> Electropolished tube supply to APIIC Industrial Area, Etcherla. Ra from 0.25 um, SF4 finish, mill test certificate with every lot. | AC1006: =IF($G1006="VERIFY","PENDING RESEARCH",IF(LEN($AB1006)>160,"TRIM ("&LEN($AB1006)&")",IF(LEN($AB1006)<110,"SHORT ("&LEN($AB1006)&")","OK ("&LEN($AB1006)&")"))) -> PENDING RESEARCH | AD1006: ="Electropolished Pipes Manufacturer in "&$E1006 -> Electropolished Pipes Manufacturer in Etcherla | AE1006: =CHOOSE($S1006,"Electropolished Pipe & Tube Manufacturing for "&$E1006&" - Grades, Finishes & Certification","How We Manufacture Electropolished Tube for "&$E1006&" Plants","Electropolished Pipes Manufacturer in "&$E1006&" - Our Process & Capability","Manufacturing Electropolished SS Tube for "&$E1006&": The Standards We Build To","Electropolished Tube Manufacturing Capability Serving "&$E1006) -> Electropolished Pipes Manufacturer in Etcherla - Our Process & Capability | AF1006: =CHOOSE($S1006,"Electropolished Pipes Supplier in "&$E1006&" - Stock Sizes, Lead Time & Delivery","Supplying Electropolished Pipes in "&$E1006&": Availability, Sizes & Dispatch","Electropolished Pipes Supplier in "&$E1006&" - What We Hold in Stock","Electropolished Pipe Supply Into "&$E1006&" - Certification & Transit","Electropolished Pipes Supplier in "&$E1006&" - From Order to Delivery") -> Electropolished Pipes Supplier in Etcherla - What We Hold in Stock | AG1006: =CHOOSE($S1006,"Electropolished Pipes Wholesaler & Stockist in "&$E1006&" - Bulk & Project Pricing","Wholesale Electropolished Pipe Supply for "&$E1006&" Projects","Bulk & Wholesale Electropolished Pipe Rates for "&$E1006&" Buyers","Electropolished Pipes Wholesaler in "&$E1006&" - Project Quantities & Terms","Stockist & Wholesale Supply of Electropolished Pipes in "&$E1006) -> Bulk & Wholesale Electropolished Pipe Rates for Etcherla Buyers | AH1006: ="electropolished pipes manufacturer in "&$D1006&", electropolished pipes supplier in "&$D1006&", electropolished pipes wholesaler in "&$D1006&", electropolished tube manufacturer "&$D1006&", EP pipe supplier "&$D1006&", sanitary tube supplier "&$D1006&", ASME BPE tubing "&$D1006&", ASTM A270 tube "&$D1006&", SS 316L electropolished pipe "&$D1006 -> electropolished pipes manufacturer in Etcherla, electropolished pipes supplier in Etcherla, electropolished pipes wholesaler in Etcherla, electropolished tube manufacturer Etcherla, EP pipe supplier Etcherla, sanitary tube supplier Etcherla, ASME BPE tubing Etcherla, ASTM A270 tube Etcherla, SS 316L electropolished pipe Etcherla | AI1006: ="Electropolished Pipes Manufacturer & Supplier in "&$E1006 -> Electropolished Pipes Manufacturer & Supplier in Etcherla | AJ1006: ="EP-finished SS 304/316L pipes and tubes for "&$K1006&" plants in "&$E1006&". ASME BPE SF1-SF4, Ra from 0.25 um, EN 10204 3.1 certificate with every lot." -> EP-finished SS 304/316L pipes and tubes for VERIFY plants in Etcherla. ASME BPE SF1-SF4, Ra from 0.25 um, EN 10204 3.1 certificate with every lot. | AK1006: ="Electropolished stainless steel pipes supplied by Sakshi Forge to "&$K1006&" plants at "&$I1006&", "&$E1006 -> Electropolished stainless steel pipes supplied by Sakshi Forge to VERIFY plants at APIIC Industrial Area, Etcherla | AL1006: ="Electropolished SS 316L tube stock for "&$E1006&" - Sakshi Forge" -> Electropolished SS 316L tube stock for Etcherla - Sakshi Forge | AM1006: ="Home > Market Area > "&$B1006&" > "&$C1006&" > "&$D1006 -> Home > Market Area > India > Andhra Pradesh > Etcherla | AN1006: =IF($F1006="A",1400,IF($F1006="B",1000,750)) -> 750 | AO1006: =IF($F1006="A",10,IF($F1006="B",8,6)) -> 6 | AP1006: =IF($F1006="A",12,IF($F1006="B",8,6)) -> 6 | AQ1006: =ROUNDUP((ROW()-3)/60,0) -> 17 | AT1006: Not started
